Workbook

Sheet Overall Summary
D1: ='Sector_MDAs Summary-Details'!C1 -> Perfomance Delivery Coordination Unit (PDCU), Office of the Executive Governor
A2: January to December 2024 MDA/Sector Summary of Performance on Commitments
A3: S/N | B3: Ministries and Agencies | C3: ='Sector_MDAs Summary-Details'!B3 -> Commitments | D3: ='Sector_MDAs Summary-Details'!C3 -> No. of Outputs | E3: ='Sector_MDAs Summary-Details'!D3 -> No Results to be Delivered | F3: ='Sector_MDAs Summary-Details'!E3 -> Performance for Each Result | G3: ='Sector_MDAs Summary-Details'!F3 -> 0 | H3: ='Sector_MDAs Summary-Details'!G3 -> 0 | I3: ='Sector_MDAs Summary-Details'!H3 -> 0 | J3: ='Sector_MDAs Summary-Details'!I4 -> Below Minimum Expectation | K3: ='Sector_MDAs Summary-Details'!J4 -> Not Assessed | L3: ='Sector_MDAs Summary-Details'!K3 -> Overall Performance | M3: ='Sector_MDAs Summary-Details'!L3 -> 0
A4: 0 | B4: 0 | C4: ='Sector_MDAs Summary-Details'!B4 -> 0 | D4: ='Sector_MDAs Summary-Details'!C4 -> 0 | F4: ='Sector_MDAs Summary-Details'!E4 -> Exceptional | G4: ='Sector_MDAs Summary-Details'!F4 -> Above Expectation | H4: ='Sector_MDAs Summary-Details'!G4 -> Meets Expectation | I4: ='Sector_MDAs Summary-Details'!H4 -> Needs Improvement | L4: ='Sector_MDAs Summary-Details'!K4 -> 0 | M4: ='Sector_MDAs Summary-Details'!L4 -> 0
A5: 0 | B5: 0 | C5: ='Sector_MDAs Summary-Details'!B5 -> 0 | D5: ='Sector_MDAs Summary-Details'!C5 -> 0 | E5: No. of Results | F5: ='Sector_MDAs Summary-Details'!E5 -> Above 100% | G5: ='Sector_MDAs Summary-Details'!F5 -> 70% -100% | H5: ='Sector_MDAs Summary-Details'!G5 -> 60% - 69% | I5: ='Sector_MDAs Summary-Details'!H5 -> 40% - 59% | J5: ='Sector_MDAs Summary-Details'!I5 -> Below 40% | K5: ='Sector_MDAs Summary-Details'!J5 -> N/A | L5: ='Sector_MDAs Summary-Details'!K5 -> Performance | M5: ='Sector_MDAs Summary-Details'!L5 -> Rating
A7: 1 | B7: Youth Empowerment and Employment Agency | C7: 1 | D7: ='Sector_MDAs Summary-Details'!C9 -> 9 | E7: ='Sector_MDAs Summary-Details'!D9 -> 20 | F7: ='Sector_MDAs Summary-Details'!E9 -> 5 | G7: ='Sector_MDAs Summary-Details'!F9 -> 5 | H7: ='Sector_MDAs Summary-Details'!G9 -> 2 | I7: ='Sector_MDAs Summary-Details'!H9 -> 5 | J7: ='Sector_MDAs Summary-Details'!I9 -> 2 | K7: ='Sector_MDAs Summary-Details'!J9 -> 1 | ... M7: ='Sector_MDAs Summary-Details'!L9 -> Very Good (Above Expectations) | N7: =E7-(F7+G7+H7+I7+J7+K7) -> 0
A8: 2 | B8: Ministry of Commerce, Industry, Cooperatives & Tourism | C8: 10 | D8: ='Sector_MDAs Summary-Details'!C22 -> 19 | E8: ='Sector_MDAs Summary-Details'!D22 -> 31 | F8: ='Sector_MDAs Summary-Details'!E22 -> 4 | G8: ='Sector_MDAs Summary-Details'!F22 -> 6 | H8: ='Sector_MDAs Summary-Details'!G22 -> 0 | I8: ='Sector_MDAs Summary-Details'!H22 -> 1 | J8: ='Sector_MDAs Summary-Details'!I22 -> 15 | K8: ='Sector_MDAs Summary-Details'!J22 -> 5 | ... M8: ='Sector_MDAs Summary-Details'!L22 -> Fair (Needs Improvement) | N8: =E8-(F8+G8+H8+I8+J8+K8) -> 0
A9: 3 | B9: Ministry of Women Affairs and Social Development | C9: 4 | D9: ='Sector_MDAs Summary-Details'!C30 -> 8 | E9: ='Sector_MDAs Summary-Details'!D30 -> 19 | F9: ='Sector_MDAs Summary-Details'!E30 -> 4 | G9: ='Sector_MDAs Summary-Details'!F30 -> 4 | H9: ='Sector_MDAs Summary-Details'!G30 -> 2 | I9: ='Sector_MDAs Summary-Details'!H30 -> 3 | J9: ='Sector_MDAs Summary-Details'!I30 -> 4 | K9: ='Sector_MDAs Summary-Details'!J30 -> 2 | L9: ='Sector_MDAs Summary-Details'!K30 -> 0.62036672 | M9: Good (Meets Expectations) | N9: =E9-(F9+G9+H9+I9+J9+K9) -> 0
A10: 4 | B10: Ministry for Local Govt. & Community Development | C10: 5 | D10: ='Sector_MDAs Summary-Details'!C38 -> 6 | E10: ='Sector_MDAs Summary-Details'!D38 -> 8 | F10: ='Sector_MDAs Summary-Details'!E38 -> 0 | G10: ='Sector_MDAs Summary-Details'!F38 -> 5 | H10: ='Sector_MDAs Summary-Details'!G38 -> 1 | I10: ='Sector_MDAs Summary-Details'!H38 -> 1 | J10: ='Sector_MDAs Summary-Details'!I38 -> 1 | K10: ='Sector_MDAs Summary-Details'!J38 -> 0 | ... M10: ='Sector_MDAs Summary-Details'!L38 -> Very Good (Above Expectations) | N10: =E10-(F10+G10+H10+I10+J10+K10) -> 0
A11: 5 | B11: Ministry of Environment | C11: 6 | D11: ='Sector_MDAs Summary-Details'!C47 -> 31 | E11: ='Sector_MDAs Summary-Details'!D47 -> 47 | F11: ='Sector_MDAs Summary-Details'!E47 -> 12 | G11: ='Sector_MDAs Summary-Details'!F47 -> 21 | H11: ='Sector_MDAs Summary-Details'!G47 -> 3 | I11: ='Sector_MDAs Summary-Details'!H47 -> 3 | J11: ='Sector_MDAs Summary-Details'!I47 -> 7 | K11: ='Sector_MDAs Summary-Details'!J47 -> 1 | ... M11: ='Sector_MDAs Summary-Details'!L47 -> Very Good (Above Expectations) | N11: =E11-(F11+G11+H11+I11+J11+K11) -> 0
A12: 6 | B12: Ministry of Basic Education | C12: 9 | D12: ='Sector_MDAs Summary-Details'!C59 -> 10 | E12: ='Sector_MDAs Summary-Details'!D59 -> 19 | F12: ='Sector_MDAs Summary-Details'!E59 -> 6 | G12: ='Sector_MDAs Summary-Details'!F59 -> 6 | H12: ='Sector_MDAs Summary-Details'!G59 -> 0 | I12: ='Sector_MDAs Summary-Details'!H59 -> 2 | J12: ='Sector_MDAs Summary-Details'!I59 -> 5 | K12: ='Sector_MDAs Summary-Details'!J59 -> 0 | ... M12: ='Sector_MDAs Summary-Details'!L59 -> Good (Meets Expectations) | N12: =E12-(F12+G12+H12+I12+J12+K12) -> 0
A13: 7 | B13: Ministry of Higher Education | C13: 11 | D13: ='Sector_MDAs Summary-Details'!C75 -> 13 | E13: ='Sector_MDAs Summary-Details'!D75 -> 23 | F13: ='Sector_MDAs Summary-Details'!E75 -> 9 | G13: ='Sector_MDAs Summary-Details'!F75 -> 11 | H13: ='Sector_MDAs Summary-Details'!G75 -> 1 | I13: ='Sector_MDAs Summary-Details'!H75 -> 0 | J13: ='Sector_MDAs Summary-Details'!I75 -> 1 | K13: ='Sector_MDAs Summary-Details'!J75 -> 1 | ... M13: ='Sector_MDAs Summary-Details'!L75 -> Very Good (Above Expectations) | N13: =E13-(F13+G13+H13+I13+J13+K13) -> 0
A14: 8 | B14: Ministry of Finance/Jigawa Internal Revenue Service | C14: 1 | D14: ='Sector_MDAs Summary-Details'!C80 -> 3 | E14: ='Sector_MDAs Summary-Details'!D80 -> 18 | F14: ='Sector_MDAs Summary-Details'!E80 -> 8 | G14: ='Sector_MDAs Summary-Details'!F80 -> 7 | H14: ='Sector_MDAs Summary-Details'!G80 -> 0 | I14: ='Sector_MDAs Summary-Details'!H80 -> 2 | J14: ='Sector_MDAs Summary-Details'!I80 -> 1 | K14: ='Sector_MDAs Summary-Details'!J80 -> 0 | ... M14: ='Sector_MDAs Summary-Details'!L80 -> Very Good (Above Expectations) | N14: =E14-(F14+G14+H14+I14+J14+K14) -> 0
A15: 9 | B15: Jigawa State Investment Promotion Agency (InvestJigawa) | C15: 3 | D15: ='Sector_MDAs Summary-Details'!C90 -> 10 | E15: ='Sector_MDAs Summary-Details'!D90 -> 22 | F15: ='Sector_MDAs Summary-Details'!E90 -> 6 | G15: ='Sector_MDAs Summary-Details'!F90 -> 5 | H15: ='Sector_MDAs Summary-Details'!G90 -> 0 | I15: ='Sector_MDAs Summary-Details'!H90 -> 2 | J15: ='Sector_MDAs Summary-Details'!I90 -> 5 | K15: ='Sector_MDAs Summary-Details'!J90 -> 4 | ... M15: ='Sector_MDAs Summary-Details'!L90 -> Good (Meets Expectations) | N15: =E15-(F15+G15+H15+I15+J15+K15) -> 0
A16: 10 | B16: Ministry of Lands, Housing, Urban & Regional Planning | C16: 4 | D16: ='Sector_MDAs Summary-Details'!C92 -> 0 | E16: ='Sector_MDAs Summary-Details'!D98 -> 21 | F16: ='Sector_MDAs Summary-Details'!E98 -> 0 | G16: ='Sector_MDAs Summary-Details'!F98 -> 6 | H16: ='Sector_MDAs Summary-Details'!G98 -> 1 | I16: ='Sector_MDAs Summary-Details'!H98 -> 1 | J16: ='Sector_MDAs Summary-Details'!I98 -> 12 | K16: ='Sector_MDAs Summary-Details'!J98 -> 1 | L16: ='Sector_MDAs Summary-Details'!K98 -> 0.45484224 | M16: ='Sector_MDAs Summary-Details'!L98 -> Fairly Ok (Needs Improvement) | N16: =E16-(F16+G16+H16+I16+J16+K16) -> 0
A17: 11 | B17: Ministry of Water Resources / Water Sector | C17: 3 | D17: ='Sector_MDAs Summary-Details'!C104 -> 10 | E17: ='Sector_MDAs Summary-Details'!D104 -> 36 | F17: ='Sector_MDAs Summary-Details'!E104 -> 6 | G17: ='Sector_MDAs Summary-Details'!F104 -> 14 | H17: ='Sector_MDAs Summary-Details'!G104 -> 2 | I17: ='Sector_MDAs Summary-Details'!H104 -> 2 | J17: ='Sector_MDAs Summary-Details'!I104 -> 12 | K17: ='Sector_MDAs Summary-Details'!J104 -> 0 | ... M17: ='Sector_MDAs Summary-Details'!L104 -> Good (Meets Expectations) | N17: =E17-(F17+G17+H17+I17+J17+K17) -> 0
A18: 12 | B18: Ministry of Works | C18: 1 | D18: ='Sector_MDAs Summary-Details'!C114 -> 1 | E18: ='Sector_MDAs Summary-Details'!D114 -> 7 | F18: ='Sector_MDAs Summary-Details'!E114 -> 4 | G18: ='Sector_MDAs Summary-Details'!F114 -> 0 | H18: ='Sector_MDAs Summary-Details'!G114 -> 0 | I18: ='Sector_MDAs Summary-Details'!H114 -> 2 | J18: ='Sector_MDAs Summary-Details'!I114 -> 1 | K18: ='Sector_MDAs Summary-Details'!J114 -> 0 | ... M18: ='Sector_MDAs Summary-Details'!L114 -> Very Good (Above Expectations) | N18: =E18-(F18+G18+H18+I18+J18+K18) -> 0
A19: 13 | B19: Min. of Power & Energy (State Electricity Board) | C19: 1 | D19: ='Sector_MDAs Summary-Details'!C119 -> 3 | E19: ='Sector_MDAs Summary-Details'!D119 -> 8 | F19: ='Sector_MDAs Summary-Details'!E119 -> 2 | G19: ='Sector_MDAs Summary-Details'!F119 -> 0 | H19: ='Sector_MDAs Summary-Details'!G119 -> 0 | I19: ='Sector_MDAs Summary-Details'!H119 -> 2 | J19: ='Sector_MDAs Summary-Details'!I119 -> 2 | K19: ='Sector_MDAs Summary-Details'!J119 -> 2 | ... M19: ='Sector_MDAs Summary-Details'!L119 -> Fairly Ok (Needs Improvement) | N19: =E19-(F19+G19+H19+I19+J19+K19) -> 0
A20: 14 | B20: Office of the Head of the State Civil Service | C20: 4 | D20: ='Sector_MDAs Summary-Details'!C130 -> 7 | E20: ='Sector_MDAs Summary-Details'!D130 -> 24 | F20: ='Sector_MDAs Summary-Details'!E130 -> 7 | G20: ='Sector_MDAs Summary-Details'!F130 -> 3 | H20: ='Sector_MDAs Summary-Details'!G130 -> 0 | I20: ='Sector_MDAs Summary-Details'!H130 -> 1 | J20: ='Sector_MDAs Summary-Details'!I130 -> 10 | K20: ='Sector_MDAs Summary-Details'!J130 -> 3 | ... M20: ='Sector_MDAs Summary-Details'!L130 -> Fairly Ok (Needs Improvement) | N20: =E20-(F20+G20+H20+I20+J20+K20) -> 0
A21: 15 | B21: Ministry of Agriculture / Agricultural Sector | C21: 12 | D21: ='Sector_MDAs Summary-Details'!C146 -> 24 | E21: ='Sector_MDAs Summary-Details'!D146 -> 67 | F21: ='Sector_MDAs Summary-Details'!E146 -> 12 | G21: ='Sector_MDAs Summary-Details'!F146 -> 20 | H21: ='Sector_MDAs Summary-Details'!G146 -> 4 | I21: ='Sector_MDAs Summary-Details'!H146 -> 14 | J21: ='Sector_MDAs Summary-Details'!I146 -> 13 | K21: ='Sector_MDAs Summary-Details'!J146 -> 4 | ... M21: ='Sector_MDAs Summary-Details'!L146 -> Good (Meets Expectations) | N21: =E21-(F21+G21+H21+I21+J21+K21) -> 0
A22: 16 | B22: Ministry of Special Duties | C22: 3 | D22: ='Sector_MDAs Summary-Details'!C152 -> 4 | E22: ='Sector_MDAs Summary-Details'!D152 -> 11 | F22: ='Sector_MDAs Summary-Details'!E152 -> 2 | G22: ='Sector_MDAs Summary-Details'!F152 -> 3 | H22: ='Sector_MDAs Summary-Details'!G152 -> 0 | I22: ='Sector_MDAs Summary-Details'!H152 -> 1 | J22: ='Sector_MDAs Summary-Details'!I152 -> 4 | K22: ='Sector_MDAs Summary-Details'!J152 -> 1 | ... M22: ='Sector_MDAs Summary-Details'!L152 -> Fairly Ok (Needs Improvement) | N22: =E22-(F22+G22+H22+I22+J22+K22) -> 0
A23: 17 | B23: Ministry of Budget and Economic Planning | C23: 4 | D23: ='Sector_MDAs Summary-Details'!C160 -> 7 | E23: ='Sector_MDAs Summary-Details'!D160 -> 18 | F23: ='Sector_MDAs Summary-Details'!E160 -> 1 | G23: ='Sector_MDAs Summary-Details'!F160 -> 8 | H23: ='Sector_MDAs Summary-Details'!G160 -> 0 | I23: ='Sector_MDAs Summary-Details'!H160 -> 3 | J23: ='Sector_MDAs Summary-Details'!I160 -> 4 | K23: ='Sector_MDAs Summary-Details'!J160 -> 2 | ... M23: ='Sector_MDAs Summary-Details'!L160 -> Good (Meets Expectations) | N23: =E23-(F23+G23+H23+I23+J23+K23) -> 0
A24: 18 | B24: Ministry of Justice | C24: 1 | D24: ='Sector_MDAs Summary-Details'!C163 -> 9 | E24: ='Sector_MDAs Summary-Details'!D163 -> 29 | F24: ='Sector_MDAs Summary-Details'!E163 -> 6 | G24: ='Sector_MDAs Summary-Details'!F163 -> 8 | H24: ='Sector_MDAs Summary-Details'!G163 -> 1 | I24: ='Sector_MDAs Summary-Details'!H163 -> 2 | J24: ='Sector_MDAs Summary-Details'!I163 -> 11 | K24: ='Sector_MDAs Summary-Details'!J163 -> 1 | ... M24: ='Sector_MDAs Summary-Details'!L163 -> Fairly Ok (Needs Improvement) | N24: =E24-(F24+G24+H24+I24+J24+K24) -> 0
A25: 19 | B25: Office of the SSG (Security) | C25: 8 | D25: ='Sector_MDAs Summary-Details'!C183 -> 9 | E25: ='Sector_MDAs Summary-Details'!D183 -> 19 | F25: ='Sector_MDAs Summary-Details'!E183 -> 5 | G25: ='Sector_MDAs Summary-Details'!F183 -> 2 | H25: ='Sector_MDAs Summary-Details'!G183 -> 0 | I25: ='Sector_MDAs Summary-Details'!H183 -> 0 | J25: ='Sector_MDAs Summary-Details'!I183 -> 3 | K25: ='Sector_MDAs Summary-Details'!J183 -> 9 | ... M25: ='Sector_MDAs Summary-Details'!L183 -> Good (Meets Expectations) | N25: =E25-(F25+G25+H25+I25+J25+K25) -> 0
A26: 20 | B26: Ministry of Health / Health Sector | C26: 6 | D26: ='Sector_MDAs Summary-Details'!C192 -> 8 | E26: ='Sector_MDAs Summary-Details'!D192 -> 57 | F26: ='Sector_MDAs Summary-Details'!E192 -> 5 | G26: ='Sector_MDAs Summary-Details'!F192 -> 18 | H26: ='Sector_MDAs Summary-Details'!G192 -> 7 | I26: ='Sector_MDAs Summary-Details'!H192 -> 10 | J26: ='Sector_MDAs Summary-Details'!I192 -> 14 | K26: ='Sector_MDAs Summary-Details'!J192 -> 3 | ... M26: ='Sector_MDAs Summary-Details'!L192 -> Fairly Ok (Needs Improvement) | N26: =E26-(F26+G26+H26+I26+J26+K26) -> 0
A27: 21 | B27: Ministry of Information | C27: 5 | D27: ='Sector_MDAs Summary-Details'!C200 -> 6 | E27: ='Sector_MDAs Summary-Details'!D200 -> 28 | F27: ='Sector_MDAs Summary-Details'!E200 -> 1 | G27: ='Sector_MDAs Summary-Details'!F200 -> 19 | H27: ='Sector_MDAs Summary-Details'!G200 -> 0 | I27: ='Sector_MDAs Summary-Details'!H200 -> 2 | J27: ='Sector_MDAs Summary-Details'!I200 -> 5 | K27: ='Sector_MDAs Summary-Details'!J200 -> 1 | ... M27: ='Sector_MDAs Summary-Details'!L200 -> Good (Meets Expectations) | N27: =E27-(F27+G27+H27+I27+J27+K27) -> 0
C29: =SUM(C6:C28) -> 102 | D29: =SUM(D6:D28) -> 197 | E29: =SUM(E6:E28) -> 532 | F29: =SUM(F6:F28) -> 105 | G29: =SUM(G6:G28) -> 171 | H29: =SUM(H6:H28) -> 24 | I29: =SUM(I6:I28) -> 59 | J29: =SUM(J6:J28) -> 132 | K29: =SUM(K6:K28) -> 41 | L29: =AVERAGE(L7:L28) -> 0.6484455

Sheet Grand Summary-Sector_MDAs+
A1: Perfomance Delivery Coordination Unit (PDCU), Office of the Executive Governor
A2: 2024 Fiscal Year Snapshot View of MDA/Sector Performance (January to Decemeber)
A3: S/N | B3: Names of MDAs / Sector | C3: No. of Commitments | D3: No. of Outputs | E3: No Results to be Delivered | F3: Overall Performance
F4: Performance at Mid-Year | G4: Fully Performance | H4: Fully Performance Rating
A5: 1 | B5: Youth Empowerment and Employment Agency | C5: ='Overall Summary'!C27 -> 5 | D5: 9 | E5: ='[1]MDA_Sector Summary'!D8 -> 20 | F5: 0.4378104 | G5: ='15. Empowerment'!H34 -> 0.72931604 | H5: Very Good - Above Expectations | I5: 1 | J5: 0.68533333
A6: 2 | B6: Min. of Commerce, Industries & Co-operatives | C6: ='Overall Summary'!C13 -> 11 | D6: 14 | E6: 27 | F6: 0.287 | G6: ='8. Min. of Comm'!H59 -> 0.4496148 | H6: Fair - Needs Improvement | I6: 2 | J6: 0.51601965
A7: 3 | B7: Ministry of Women Affairs & Social Development | C7: ='Overall Summary'!C24 -> 1 | D7: 8 | E7: 16 | F7: 0.36335417 | G7: ='18. Min. of Women Affrs'!H34 -> 0.62036672 | H7: Good Meet s Expectations | I7: 3 | J7: 0.56356926
A8: 4 | B8: Ministry of Local Government | C8: ='Overall Summary'!C21 -> 12 | D8: 6 | E8: 8 | F8: 0.47737778 | G8: ='4. Min. of LG'!H29 -> 0.70770833 | H8: Very Good - Above Expectations | I8: 4 | J8: 0.64717905
A9: 5 | B9: Ministry of Environment | C9: ='Overall Summary'!C14 -> 1 | D9: ='[1]MDA_Sector Summary'!C43 -> 31 | E9: ='[1]MDA_Sector Summary'!D43 -> 47 | F9: 0.36724017 | G9: ='19. Min. of Env'!H71 -> 0.76182238 | H9: Very Good - Above Expectations | I9: 5 | J9: 0.6888195
A10: 6 | B10: Ministry of Basic Education | C10: ='Overall Summary'!C11 -> 6 | D10: 10 | E10: 16 | F10: 0.24 | G10: ='13. Min. of Basic Edu'!H44 -> 0.6888195 | H10: Good Meet s Expectations | I10: 6 | J10: 0.59988095
A11: 7 | B11: Min. of Higher Education, Science & Technology | C11: ='Overall Summary'!C17 -> 3 | D11: 13 | E11: 23 | F11: 0.50318182 | G11: ='14. Min. of Higher Edu'!H50 -> 0.9333092 | H11: Very Good - Above Expectations | I11: 7 | J11: 0.4496148
A12: 8 | B12: Ministry of Finance (Internal Revenue Service) | C12: ='Overall Summary'!C15 -> 3 | D12: 3 | E12: 17 | F12: 0.441 | G12: ='MoF-JIRS'!H25 -> 0.86473684 | H12: Very Good - Above Expectations | I12: 8 | J12: 0.76182238
A13: 9 | B13: State Investment Promotion Agency | C13: ='Overall Summary'!C26 -> 6 | D13: ='[1]MDA_Sector Summary'!C82 -> 10 | E13: ='[1]MDA_Sector Summary'!D88 -> 20 | F13: 0.425 | G13: ='16. JigawaInvest'!H34 -> 0.66296542 | H13: Good Meet s Expectations | I13: 9 | J13: 0.86473684
A14: 10 | B14: Min. of Lands, Housing and Urban Development | C14: ='Overall Summary'!C20 -> 4 | D14: 10 | E14: 20 | F14: 0.27721461 | G14: ='20. Min. of Land'!H37 -> 0.45484224 | H14: Fair - Needs Improvement | I14: 10 | J14: 0.65406464
A15: 11 | B15: Ministry of Water Resources | C15: ='Overall Summary'!C23 -> 4 | D15: 10 | E15: ='[1]MDA_Sector Summary'!D94 -> 36 | F15: 0.39566667 | G15: ='10. Min. of Water SS'!H49 -> 0.63785681 | H15: Good Meet s Expectations | I15: 11 | J15: 0.9333092
A16: 12 | B16: Ministry of Works & Transport | C16: ='Overall Summary'!C25 -> 8 | D16: 1 | E16: ='[1]MDA_Sector Summary'!D98 -> 7 | F16: 0.319 | G16: ='6. Min. of Works'!I16 -> 0.76428571 | H16: Very Good - Above Expectations | I16: 12 | J16: 0.65038752
A17: 13 | B17: Ministry of Power and Energy | C17: ='Overall Summary'!C22 -> 3 | D17: 3 | E17: 8 | F17: 0.2528 | G17: ='7. Power'!H14 -> 0.56083333 | H17: Fair - Needs Improvement | I17: 13 | J17: 0.56943897
A18: 14 | B18: Office of the Head of the State Civil Service | C18: ='Overall Summary'!C8 -> 10 | D18: 4 | E18: 24 | F18: 0.35368634 | G18: ='1. OHOS'!H37 -> 0.51601965 | H18: Fair - Needs Improvement | I18: 14 | J18: 0.45484224
A19: 15 | B19: Ministry of Agriculture & Natural Resources | C19: ='Overall Summary'!C10 -> 5 | D19: 25 | E19: 64 | F19: 0.455 | G19: ='9. Min. of Agric'!H98 -> 0.64717905 | H19: Good Meet s Expectations | I19: 15 | J19: 0.70770833
A20: 16 | B20: Ministry For Special Duties | C20: ='Overall Summary'!C9 -> 4 | D20: ='[1]MDA_Sector Summary'!C132 -> 4 | E20: ='[1]MDA_Sector Summary'!D132 -> 9 | F20: 0.42 | G20: ='3. Min. of Special Duties'!I28 -> 0.56356926 | H20: Fair - Needs Improvement | I20: 16 | J20: 0.56083333
A21: 17 | B21: Ministry of Budget and Economic Planning | C21: ='Overall Summary'!C12 -> 9 | D21: 7 | E21: 22 | F21: 0.39816162 | G21: ='5. Min. of Budget'!H32 -> 0.59988095 | H21: Good Meet s Expectations | I21: 17 | J21: 0.63785681
A22: 18 | B22: Ministry of Justice | C22: ='Overall Summary'!C19 -> 1 | D22: 9 | E22: 29 | F22: 0.4141434 | G22: ='21. MoJustice'!H34 -> 0.56943897 | H22: Fair - Needs Improvement | I22: 18 | J22: 0.62036672
A23: 19 | B23: Office of the Secretary to the State Government | C23: ='Overall Summary'!C7 -> 1 | D23: 4 | E23: 14 | F23: 0.22222222 | G23: ='Sector_MDAs Summary-Details'!K183 -> 0.68533333 | H23: Good Meet s Expectations | I23: 19 | J23: 0.76428571
A24: 20 | B24: Ministry of Health | C24: ='Overall Summary'!C16 -> 4 | D24: ='[1]MDA_Sector Summary'!C163 -> 8 | E24: ='[1]MDA_Sector Summary'!D163 -> 60 | F24: 0.41021999 | G24: ='11. Min. of Health'!H80 -> 0.65406464 | H24: Good Meet s Expectations | I24: 20 | J24: 0.66296542
A25: 21 | B25: Min. of Information Youths, Sports and Culture | C25: ='Overall Summary'!C18 -> 1 | D25: ='[1]MDA_Sector Summary'!C171 -> 6 | E25: ='[1]MDA_Sector Summary'!D171 -> 26 | F25: 0.45837963 | G25: ='12. Min. of Infor'!H45 -> 0.65038752 | H25: Good Meet s Expectations | I25: 21 | J25: 0.72931604
A26: 22 | B26: Overall State Performance | C26: ='Overall Summary'!C28 -> 0 | D26: =SUM(D5:D25) -> 195 | E26: =SUM(E5:E25) -> 513 | F26: 0.37706947 | G26: =AVERAGE(G5:G25) -> 0.65344527 | H26: Good Meet s Expectations | J26: 0.65344527
B34: =1109+4556+2202 -> 7867

Sheet Sector_MDAs Summary-Details
C1: Perfomance Delivery Coordination Unit (PDCU), Office of the Executive Governor
A2: January to December 2024 MDA/Sector Summary of Performance on Commitments
A3: S/N | B3: Commitments | C3: No. of Outputs | D3: No Results to be Delivered | E3: Performance for Each Result | K3: Overall Performance | M3: r
E4: Exceptional | F4: Above Expectation | G4: Meets Expectation | H4: Needs Improvement | I4: Below Minimum Expectation | J4: Not Assessed | N4: Check
E5: Above 100% | F5: 70% -100% | G5: 60% - 69% | H5: 40% - 59% | I5: Below 40% | J5: N/A | K5: Performance | L5: Rating
M6: A Good Performance with significant improvement compared to mid0year performance of 44%
B7: Youth Empowerment and Employment Agency
A8: 1 | B8: Employment Generation and Youth Empowerment for Productivity and Sustainable Means of Livelihoods for the People of Jigawa State. | C8: 9 | D8: 20 | E8: 5 | F8: 5 | G8: 2 | H8: 5 | I8: 2 | J8: 1 | K8: ='15. Empowerment'!H34 -> 0.72931604 | L8: Very Good Performance
C9: =C8 -> 9 | D9: =D8 -> 20 | E9: =E8 -> 5 | F9: =F8 -> 5 | G9: =G8 -> 2 | H9: =H8 -> 5 | I9: =I8 -> 2 | J9: =J8 -> 1 | K9: =K8 -> 0.72931604 | L9: Very Good (Above Expectations)
B11: Min. of Commerce, Industry, Cooperatives & Tourism
A12: 1 | B12: Promoting of MSMSEs and Cooperatives | C12: 4 | D12: 6 | E12: 1 | F12: 2 | G12: 0 | H12: 1 | I12: 2 | J12: 0 | K12: ='8. Min. of Comm'!I14 -> 0.56199473 | L12: Fair (Needs Improvement) | M12: =D12-E12-F12-G12-H12-I12-J12 -> 0
A13: 2 | B13: Revitalization of Maigatari EPZ | C13: 3 | D13: 9 | E13: 1 | F13: 1 | G13: 0 | H13: 0 | I13: 5 | J13: 2 | K13: ='8. Min. of Comm'!I25 -> 0.32124517 | L13: Unsatisfactory (Below Minimum Requirement) | M13: =D13-E13-F13-G13-H13-I13-J13 -> 0
A14: 3 | B14: Trade Fairs | C14: 1 | D14: 2 | E14: 0 | F14: 0 | G14: 0 | H14: 0 | I14: 0 | J14: 2 | K14: ='8. Min. of Comm'!I29 -> NA | L14: Not Assessed | M14: =D14-E14-F14-G14-H14-I14-J14 -> 0
A15: 4 | B15: Tourism Development | C15: 1 | D15: 2 | E15: 0 | F15: 2 | G15: 0 | H15: 0 | I15: 0 | J15: 0 | K15: ='8. Min. of Comm'!I33 -> 0.82465009 | L15: Very Good (Above Expectation) | M15: =D15-E15-F15-G15-H15-I15-J15 -> 0
A16: 5 | B16: Access to Financing | C16: 1 | D16: 2 | E16: 2 | F16: 0 | G16: 0 | H16: 0 | I16: 0 | J16: 0 | K16: ='8. Min. of Comm'!I37 -> 1.01 | L16: Distinction (Exceptional) | M16: =D16-E16-F16-G16-H16-I16-J16 -> 0
A17: 6 | B17: Export Promotion - Increase Market Access and International Trade Opportunities | C17: 2 | D17: 2 | E17: 0 | F17: 1 | H17: 0 | I17: 1 | J17: 0 | K17: ='8. Min. of Comm'!I41 -> 0.45 | L17: Fair (Needs Improvement) | M17: =D17-E17-F17-G17-H17-I17-J17 -> 0
A18: 7 | B18: Support the operation of Jigawa State Chamber of Commerce to drive the growth of Trade and Industries in the State. | C18: 2 | D18: 2 | E18: 0 | F18: 0 | G18: 0 | H18: 0 | I18: 2 | J18: 0 | K18: ='8. Min. of Comm'!I45 -> 0 | L18: Unsatisfactory (Below Minimum Requirement) | M18: =D18-E18-F18-G18-H18-I18-J18 -> 0
A19: 8 | B19: Capitalize Coops, Agric-based Association and Social Enterprises Development | C19: 1 | D19: 2 | E19: 0 | F19: 0 | G19: 0 | H19: 0 | I19: 1 | J19: 1 | K19: ='8. Min. of Comm'!$I$49 -> 0.3 | L19: Unsatisfactory (Below Minimum Requirement) | M19: =D19-E19-F19-G19-H19-K19-J19 -> 0.7
A20: 9 | B20: Development / Modernzation of Markets in the State to Support Trading Activities and Expand Revenue Generation | C20: 2 | D20: 2 | E20: 0 | F20: 0 | G20: 0 | H20: 0 | I20: 2 | J20: 0 | K20: ='8. Min. of Comm'!I53 -> 0.43333333 | L20: Fair (Needs Improvement) | M20: =D20-E20-F20-G20-H20-I20-J20 -> 0
A21: 10 | B21: Development / Modernzation of Markets in the State to Support Trading Activities and Expand Revenue Generation | C21: 2 | D21: 2 | E21: 0 | F21: 0 | G21: 0 | H21: 0 | I21: 2 | J21: 0 | K21: ='8. Min. of Comm'!I58 -> 0.16666667 | L21: Unsatisfactory (Below Minimum Requirement) | M21: =D21-E21-F21-G21-H21-I21-J21 -> 0
C22: =SUM(C12:C21) -> 19 | D22: =SUM(D12:D21) -> 31 | E22: =SUM(E12:E21) -> 4 | F22: =SUM(F12:F21) -> 6 | G22: =SUM(G12:G21) -> 0 | H22: =SUM(H12:H21) -> 1 | I22: =SUM(I12:I21) -> 15 | J22: =SUM(J12:J21) -> 5 | K22: ='8. Min. of Comm'!H59 -> 0.4496148 | L22: Fair (Needs Improvement) | M22: =D22-E22-F22-G22-H22-I22-J22 -> 0
B24: Ministry of Women Affairs and Social Development
A25: 1 | B25: Pursuit of targeted women empowerment programmes for job and employment creation | C25: 2 | D25: 5 | E25: 1 | F25: 2 | G25: 0 | H25: 1 | I25: 0 | J25: 1 | K25: ='18. Min. of Women Affrs'!I10 -> 0.79 | L25: Very Good (Above Expectations_
A26: 2 | B26: Evolution of new social protection programs along the Life Cycle | C26: 4 | D26: 8 | E26: 3 | F26: 1 | G26: 1 | H26: 1 | I26: 2 | J26: 0 | K26: ='18. Min. of Women Affrs'!I21 -> 0.67333333 | L26: Good (Meets Expectations)
A27: 3 | B27: Develop and implement policies on the protection, survival & development of women and children to address concerns on the Situation of Children in Jigawa State | C27: 1 | D27: 3 | E27: 0 | F27: 0 | G27: 0 | H27: 1 | I27: 2 | J27: 0 | K27: ='18. Min. of Women Affrs'!I27 -> 0.16271777 | L27: Unsatisfactory (Below Minimum Requirement)
A28: 4 | B28: Sustained improvements in Social Welfare Institutions in the State | C28: 1 | D28: 3 | E28: 0 | F28: 1 | G28: 1 | H28: 0 | I28: 0 | J28: 1 | K28: ='18. Min. of Women Affrs'!I33 -> 0.7815 | L28: Very Good (Above Expectations_
E29: Above 100% | F29: 70% -100% | G29: 60% - 69% | H29: 40% - 59% | I29: Below 40% | J29: N/A
C30: =SUM(C25:C28) -> 8 | D30: =SUM(D25:D28) -> 19 | E30: =SUM(E25:E28) -> 4 | F30: =SUM(F25:F28) -> 4 | G30: =SUM(G25:G28) -> 2 | H30: =SUM(H25:H28) -> 3 | I30: =SUM(I25:I28) -> 4 | J30: =SUM(J25:J28) -> 2 | K30: ='18. Min. of Women Affrs'!H34 -> 0.62036672 | L30: Good (Meets Expectations)
B32: Ministry for Local Govt. & Community Development
A33: 1 | B33: Strengthen Community Based Security Architecture | C33: 1 | D33: 1 | E33: 0 | F33: 1 | G33: 0 | H33: 0 | I33: 0 | J33: 0 | K33: ='4. Min. of LG'!I8 -> 1.01 | L33: Distinction (Exceptional
A34: 2 | B34: Launch of Community Peace Initiative (CPI) for improve service delivery and Community Development | C34: 1 | D34: 1 | E34: 0 | F34: 0 | G34: 0 | H34: 1 | I34: 0 | J34: 0 | K34: ='4. Min. of LG'!I13 -> 0.46 | L34: Fair (Needs Improvement)
A35: 3 | B35: Commitment-3: Create an Elders Advisory Committee (ELCO) in every Local Government to advise Government on various government programs and implementation strategies for development. | C35: 1 | D35: 1 | E35: 0 | F35: 0 | G35: 1 | H35: 0 | I35: 0 | J35: 0 | K35: ='4. Min. of LG'!I16 -> 0.6 | L35: Good (Meets Expectations)
A36: 4 | B36: Commitment-4: Entrench an effective financial management system alongside improved policy and strategy across all the Local Governments with the support and collaboration with Development Partners. | C36: 2 | D36: 2 | E36: 0 | F36: 2 | G36: 0 | H36: 0 | I36: 0 | J36: 0 | K36: ='4. Min. of LG'!I20 -> 0.8375 | L36: Very Good (Above Expectations)
A37: 5 | B37: Commitment-5: Sustain street light maintenance across all the 27 LGAs | C37: 1 | D37: 3 | E37: 0 | F37: 2 | G37: 0 | H37: 0 | I37: 1 | J37: 0 | K37: ='4. Min. of LG'!I27 -> 0.63888889 | L37: Good (Meets Expectations)
C38: =SUM(C33:C37) -> 6 | D38: =SUM(D33:D37) -> 8 | E38: =SUM(E33:E37) -> 0 | F38: =SUM(F33:F37) -> 5 | G38: =SUM(G33:G37) -> 1 | H38: =SUM(H33:H37) -> 1 | I38: =SUM(I33:I37) -> 1 | J38: =SUM(J33:J37) -> 0 | K38: ='4. Min. of LG'!H29 -> 0.70770833 | L38: Very Good (Above Expectations)
B40: Ministry of Environment
A41: 1 | B41: Take appropriate proactive measures to address some critical areas of environmental degradation. | C41: 4 | D41: 7 | E41: 3 | F41: 2 | G41: 1 | H41: 1 | I41: 0 | J41: 0 | K41: ='19. Min. of Env'!I13 -> 0.81721088 | L41: Very Good (Above Expectations)
A42: 2 | B42: Take action to address desert encroachment and improved vegetation cover | C42: 7 | D42: 7 | E42: 1 | F42: 5 | G42: 0 | H42: 1 | I42: 0 | J42: 0 | K42: ='19. Min. of Env'!I23 -> 0.8904601 | L42: Very Good (Above Expectations)
A43: 3 | B43: Mobilize and Leverage on External Support from Development Partners to Address issues on Environmental Sustainability including Climate Change (These include World Bank Assisted Projects, FGN Supported Great Green World Projects, etc. | C43: 1 | D43: 3 | E43: 1 | F43: 1 | G43: 0 | H43: 0 | I43: 1 | J43: 0 | K43: ='19. Min. of Env'!I29 -> 0.78111111
A44: 4 | B44: Improve the Health Status of the Population through the Promotion of Environmental Health and Public Health Security | C44: 12 | D44: 17 | E44: 5 | F44: 7 | G44: 0 | H44: 0 | I44: 4 | J44: 1 | K44: ='19. Min. of Env'!I50 -> 0.73195769
A45: 5 | B45: Pursuit of initiatives to mitigate the adverse effects of Climate Change on Environmental Sustainability | C45: 2 | D45: 4 | E45: 0 | F45: 2 | G45: 2 | H45: 0 | I45: 0 | J45: 0 | K45: ='19. Min. of Env'!$I$57 -> 0.73511905
A46: 6 | B46: Pursuit of Initiatives to promote nature conservation for the protection of the flora and fauna of the environment | C46: 5 | D46: 9 | E46: 2 | F46: 4 | G46: 0 | H46: 1 | I46: 2 | J46: 0 | K46: ='19. Min. of Env'!I70 -> 0.67722222
A47: Overall | C47: =SUM(C41:C46) -> 31 | D47: =SUM(D41:D46) -> 47 | E47: =SUM(E41:E46) -> 12 | F47: =SUM(F41:F46) -> 21 | G47: =SUM(G41:G46) -> 3 | H47: =SUM(H41:H46) -> 3 | I47: =SUM(I41:I46) -> 7 | J47: =SUM(J41:J46) -> 1 | K47: ='19. Min. of Env'!H71 -> 0.76182238 | L47: Very Good (Above Expectations)
B49: Ministry of Basic Education
A50: 1 | B50: Automation and digitization of school administrations, governance and admission process | C50: 1 | D50: 1 | E50: 0 | F50: 1 | G50: 0 | H50: 0 | I50: 0 | J50: 0 | K50: ='[2]13. Min. of Basic Edu'!I9 -> 1
A51: 2 | B51: Enhance the Education database for proper mapping of all schools in the State by undertaking bio-metric-based capturing of all pupils and teachers | C51: 1 | D51: 1 | E51: 0 | F51: 1 | G51: 0 | H51: 0 | I51: 0 | J51: 0 | K51: ='[2]13. Min. of Basic Edu'!I12 -> 1
A52: 3 | B52: Automation and digitization of school administrations, governance and admission process | C52: 1 | D52: 2 | E52: 0 | F52: 0 | G52: 0 | H52: 1 | I52: 1 | J52: 0 | K52: ='[2]13. Min. of Basic Edu'!I16 -> 0.41998525
A53: 4 | B53: Enhance the efficiency, resourcefulness, competence of teachers and other educational personnel through training, capacity building, and motivation (Continuous training and retraining of at least 5,000 Teachers/Instructors annually, focusing on Modern Teaching Research Techniques, Digital Literacy, and Skills for Basic Education) | C53: 1 | D53: 4 | E53: 1 | F53: 1 | G53: 0 | I53: 2 | J53: 0 | K53: ='[2]13. Min. of Basic Edu'!I22 -> 0.43815
A54: 5 | B54: Consolidate on gains achieved in girl-child education by introducing Girl-Child Community Committee (GCCC) to monitor retention rates for girls in schools | C54: 1 | D54: 1 | E54: 1 | F54: 0 | G54: 0 | H54: 0 | I54: 0 | J54: 0 | K54: ='[2]13. Min. of Basic Edu'!I25 -> 1.01
A55: 6 | B55: Leapfrog Jigawa into the Digital Economy by introducing digital skills such as coding, web development, and artificial intelligence to all public primary and secondary schools in the state | C55: 2 | D55: 2 | E55: 0 | F55: 0 | G55: 0 | H55: 0 | I55: 2 | J55: 0 | K55: ='[2]13. Min. of Basic Edu'!I29 -> 0.0275
A56: 7 | B56: Address the challenge of unfavorable pupil-teacher ratio in Basic schools | C56: 1 | D56: 6 | E56: 2 | F56: 3 | G56: 0 | H56: 1 | I56: 0 | J56: 0 | K56: ='[2]13. Min. of Basic Edu'!I37 -> 0.90333333
A57: 8 | B57: Reviewing the concept of established Effective Schools at Basic Education | C57: 1 | D57: 1 | E57: 1 | F57: 0 | G57: 0 | H57: 0 | I57: 0 | J57: 0 | K57: ='[2]13. Min. of Basic Edu'!I43 -> 1.01
A58: 9 | B58: Leveraging on the power of e-learning to achieve better learning outcomes in schools (This would be part of an integrated State ICT Strategy and e-governance) | C58: 1 | D58: 1 | E58: 1 | F58: 0 | G58: 0 | H58: 0 | I58: 0 | J58: 0 | K58: ='[2]13. Min. of Basic Edu'!I43 -> 1.01
C59: =SUM(C50:C58) -> 10 | D59: =SUM(D50:D58) -> 19 | E59: =SUM(E50:E58) -> 6 | F59: =SUM(F50:F58) -> 6 | G59: =SUM(G50:G58) -> 0 | H59: =SUM(H50:H58) -> 2 | I59: =SUM(I50:I58) -> 5 | J59: =SUM(J50:J58) -> 0 | K59: ='[2]13. Min. of Basic Edu'!H44 -> 0.6888195 | L59: Good (Meets Expectations)
B61: Ministry of Higher Education
A63: 1 | B63: Address the challenges of unfavorable pupil - teacher ratio in post basic school (senior secondary school) | C63: 1 | D63: 1 | E63: 1 | F63: 0 | G63: 0 | H63: 0 | I63: 0 | J63: 0 | K63: ='[2]14. Min. of Higher Edu'!$I$7 -> 1.01
A64: 2 | B64: Reviewing the concept of Establishing centers of excellence and effective schools at post basic Education | C64: 1 | D64: 1 | E64: 0 | F64: 1 | G64: 0 | H64: 0 | I64: 0 | J64: 0 | K64: ='[2]14. Min. of Higher Edu'!$I$10 -> 1
A65: 3 | B65: Provision of Critical Infrastructures (Decongestion of student classes and Hostel) | C65: 2 | D65: 2 | E65: 1 | F65: 1 | G65: 0 | H65: 0 | I65: 0 | J65: 0 | K65: ='[2]14. Min. of Higher Edu'!I14 -> 0.96227273
A66: 4 | B66: Enhance quality of science, technology and vocational Education Training (STEM and TVET) | C66: 1 | D66: 2 | E66: 2 | F66: 0 | G66: 0 | H66: 0 | I66: 0 | J66: 0 | K66: ='[2]14. Min. of Higher Edu'!I18 -> 1.01
A67: 5 | B67: Leveraging on the power of e-learning to achieve better learning outcomes in schools (This would be part of an integrated state ICT strategy and e-governance | C67: 1 | D67: 3 | E67: 1 | F67: 2 | G67: 0 | H67: 0 | I67: 0 | J67: 0 | K67: ='[2]14. Min. of Higher Edu'!I23 -> 1.0033333
A68: 6 | B68: Ensure effective operation of ICT in Schools | C68: 1 | D68: 4 | E68: 2 | F68: 2 | G68: 0 | H68: 0 | I68: 0 | J68: 0 | K68: ='[2]14. Min. of Higher Edu'!I29 -> 0.98206422
A69: 7 | B69: Accelerate effort to commence medical training in the state university | C69: 2 | D69: 2 | E69: 0 | F69: 1 | G69: 0 | H69: 0 | I69: 0 | J69: 1 | K69: ='[2]14. Min. of Higher Edu'!I33 -> 1
A70: 8 | B70: Improve operation of Jigawa quality Assurance Agency (JISEQAA) | C70: 1 | D70: 5 | E70: 2 | F70: 2 | G70: 1 | H70: 0 | I70: 0 | J70: 0 | K70: ='[2]14. Min. of Higher Edu'!$I$40 -> 0.878
A71: 9 | B71: Ensure that all program in the state tertiary institution are fully accredited by the relevant authorities | C71: 1 | D71: 1 | E71: 0 | F71: 1 | G71: 0 | H71: 0 | I71: 0 | J71: 0 | K71: ='[2]14. Min. of Higher Edu'!$I$43 -> 1
A72: 10 | B72: Establish research centers in tertiary institutions to attract intervention/collaboration from (public/private sectors) and improve the existing ones | C72: 1 | D72: 1 | E72: 0 | F72: 1 | G72: 0 | H72: 0 | I72: 0 | J72: 0 | K72: ='[2]14. Min. of Higher Edu'!I46 -> 0.75
A73: 11 | B73: Funding research in science, technology and Agriculture through collaboration with private sector and Donor agencies | C73: 1 | D73: 1 | E73: 0 | F73: 0 | G73: 0 | H73: 0 | I73: 1 | J73: 0 | K73: ='[2]14. Min. of Higher Edu'!I49 -> 0.5
C75: =SUM(C63:C74) -> 13 | D75: =SUM(D63:D74) -> 23 | E75: =SUM(E63:E74) -> 9 | F75: =SUM(F63:F74) -> 11 | G75: =SUM(G63:G74) -> 1 | H75: =SUM(H63:H74) -> 0 | I75: =SUM(I63:I74) -> 1 | J75: =SUM(J63:J74) -> 1 | K75: ='[2]14. Min. of Higher Edu'!H50 -> 0.9333092 | L75: Very Good (Above Expectations)
B77: Ministry of Finance/Jigawa Internal Revenue Service
A78: 1 | B78: Sustained Improvement in the Efficiency and Effectiveness in Internal Revenue Administration, Management and Performance | C78: 3 | D78: 18 | E78: 8 | F78: 7 | G78: 0 | H78: 2 | I78: 1 | J78: 0 | K78: ='[2]MoF-JIRS'!H25 -> 0.86473684
C80: =C78 -> 3 | D80: =D78 -> 18 | E80: =E78 -> 8 | F80: =F78 -> 7 | G80: =G78 -> 0 | H80: =H78 -> 2 | I80: =I78 -> 1 | J80: =J78 -> 0 | K80: =K78 -> 0.86473684 | L80: Very Good (Above Expectations)
A82: January to December 2024 MDA/Sector Summary of Performance on Commitments
A83: S/N | B83: Commitments | C83: No. of Outputs | D83: No Results to be Delivered | E83: Performance for Each Result | K83: Overall Performance
E84: Exceptional | F84: Above Expectation | G84: Meets Expectation | H84: Needs Improvement | I84: Below Minimum Expectation | J84: Not Assessed
E85: Above 100% | F85: 70% -100% | G85: 60% - 69% | H85: 40% - 59% | I85: Below 40% | J85: N/A | K85: Performance | L85: Rating
B86: Jigawa State Investment Promotion Agency (InvestJigawa)
A87: 1 | B87: Improvement of the State’s Business Environment and Investment Climate aimed at mobilizing Domestic and Foreign Direct Investments into the State to support quest for economic growth and development. This will involve the provision of pragmatic and relevant policy, legal, regulatory, and institutional frameworks for investment mobilization and private sector development. | C87: 8 | D87: 18 | E87: 4 | F87: 4 | G87: 0 | H87: 2 | I87: 5 | J87: 3 | K87: ='[2]16. JigawaInvest'!I25 -> 0.59422517 | L87: Fair (Needs Improvement)
A88: 2 | B88: To Fast track the realization of mobilized / pipeline investment proposals and support to the private sector for increased investments and job creation | C88: 1 | D88: 3 | E88: 2 | F88: 1 | G88: 0 | H88: 0 | I88: 0 | J88: 0 | K88: ='[2]16. JigawaInvest'!I30 -> 1.0066667 | L88: Exceptional (Distinction)
A89: 3 | B89: Continue to provide the necessary business environment and investment climate attractive to both Domestic and Foreign Investors; be among the topmost performers in the Nation’s Business Competitiveness Index | C89: 1 | D89: 1 | E89: 0 | F89: 0 | G89: 0 | H89: 0 | I89: 0 | J89: 1 | L89: Not Assessed
B90: Total | C90: =SUM(C87:C89) -> 10 | D90: =SUM(D87:D89) -> 22 | E90: =SUM(E87:E89) -> 6 | F90: =SUM(F87:F89) -> 5 | G90: =SUM(G87:G89) -> 0 | H90: =SUM(H87:H89) -> 2 | I90: =SUM(I87:I89) -> 5 | J90: =SUM(J87:J89) -> 4 | K90: ='[2]16. JigawaInvest'!H34 -> 0.66296542 | L90: Good (Meets Expectations)
B92: Ministry of Lands, Housing, Urban & Regional Planning
A93: 1 | B93: Development of comprehensive Geographic Information System for more effective Land Administration in the State | C93: 4 | D93: 12 | E93: 0 | F93: 4 | G93: 1 | H93: 0 | I93: 7 | J93: 0 | K93: ='20. Min. of Land'!$I$18 -> 0.47480159 | L93: Fairly Ok (Needs Improvement)
A94: 2 | B94: Implementation of Mass Housing Program (including in collaboration with private sector) to reducing Housing Deficit in the State Capital and other Major Urban Centers in the State | C94: 4 | D94: 4 | E94: 0 | F94: 1 | I94: 3 | J94: 0 | K94: ='20. Min. of Land'!$I$25 -> 0.4 | L94: Fairly Ok (Needs Improvement)
A95: 3 | B95: Pursuit of urban renewal program guided by updated and simple master plan | C95: 1 | D95: 2 | E95: 0 | F95: 0 | G95: 0 | H95: 1 | I95: 0 | J95: 1 | K95: ='20. Min. of Land'!I29 -> 0.5 | L95: Fairly Ok (Needs Improvement)
A96: 4 | B96: Percentage of Progress on Review of Revenue Rates and Scope under Land Administration | C96: 1 | D96: 3 | E96: 0 | F96: 1 | G96: 0 | H96: 0 | I96: 2 | J96: 0 | K96: ='20. Min. of Land'!I36 -> 0.41479452 | L96: Fairly Ok (Needs Improvement)
B98: Total | C98: =SUM(C93:C96) -> 10 | D98: =SUM(D93:D96) -> 21 | E98: =SUM(E93:E96) -> 0 | F98: =SUM(F93:F96) -> 6 | G98: =SUM(G93:G96) -> 1 | H98: =SUM(H93:H96) -> 1 | I98: =SUM(I93:I96) -> 12 | J98: =SUM(J93:J96) -> 1 | K98: ='20. Min. of Land'!$H$37 -> 0.45484224 | L98: Fairly Ok (Needs Improvement)
B100: Ministry of Water Resources / Water Sector
A101: 1 | B101: Achieve universal access to safe drinking water and sanitation services | C101: 7 | D101: 26 | E101: 5 | F101: 12 | G101: 0 | H101: 2 | I101: 7 | J101: 0 | K101: ='[2]10. Min. of Water SS'!I34 -> 0.69914789
A102: 2 | B102: Increased Investments in the Rehabilitation and Expansion of Irrigation Facilities and Infrastructure (Dams and Water Reservoirs) | C102: 2 | D102: 4 | E102: 1 | F102: 1 | G102: 0 | H102: 0 | I102: 2 | J102: 0 | K102: ='[2]10. Min. of Water SS'!I40 -> 0.565
A103: 3 | B103: Achieve the provisions of SDG Goal 6 to ensure availability and sustainable management of water and sanitation for all | C103: 1 | D103: 6 | E103: 0 | F103: 1 | G103: 2 | H103: 0 | I103: 3 | K103: ='[2]10. Min. of Water SS'!I48 -> 0.42083333
C104: =SUM(C101:C103) -> 10 | D104: =SUM(D101:D103) -> 36 | E104: =SUM(E101:E103) -> 6 | F104: =SUM(F101:F103) -> 14 | G104: =SUM(G101:G103) -> 2 | H104: =SUM(H101:H103) -> 2 | I104: =SUM(I101:I103) -> 12 | J104: =SUM(J101:J103) -> 0 | K104: ='[2]10. Min. of Water SS'!$H$49 -> 0.63785681 | L104: Good (Meets Expectations)
A106: January to December 2024 MDA/Sector Summary of Performance on Commitments
A107: S/N | B107: Commitments | C107: No. of Outputs | D107: No Results to be Delivered | E107: Performance for Each Result | K107: Overall Performance
E108: Exceptional | F108: Above Expectation | G108: Meets Expectation | H108: Needs Improvement | I108: Below Minimum Expectation | J108: Not Assessed
E109: Above 100% | F109: 70% -100% | G109: 60% - 69% | H109: 40% - 59% | I109: Below 40% | J109: N/A | K109: Performance | L109: Rating
B111: Ministry of Works
A112: 1 | B112: Continued provision of Critical Infrastructure including Regional and Township Roads, Bridges/Culverts for Inclusive and Sustainable Economic Growth and improved Socioeconomic Wellbeing of the People. This includes new constructions, rehabilitation and routine maintenance. | C112: 1 | D112: 7 | E112: 4 | F112: 0 | G112: 0 | H112: 2 | I112: 1 | K112: ='[2]6. Min. of Works'!I16 -> 0.76428571 | L112: Very Good (Above Expectation)
B114: Total | C114: =SUM(C105:C112) -> 1 | D114: =SUM(D105:D112) -> 7 | E114: =SUM(E105:E112) -> 4 | F114: =SUM(F105:F112) -> 0 | G114: =SUM(G105:G112) -> 0 | H114: =SUM(H105:H112) -> 2 | I114: =SUM(I105:I112) -> 1 | J114: =SUM(J105:J112) -> 0 | K114: =SUM(K105:K112) -> 0.76428571 | L114: Very Good (Above Expectations)
B116: Min. of Power & Energy (State Electricity Board)
A118: 1 | B118: To improve access to realizable and affordable energy for the citizens through development of conventional energy sources | C118: 3 | D118: 8 | E118: 2 | F118: 0 | G118: 0 | H118: 2 | I118: 2 | J118: 2 | K118: ='[2]7. Power'!H14 -> 0.56083333
B119: Total | C119: =SUM(C116:C118) -> 3 | D119: =SUM(D116:D118) -> 8 | E119: =SUM(E116:E118) -> 2 | F119: =SUM(F116:F118) -> 0 | G119: =SUM(G116:G118) -> 0 | H119: =SUM(H116:H118) -> 2 | I119: =SUM(I116:I118) -> 2 | J119: =SUM(J116:J118) -> 2 | K119: =SUM(K116:K118) -> 0.56083333 | L119: Fairly Ok (Needs Improvement)
...

Sheet 1. OHOS
A1: OFFICE OF THE HEAD OF SERVICE (Publi Service Reforms and Service Delivery Improvement Initiatives
A2: FULL YEAR [JANUARY TO DECEMBER 2024] PERFORMANCE ASSESSMENT
A3: No. of Ops | B3: Expected Outputs for Delivering the Outcome Targets | C3: Output KPIs | D3: Results No. | E3: 2024 Target | F3: Jan. - Dec Results | G3: Performance | H3: Adjusted Performance | I3: Evidences
A4: OUTPUT LEVEL FRAMEWORK - OFFICE OF THE HEAD OF SERVICE
A5: Commitment-1: Sustain Improvement of Public Service Delivery through an optimized State Civil Service by the Principles of rewards and sanctions
B6: Enhanced Personnel and Organizational Productivity through their mandates, job descriptions and performance target with Annual State Productivity Awards | C6: Organisational Productivity Level | D6: 1 | E6: 70 | F6: NA | G6: Not Assessed | H6: Not Assessed | I6: Measurement Yardstick not defined yet. | J6: What is the yardstick of measurement?
C7: No. of staff that are rewarded for recorded outstanding performance | D7: 2 | E7: 10 | F7: 0 | G7: =F7/E7 -> 0 | H7: =G7 -> 0 | J7: Is he a staff or citizen of Jigawa State?
C8: No. of staff that are sanctioned for recorded poor performance | D8: 3 | E8: 10 | F8: 10 | G8: =F8/E8 -> 1 | H8: =G8 -> 1 | I8: Scores of staff were sanctioned following recommendations by a Whitepaper Committee. The MDAs included Ministry of Health and Tertiary Educational Institutions
C9: No of MDAs introduced to Corporate Planning | D9: 4 | E9: 5 | F9: 5 | G9: =F9/E9 -> 1 | H9: =G9 -> 1 | I9: The organisational structures functions and mandates of MDAs superviced by HoS have been completed | J9: OHOS, Manpower Development & Training,
C10: Executive Orders Issued on Development and Implementation of Service Charters in MDAs (No. of E.O Provisions implemented | D10: 5 | E10: 10 | F10: 0 | G10: =F10/E10 -> 0 | H10: =G10 -> 0 | I10: Servicom not yet reactivated and Exe. Order Issued
C11: Number of comprehensive service charters in MDAs (New and Reviewed) with bi-annual report from SERVICOM | D11: 6 | E11: 10 | F11: 0 | G11: =F11/E11 -> 0 | H11: =G11 -> 0 | I11: Servicom will soon be reactivated
C12: Average Performance | I12: =AVERAGE(H6:H11) -> 0.4
A13: Commitment 2: Merit based Staff Recruitment in Ministries, Departments and Agencies (especially in professional and technical cadres) to fill critical manpower gaps in public service and other sectors to allow for optimal performance
A14: 2 | B14: New staff recruitment to fill criticall manpower gaps especially in Public Service Delivery Sectors | C14: % of staff needs that are met through recruitments across all MDAs | D14: 1 | E14: 5 | F14: 5 | G14: =F14/E14 -> 1 | H14: =G14 -> 1 | I14: 560 college of nursing and midwives, 827 in Ministry of Health - 1225 in Subeb - 272 First Class in MoHEST - 187 in Nomadic and 130 Vet Dr's in MoA | J14: This is looking for the staff needs of all MDAs in the State and what % of such needs were met.
C15: % of Recruited staff that are females | D15: 2 | E15: 10 | F15: 10 | G15: =F15/E15 -> 1 | H15: =G15 -> 1 | I15: PROVIDE NO. OF FEMALES AND TOTAL RECRUITMENT
C16: % of Recruited staff that are people with disabilities | D16: 3 | E16: 0.05 | F16: =28/3210 -> 0.0087227414 | G16: =F16/E16 -> 0.17445483 | H16: =G16 -> 0.17445483 | I16: 2No. Disabled in Momadic and 26 in SUBEB
C17: Skill/Manpower Gaps Analysis conducted across all MDAs and periodically updated (Number of MDAs covered / reviewed) | D17: 4 | E17: 91 | F17: 80 | G17: =F17/E17 -> 0.87912088 | H17: =G17 -> 0.87912088 | I17: 80 mainstream MDA workforce planning has been completed, the remaining 11 are tertiary instituitions and some health facilities | J17: Evidence needed - the MPA document
C18: Average Performance | I18: =AVERAGE(H14:H17) -> 0.76339393
A19: Commitment-3: Ensure effectiveness and Sustainability of the State Pension Schemes
A20: 3 | B20: Gratuity and Monthly Pension paid as when due | C20: Percentage of retired staff paid their gratuity as when due | D20: 1 | E20: 100 | F20: 98.98 | G20: =F20/E20 -> 0.9898 | H20: =G20 -> 0.9898 | I20: N6,965,000,000 was paid to 2642 out of about ….. persons were paid gratuity and death benefits.
C21: Percentage of retired staff paid their monthly pension as when due | D21: 2 | E21: 100 | F21: 100 | G21: =F21/E21 -> 1 | H21: =G21 -> 1 | I21: 17,029 pensioners were paid the sum of N6,965,912,178.17
C22: Conduct of ActuRIal Valuation | D22: 3 | G22: NA | H22: Not Assessed | I22: Upcoming Review of RF
C23: Implementation of ActuRIal Valuation Report | D23: 4 | G23: NA | H23: Not Assessed | I23: Upcoming Review of RF
C24: Average Performance | I24: =AVERAGE(H20:H23) -> 0.9949
A25: Commitment-4: Manpower and Human Resource Development in the State Public Service to ensure that MDAs are manned and managed by competent, proficient and skilled manpower
A26: 4 | B26: Human Recource Development in the State Public Service to ensure it is manned and managed by competent proficient, and skilled manpower in-line with the professional standards demanded by the peculiarities of each cadre for optimal performance | C26: No of training programmes implemented by the State MDI across various cadres in the State Civil Service | D26: 1 | E26: 18 | F26: 3 | G26: =F26/E26 -> 0.16666667 | H26: =G26 -> 0.16666667 | J26: Mention them (the training programmes)
C27: Number of Civil Servants Trained by State MDI across all MDAs covering various cadres | D27: 2 | E27: 540 | F27: 81 | G27: =F27/E27 -> 0.15 | H27: =G27 -> 0.15 | J27: Attendance sheet
C28: Total number of participated in short term Capacity Building Programme for Staff across MDAs | D28: 3 | E28: 300 | F28: 550 | G28: =F28/E28 -> 1.8333333 | H28: 1.01 | I28: 100 trained on e-governance, 50 on public service management, 150 on enhanding producitivity and 250 on digital transformation. | J28: Attendance sheet
C29: Number of staff trained on long term Programme through In-Service Training and other established collaborations with tertiary institutions. | D29: 4 | E29: 1000 | F29: 918 | G29: =F29/E29 -> 0.918 | H29: =G29 -> 0.918 | I29: 902 Inservice Training - 16 Doctors on Residency Training were sponsored | J29: Need for only 2024
C30: Number of staff trained through professional bodies on their task related skills | D30: 5 | E30: 150 | F30: 32 | G30: =F30/E30 -> 0.21333333 | H30: =G30 -> 0.21333333 | I30: Funds are limited to revolving payment of professional loan: N11,200,000 was paid to 32 applicants | J30: What is does this has to do with personal loan to staff?
C31: Repositioned and Improved Perforamance of the State MDI as assessed by No. of programmes mounted by the Institute across State MDAs, LGAs and others | D31: 6 | E31: 27 | F31: 5 | G31: =F31/E31 -> 0.18518519 | H31: =G31 -> 0.18518519 | J31: ??????
C32: Repositioned and Improved Perforamance of the State MDI as assessed by No. of people trained by the Institute across State MDAs, LGAs and others | D32: 7 | E32: 1080 | F32: 320 | G32: =F32/E32 -> 0.2962963 | H32: =G32 -> 0.2962963 | I32: The breakdown of additional 49 is as follows 32 Computer Certificate - 13 Professional Diploma and 4 Coding | J32: ??????
C33: Attainment of Annual Revenue Estimates (Targets as per Approved Budget) by the Manpower Development Institute | D33: 8 | E33: 90 | F33: 9.32 | G33: =F33/E33 -> 0.10355556 | H33: =G33 -> 0.10355556 | I33: Only about 54.72 million reported against a target of N587 million as per 2024 AFS which amounts to less than 10% | J33: =104.5/194 -> 0.53865979
C34: Annual growth in revenues generated by MDI | D34: 9 | E34: 10 | F34: 0 | G34: =F34/E34 -> 0 | H34: =G34 -> 0 | I34: Actual collection in 2023 was about N112.47 million against N54.72 in 2024 - declines of over 51.3% (2024 AFS)
C35: Resuscitated State Manpower Committee as assessed by qualitative bi-annual reports submitted to the State Executive Council | D35: 10 | E35: 4 | F35: 3 | G35: =F35/E35 -> 0.75 | H35: =G35 -> 0.75 | I35: 3 reports for workforce gap analysis were presented by the HoS to the State Exco (Workforce Technical Committee serving as Manpower Committee)
C36: Average Performance | I36: =AVERAGE(H26:H35) -> 0.3793037
C37: Overall Average Performance | G37: =AVERAGE(G27:G36) -> 0.49441152 | H37: =AVERAGE(H6:H36) -> 0.51601965
D43: a

Sheet 2. SSGs Office
A1: OFFICE OF THE SECRETARY TO THE STATE GOVERNMENT (SPECIAL SERVICES DIRECTORATE)
A2: FULL YEAR [JANUARY TO DECEMBER 2024] PERFORMANCE ASSESSMENT
A3: No. of Ops | B3: Expected Outputs for Delivering the Outcome Targets | C3: Output KPIs | D3: Results No. | E3: 2024 Target | F3: Jan. - Dec Results | G3: Performance | H3: Adjusted Performance | I3: Evidences
A4: Commitment 1: Work with the relevant agencies to create Jigawa State Joint Intelligence Fusion Center for command, communication and control under the relevant agencies to have a Single Security Coordination Center.
A5: 1 | B5: Sustained Support for Security Operations and Community Policing through effective collaboration between the State & Local Governments, Security Agencies, Emirate Councils, Local Vigilantes, and other Critical Stakeholders in the State Security Arctecture | C5: % Progress in streamlinng Joint Security Operations based on an Established and Functional Single Security Coordinating Center (SCC) | D5: 1 | E5: 0.6 | F5: 0.5 | G5: =F5/E5 -> 0.83333333 | H5: =G5 -> 0.83333333
C6: Number of community security cases and social vices (theft, robbery, drug-related offences, etc) cases intervened/mitigated through the Joint Security Operations | D6: 2 | E6: 20 | H6: NA | I6: Newly Set
C7: Number of potential conflicts & disputes (e.g., farmers/herders conflicts, border disputes, etc.) mitigated annually through Community-Policing and other proactive means with early-warning signals. | D7: 3 | E7: 10 | H7: NA | I7: Newly Set
C8: State Security Council meets at least Quarterly to consider reports and strategies for sustained security vigilance | D8: 4 | E8: 4 | F8: 4 | G8: =F8/E8 -> 1 | H8: =G8 -> 1
C9: No. of Targetted Stakeholder Engagements, including the Security Agencies, Traditional Institutions, and the Ulamas efforts to maintain Peace and Security in the State through effective collaboration and dialogue | D9: 5 | E9: 4 | F9: 3 | G9: =F9/E9 -> 0.75 | H9: =G9 -> 0.75 | I9: Three Meetings Held with Stakeholders from Guri Local Government on Peaceful Coexistence Between Farmers and Herdsmen Chaired by the Governor
H10: Average Score | I10: =AVERAGE(H8:H9) -> 0.875
A11: Commitment 2: Launch the Community Peace Initiative (CPI) as a performance- based grant to promote peacekeeping and attract development to the communities
A12: 2 | B12: Performance based grants given to CPIs for peace keeping performance | C12: Number of CPIs that have Received Performance Grants | D12: 6 | E12: 3 | G12: NA | H12: NA | I12: Not Yet Commenced
H13: Average Score | I13: NA
A14: Commitment 3: Empower the traditional institutions to maintain and regularly update the data of residents and newcomers to curtail and prevent the infiltration of criminals
A15: r | B15: Database of residents in the State updated | C15: Percentage of the population of residents whose data have been capture in the state security database | D15: 7 | E15: 50 | G15: NA | H15: =G15 -> NA | I15: Not Assessed
H16: Average Score | I16: NA
A17: Commitment 4: Facilitate partinerships between law enforcement tagencies and residents, there by improving trust between the law enforcement agencies and residenta and ignite the free flow of accurate information from the residents regarding criminal activities in thier community
A18: 4 | B18: Improve residents perception of trust on the law enforcement agencies | C18: Residents perception on confidence in security enforcement agencies (opinion pool) | D18: 8 | E18: 0 | G18: NA | H18: =G18 -> NA | I18: Not Assessed
H19: Average Score | I19: NA
A20: Commitment 5: Intergrate the various local security outfits and equip them with relavent non-lethal tools and better support in terms of logistics training and intellegece as part of the stratgy to improve our vigillance service.
A21: 5 | B21: Community Security guards officers intigated into the police system | C21: Number of Trained Community Security Guards recruited to support security efforts in Government Institutions and Public Places | D21: 9 | E21: 900 | F21: 900 | G21: =F21/E21 -> 1 | H21: =G21 -> 1 | I21: Over 9,000 Security Guard Officers recruited and trainined through private security agencies
C22: Propotion of the trained Community Security Guards integrated into formal security systems | D22: 10 | E22: 0.9 | F22: 1 | G22: =F22/E22 -> 1.1111111 | H22: 1.01 | I22: All 900 Security Guards were trained
H23: Average Score | I23: =AVERAGE(H21:H22) -> 1.005
A24: Commitment 6: Continued support for community policing and strengthening of preventive mechanisms with effective enforcement of the relevant criminal laws in justice system administration.
A25: 3 | B25: Support for the establishment of Community Securty Guards based on a PPP Model | C25: Percentage of Progresss towards the establishment and functionality of Community Security Guard Office (CSGO) for strengthened Community Based Security Architecture | D25: 11 | E25: 60 | F25: 60 | G25: =F25/E25 -> 1 | H25: =G25 -> 1 | I25: Assuming CSGO is equivelent of Hisba, this much progress was achieved following recruiment / appointment of key personnel and submission of Hisba Bill to HoA
C26: Number of Community Security Guards Recruited, Trained, Empwered and Drafted into Community Policing Annually | D26: 12 | E26: =27*30 -> 810 | F26: 900 | G26: =F26/E26 -> 1.1111111 | H26: 1.01 | I26: This is represented by the 900 Recruited Personnel for Government Institutions
H28: Average Score | I28: =AVERAGE(H25:H26) -> 1.005
A29: Commitment 7: Collaboration with the relevant Federal Agencies in dealing with security threats and youth drug abuse through the nefarious activities of drug dealers in the Communities.
A30: 4 | B30: MultiSectoral Approach in the Crusade Against Drug Abuse | C30: Establishment and Functionality of a MultiSectoral Taskforce on the Security Threats by Local Drug Dealers, Canpaign Agaist Drug Abuse and Rehabilitarion of Drug Addicts | D30: 13 | H30: Not Assessed | I30: Newly Set
C31: Number of Local Drug Dealers Apprehended | D31: 14 | H31: Not Assessed | I31: Newly Set
C32: Number of Activities Conducted in the Campsign Against Drug Abuse | D32: 15 | H32: Not Assessed | I32: Newly Set
A33: 1 | B33: Community Security guards officers intigated into the police system | C33: Propotion of the trained community security guards officers that have been integrated into formal police force | D33: 16 | E33: 60 | F33: 0 | G33: =F33/E33 -> 0 | H33: =G33 -> 0 | I33: Not Achieved
H34: Average Score | I34: =AVERAGE(H30:H33) -> 0
A35: Commitment 8: Introduce and Operationalize Jigawa Security Trust fund to increase financing and support to national and local security forces
A36: 2 | B36: Establishment of Security Trust Fund for improved funding and support to Security Agencies including the implementation of Performance-based grants for Community-based Peace Initiatives | C36: Percentage Progress towards the establishment and Functionality of Security Trust Fund (Establishment, Legal Backing and Operations | D36: 17 | E36: 20 | F36: 5 | G36: =F36/E36 -> 0.25 | H36: =G36 -> 0.25 | I36: Memo has already put in place and waiting for approval by His Excellecy based on discussion at the Expanded
C37: % Increase in Mobilized Financial Resources Above Initial Seed Funds | D37: 18 | E37: 0.2 | F37: 0 | G37: =F37/E37 -> 0 | H37: =G37 -> 0 | I37: No Assessed
C38: Number of Community-based Peace Initiatives Supported through the Performance-based Grants | D38: 19 | E38: 60 | F38: 0 | G38: =F38/E38 -> 0 | H38: Not Assessed | I38: Not Yet Commenced
H39: Average Score | I39: =AVERAGE(H36:H38) -> 0.125
G40: Aggregate Score | H40: =AVERAGE(H5:H39) -> 0.68533333

Sheet 3. Min. of Special Duties
A1: MINISTRY FOR SPECIAL DUTIES
A2: FULL YEAR [JANUARY TO DECEMBER 2024] PERFORMANCE ASSESSMENT
A3: No. of Ops | B3: Expected Outputs for Delivering the Outcome Targets | C3: Output KPIs | D3: RAs No. | E3: 2024 Target | F3: Jan. - Dec Results | G3: Performance | H3: Evidences | I3: Adjusted Performance | J3: Remarks / Evidances
A4: DELIVERY PERFORMANCE MANAGEMENT FRAMEWORK
A5: Commitment 1 - Effectively and Effeciently Execute Emergency Response & Prepraredness in dealing with any form of disaster or emergencies in the State
A7: 1 | B7: Improved Effeciency and Effectiveness of Emergency relief and Disaster Mangement | C7: Timeliness in Response to Disaster Occurance | D7: 1 | G7: N/A | I7: =G7 -> N/A | J7: Not Assessed
C8: Number of MoUs signed with either Local or international Partners on disaster management | D8: 2 | E8: 5 | F8: 2 | G8: =F8/E8 -> 0.4 | I8: =G8 -> 0.4 | J8: PPFN collaborated with State Emergency Management Agency of Jigawa state as well as the State Ministry of Health throughout the outreach.LGA OF IMPLEMENATION: MIGA, KIYAWA, GWARAM, DUTSE OBJECTIVES OF THE ACTIVITY (The activity objective is what the activity aims to do, for example provide your perspective or deliver some sort of experience for the young people you work with. 2.Partner: Relief Rescue Initiative (RRI) Project Title: Emergency WASH and Multipurpose Cash Assistance to flood-affected Community in Jigawa State Location: Jahun, Miga, Kiri kasamma, Buji and Gwarama
C9: Percentage of household victims that received relief package during emergency | D9: 3 | E9: 100 | F9: 100 | G9: =F9/E9 -> 1 | I9: =G9 -> 1 | J9: 38,078 victims has fully received relief package during emergency | K9: Conprehensive reports will be submitted
C10: State emergency policy developed and operationalised | D10: 4 | E10: 1 | F10: 1 | G10: =F10/E10 -> 1 | I10: =G10 -> 1 | J10: Emergency Contingency Plan developed and publishe with support of UNICEF.
A11: 2 | B11: Emergency mangement committee established at State level in 27 local Government and at a ward level in specific flood-prone areas | C11: Numberof local Government that have fuctional emergency management committee | D11: 5 | E11: 12 | F11: 27 | G11: =F11/E11 -> 2.25 | I11: 1.01 | J11: LEMCs estarblished and trained across the 27 LGAs
C12: Percentage of political wards that have fuctional Emergency management committee | D12: 6 | E12: 20 | F12: 0 | G12: =F12/E12 -> 0 | I12: =G12 -> 0
C13: Average Performance
A15: DELIVERY PERFORMANCE MANAGEMENT FRAMEWORK
A16: Commitmen 2 Effectively and Effeciently Provide Support to Citizens of Jigawa State Seeking Enlistment in the Military, Paramilitary Organzations and Federal Establishments including the Provision of Guidance & Counselling Support to Youths in Jigawa State
A17: No. of Ops | B17: Expected Outputs for Delivering the Outcome Targets | C17: Output KPIs | D17: RAs No. | E17: 2024 Target | F17: Jan. - Dec Results | G17: Performance | H17: Evidences | J17: Remarks / Evidances
A18: 3 | B18: Support towards the placement of Citizens of Jigawa State in the Military, Paramilitary and other Federal Establishment | C18: No. of Jigawa Citizens Supported to be Enrolled in Military, Paramilitary and Federal Establishments | D18: 7 | E18: 1500 | F18: 1947 | G18: =F18/E18 -> 1.298 | H18: =G18/F18 -> 0.00066666667 | I18: 1.01 | J18: Target achieved due to the commitment of present administration in order to provide more employment.
C19: No. of Engagements with Federal Character Commission through the State Representative in the Employment of Jigawa Citizens in Federal Agencies | D19: 8 | E19: 6 | F19: 2 | G19: =F19/E19 -> 0.33333333 | H19: =G19/F19 -> 0.16666667 | I19: =G19 -> 0.33333333 | J19: Evidence and what was the outcome
A20: 4 | B20: Guidance and Counselling Support to Youths in Jigawa State | C20: No of Guidance & Counselling Activities Conducted across all the 27 LGAs in the State | D20: 9 | E20: 54 | F20: 10 | G20: =F20/E20 -> 0.18518519 | H20: =G20/F20 -> 0.018518519 | I20: =G20 -> 0.18518519 | J20: What are the LGs
C21: Average Performance
A22: DELIVERY PERFORMANCE MANAGEMENT FRAMEWORK
A23: Commitment 3 - Effectively and Effeciently Execute any Duty of Special Natuture required for the overall socioeconomi welbeing of the citizens of Jigawa State
A24: No. of Ops | B24: Expected Outputs for Delivering the Outcome Targets | C24: Output KPIs | D24: RAs No. | E24: 2024 Target | F24: Jan. - Dec Results | G24: Performance | H24: Evidences | J24: Remarks / Evidances
A25: 5 | B25: Effective Discharge of Other Special Duties | C25: No. of Palliative Shops Established in each LGA Headquarter | D25: 10 | E25: 27 | F25: 27 | G25: =F25/E25 -> 1 | I25: =G25 -> 1 | J25: Palliative Shops Established in each LGA and Headquarter
C26: No. of Palliative Shops Established in all 287 Political Wards in the State | D26: 11 | E26: 287 | F26: 27 | G26: =F26/E26 -> 0.094076655 | I26: =G26 -> 0.094076655 | J26: Ongoing project
C27: No. of other Major Special Duties Successfully Executed | D27: 12 | E27: 6 | F27: 1 | G27: =F27/E27 -> 0.16666667 | I27: =G27 -> 0.16666667 | J27: Free Ramadan feeding is provided across 27 LGAs iun 639 centres
C28: Average Performance | I28: =AVERAGE(I7:I27) -> 0.56356926

Sheet 4. Min. of LG
A1: MINISTRY FOR LOCAL GOVERNMENT & COMMUNITY DEVELOPMENT
A2: FULL YEAR [JANUARY TO DECEMBER 2024] PERFORMANCE ASSESSMENT
A3: DELIVERY PERFORMANCE MANAGEMENT FRAMEWORK
A4: No. of Ops | B4: Expected Outputs for Delivering the Outcome Targets | C4: Output KPIs | D4: No. of RAs | E4: 2024 Target | F4: Jan - Dec Results | G4: Performance | H4: Adjusted Performance | I4: Remarks / Evidences
A5: Commitment 1: Strengthen Community Based Security Architecture
A7: 1 | B7: Community Guards Coordinating Unit established and Fuctional at State and Local Governments | C7: Number of Local Governments Councils that have Functional Community Guards Coordinating Units. | D7: 1 | E7: 6 | F7: 10 | G7: =F7/E7 -> 1.6666667 | H7: 1.01 | I7: There are Six (6) LGCs in the State that have Functional Community Guards Coordinating Units, the Local Government are Mallam Madori, Kafin Hausa, Birnin Kudu, Maigatari, Kaugama, Yankwashi, Gumel, Birniwa, Gwaram, and Guri Local Government Councils.
I8: =AVERAGE(H7) -> 1.01
A9: Commitment 2: Launch the Community Peace Initiative (CPI)as a Performance-based grant to improve service delivery and overall socioeconomic development at the Community level
A10: 2 | B10: Support Community Based Projects across the State | C10: Number of Community Led Projects Financed | D10: 1 | E10: 50 | F10: 23 | G10: =F10/E10 -> 0.46 | H10: =G10 -> 0.46 | I10: There are twenty one (21)No. Community Led Project Financed in the Ten ( 10) LGAs in the State. The Supported Communities include the following: 1 - Kungiyar Cigaban Kewaye, Lafiya Ward - The Constructed a Mosque to Linter Stage. 2 - Lafiya Youth Association - The Constructed a Mosques to Linter Stage. 3 - Birnin Kudu Youth Association - They Planted 2,000 Trees at FMC Birnin Kudu New Site. 4 - Mafitar Matasan Birnin Kudu Yau da Gobe - They Cleared Grave Yard at Birnin Kudu and Cleared Grasses at Birnin kudu General Hospital. 5 - Kaugama Development Association - Support in the Completion of Kaugama Central Mosque. 6 - Gawon Bariki Development Association (Dakayyawa) - The Constructed Islamiyya School to Linter Statge. 7 - Hospital Friends Committee - The Constructed One Block to Linter Stage at Kafin HausaaGenenal Hospital. 8 - Dantanoma Self-Help Group - The Constrcted Islamiyya School to Linter Stage. 9 - Mele Development Association - They Constructed Mosque to Linter Stage. 10 - Maigatari Development Association - They Constructed Mosque to Linter. 11 - Maigatari Foundation - They Constructed Islamiyya School to Linter Statge. 12 - Sabuwar Unguwar Kiyawa Self-help Group - They Constructed Mosque to Linter Stage. 13 - Kungiyar Cigaban Unguwar Galadanci - They Constructed 1/3 Mosque. 14 - Gumel Emirate Foundation - Four LGAs from the emirate Renovated and completed the Main Building and Guess Rooms for the Organistion.
I11: 9- MELE DEVELOPMENT ASSOCIATION. They Constructed Mosque to Linter Stage. 10- MAIGATARI DEVELOPMENT ASSOCIATION. They Constructed Mosque to Linter. 11- MAIGATARI FOUNDATION. They Constructed Islamiyya School TO Linter Statge. 12- SABUWAR UNGUWA KIYAWA SELP-HELP GROUP. They Constructed Mosque to Linter Stage. 13- KUNGIYAR CIGABAN UNGUWAR GALADANCI. They Constructed 1/3 Mosque. 14- GUMEL EMIRATE FOUNDATION .four LGAs from the emirate Renovated and completed the Main Building and Guess Rooms for the Organistion
I12: 15- BIRNIN KUDU YOUTH ASSOCIATION (B.Y.A) has constructed Islamiyya to Linter Stage and Completed by the Birnin Kudu Local Govt. 16 - MURYA BIRNIN KUDU has renovated 2blocks at Zango Primary School Birnin Kudu 17 - KAYA DEVELOPMENT ASSOCIATION Garki L.G Constructed Friday Mosque to Linter at KAYA Village 18 - NATO MOTOR PARK DUTSE L.G constructed a Five (5) daily prayer Mosque to linter stage at the Motor park. 19 - SULE TANKARKAR SERLF GROUP: Constructed a five (5) daily Prayer Mosque to Completion Stage at Sule Tankarkar Town. 20 - ALTIMA MALAM UBALI SEVEN DEVELOPMENT ASSOCIATION : Constructed 1block of Islamiyya school to completion stage at Babura Town 21 - LAFKA SELF HELP GROUP Kaugama LG Constructed a five daily Prayer Mosque To Completion Stage at Kagama.
I13: =AVERAGE(H10:H13) -> 0.46
A14: Commitment 3: Create an Elders Advisory Committee (ELCO) in every Local Government to Advise Government On variours government programs and implementations strategies for
A15: 3 | B15: Elders Advisory Committee Fuctional in the 27 Local Governments | C15: Number of Locsl Government Councils with Functional Elders Advisory Committee. | D15: 1 | E15: 10 | F15: 6 | G15: =F15/E15 -> 0.6 | H15: =G15 -> 0.6 | I15: We mobilised self help Group and Development Associations Toward Communty engagement in Government Policies and Objectives at 6 Local Government of the state. The six Local Government Include: HADEJIA, BIRNIN KUDU, GUMEL, KAZAURE, KIYAWA AND RINGIM. - The Elders Advisory Committe Established in OCTOBER 2024 and the Names of the Community Members will be collected after the completion of the 21 Local Government of the State for inauguration by FEB 2025 and Functional at the same Month. - There is also a refresentatives of One persons from each Wards Across the State and the committee set of 2 women as Gender Refresentatives from each LG. - Therefore the Committee consisted of 12No. Persons From each Local Government.
I16: =AVERAGE(H15) -> 0.6
A17: Commitment 4: Entrench an effective financial management system alongside improved policy and strategy across all the Local Governments with the support and collaboration with Development Partners.
A18: 4 | B18: Development Plan Formulated for the 27 Local Governments. | C18: Percentage of LGA that have Developed First Generation Local Government Development Plan (LGDP) | D18: 1 | E18: 100 | F18: 80 | G18: =F18/E18 -> 0.8 | H18: =G18 -> 0.8 | I18: All the 27 LGCs have Developed First Generation Local Government Development Plan, and the Validation and Printed will soon be undertaken
C19: Percentage of LGA that upgraded their Annual Buddget to IPSAS Standards based on National Chart of Accounts | D19: 2 | E19: 40 | F19: 35 | G19: =F19/E19 -> 0.875 | H19: =G19 -> 0.875 | I19: All the 27 LGCs has upgraded their programmers of budgeting to the IPSAS Accounting Standards and 2023 , 2024 and 2025 Budget are in form of IPSAS .
C20: Performance | I20: =AVERAGE(H18:H19) -> 0.8375
A22: Commitment-5: Sustain Improvement of Public Service Delivery and Institutional Reforms at the Local Government Level (Street Lghts, Water Supply, SERVICOM, etc)
A23: 5 | B23: Functionality of LGA Streetlights across the LGAs (Maintenance, Diesel, etc) | C23: Average number hours Streetlights function on a daily Basis | D23: 1 | E23: 12 | F23: 11 | G23: =F23/E23 -> 0.91666667 | H23: =G23 -> 0.91666667 | I23: The Streetlight are Functioning 11 Hours daily but initial Hours is from 6 to 6, due to change of whether, sometime Longer day shorter night.
A24: 6 | C24: Number of Diesel Streetlight Projects Converted to Solar | D24: 2 | E24: 15 | G24: =F24/E24 -> 0 | H24: =G24 -> 0 | I24: No any Diesel Streetlight Converted to Solar, but resolved to be undertaken in 2025 fiscal year and were already captured in the Approved Budget. There are 10 LGAs that areto be covered. The LGAs Include: GUMEL, HADEJIA, RINGIM, KAZAURE, RONI, AUYO, GAGARAWA, TAURA, KAFIN HAUSA AND KIYAWA .
A25: 7 | C25: Number of days before non-funtional Streetlights in LGAs are Fixed. | D25: 3 | E25: 14 | F25: 14 | G25: =F25/E25 -> 1 | H25: =G25 -> 1 | I25: Is Fourteen Days (14) before non-Functional Streetlights in LGCs are Fixed Armour Cables are Regularly Distributed to all 27 Local Governments according to their demand
I27: =AVERAGE(H23:I25) -> 0.63888889
C28: Performance
C29: Overall Performance | H29: =AVERAGE(H7:H28) -> 0.70770833

Sheet 5. Min. of Budget
A1: JIGAWA STATE MINISTRY OF BUDGET & ECONOMIC PLANNING
A2: FULL YEAR [JANUARY TO DECEMBER 2024] PERFORMANCE ASSESSMENT
A3: No. of Ops | B3: Expected Outputs for Delivering the Outcome Targets | C3: Output KPIs | D3: Results No. | E3: 2024 Target | F3: Jan -Dec Actuals | G3: Performance | H3: Adjusted Performance | I3: Remarks / Evidances
A4: DELIVERY PERFORMANCE MANAGEMENT FRAMEWORK
A5: Commitment 1: Commitment 1: Mobilization of Local and International Development Organizationand Effective Donor coordination
A7: 1 | B7: The scope of development support and technical assistance with International Development Partners widened | C7: Number of Development Partners / Programs Operating in the State | D7: 1 | E7: 25 | F7: 25 | G7: =F7/E7 -> 1 | H7: =G7 -> 1 | I7: List of Development Partners available
C8: Number of Programmes being supported by Development Partners in the State (exisiting and new). | D8: 2 | E8: 33 | F8: 42 | G8: =F8/E8 -> 1.2727273 | H8: 1.01 | I8: Programmes supported by Development Partners provided
C9: Increase in the Quantum of Resources coming to the State from Development Partners | D9: 3 | E9: 100 | G9: NA | H9: =G9 -> NA | I9: Not Assessed
C10: Percentage of financing gap of State Development plan filled by the ODA | D10: 4 | E10: 70 | F10: 24 | G10: NA | H10: =G10 -> NA | I10: Not Assessed
C11: Functionality of Development Partners Forum (Percentage of Quarterly Meetings Conducted) | D11: 5 | E11: 4 | F11: 0 | G11: =F11/E11 -> 0 | H11: =G11 -> 0
C12: Extent of JIMAF Implementation across MDAs and Initiatives | D12: 6 | E12: 90 | F12: 40 | G12: =F12/E12 -> 0.44444444 | H12: =G12 -> 0.44444444 | I12: Assumed
C13: Performance | I13: =AVERAGE(H7:H12) -> 0.61361111 | J13: =I13 -> 0.61361111
A14: Commitment 2: Improved Governance & Accountability through sustained Public Expenditure and Financial Management Reforms / Fiscal Sustainability.
A15: 2 | B15: Establishment of a Functional PFM Core Group to Sustain Fiscal and Financial Management Reforms. | C15: Functionality of PFM Core Group (Minmum of 4 Quarterly Meetings and 2 Key Governance Reform Activities such as Training Workshops) | D15: 1 | E15: 7 | F15: 3 | G15: =F15/E15 -> 0.42857143 | H15: =G15 -> 0.42857143 | I15: Only three PFM Core Groups Meetings Held during the year
C16: Conduct of Annual Report on Rapid Performance Assessment of PFM Indicators and Percentage Target Score of 75% | D16: 2 | E16: 75 | F16: 0 | G16: =F16/E16 -> 0 | H16: =G16 -> 0 | I16: RAPID PFM Assessment Not condicted
C17: Bi-annual Reports on the Implementation of PFM Reform Sustainability Plan by the Core Group | D17: 3 | E17: 2 | F17: 0 | G17: =F17/E17 -> 0 | H17: =G17 -> 0 | I17: No report available
A18: 3 | B18: Citizens Engagement in PFM Reforms | C18: Functionality State OGP ( 4No. Quaterly Meetings, and 2 bi-annual reports on the Implementation & Monitoring State OGP Work Plan | D18: 4 | E18: 6 | F18: 2 | G18: =F18/E18 -> 0.33333333 | H18: =G18 -> 0.33333333 | I18: Inauguration and Maiden Meeting Held and signing of SAP
C19: Extent of Citizens Participation in Governance | D19: 5 | E19: 90 | F19: 80 | G19: =F19/E19 -> 0.88888889 | H19: =G19 -> 0.88888889 | I19: Citizens are fully engaged in participating in Governance across all the three senatorial zones through the Town Hall meetings to generate citizens inputs for annual budgeting processes.
C20: Performance | G20: =AVERAGE(G15:G19) -> 0.33015873 | I20: =AVERAGE(H15:H19) -> 0.33015873 | J20: =I20 -> 0.33015873
A21: Commitment 3: Pursuit of Annual Planning and Budget Processes in line with the provisions of the State Budget Calander.
A22: 4 | B22: Timely Completion of all specific milestones covered in the Budget Calander | C22: Timely Publication of Quaterly Budget Implementation Reports | D22: 1 | E22: 4 | F22: 4 | G22: =F22/E22 -> 1 | H22: =G22 -> 1 | I22: Implementation Reports for all quarters (Q1 - Q4) published accordingly.
C23: Milestones in the Budget Calander | D23: 2 | E23: 7 | F23: 5 | G23: =F23/E23 -> 0.71428571 | H23: =G23 -> 0.71428571 | I23: MTEF and Budget Circular Timely Issued with Cielings. ASPER conducted
C24: Performance | I24: =AVERAGE(H22:H23) -> 0.85714286 | J24: =I24 -> 0.85714286
A25: Commitment 4: Expand the Coverage of Social Protection Program by bringing more people into the social register for poor and vulnerable citizens.
A26: 5 | B26: More poor and vulnerable Households covered in the State Social Register | C26: Percentage of Communities Covered by the State Social Register | D26: 1 | E26: 20 | F26: 16 | G26: =F26/E26 -> 0.8 | H26: =G26 -> 0.8 | I26: Due to additional of round 12 data on NSR
C27: Percentage of Poor and vulnerable Household Covered in the State Social Register | D27: 2 | E27: 70 | F27: 37 | G27: =F27/E27 -> 0.52857143 | H27: =G27 -> 0.52857143 | I27: Due to approval of the round 12 data for poor and vulnerable households, and also merging of NSR and RRR
C28: Percentage of the State's Population Covered in the social register | D28: 3 | E28: 15 | F28: 11 | G28: =F28/E28 -> 0.73333333 | H28: =G28 -> 0.73333333 | I28: Due to approval of the round 12 data for poor and vulnerable households, and also merging of NSR and RRR
A29: 6 | B29: More coverage to be achieved on poor and vulnarable households in the provision of basic social services, including the elderly and the most vulnerable segment of the state | C29: Percentage of coverage of the poor and vulnarable households that include elderly and the most vulnarable segment in the social register | D29: 4 | E29: 20 | F29: 17 | G29: =F29/E29 -> 0.85 | H29: =G29 -> 0.85 | I29: Due to approval of the round 12 data for poor and vulnerable households, and also merging of NSR and RRR
C30: Percentage of already empowered poor and vulnarable households that exists the social register | D30: 5 | E30: 15 | F30: 13 | G30: =F30/E30 -> 0.86666667 | H30: =G30 -> 0.86666667 | I30: NG-CARES and other social protection interventions
C31: Performance | I31: =AVERAGE(H26:H30) -> 0.75571429 | J31: =I31 -> 0.75571429
C32: Overall Performance | H32: =AVERAGE(H7:H31) -> 0.59988095 | J32: =AVERAGE(J7:J31) -> 0.63915675
C34: Conduct of ASPER/Agency Score Card
C35: Breakdown Budget Calander items
H41: \

Sheet 6. Min. of Works
A1: CRITICAL INFRASTRUCTURE SECTOR (ROADS & TRANSPORT DEVELOPMENT)
A2: FULL YEAR [JANUARY TO DECEMBER 2024] PERFORMANCE ASSESSMENT
A3: OUTPUT LEVEL RESULT FRAMEWORK - Ministry of Works
A4: No. of OPs | B4: Expected Outputs for Delivering the Outcome Targets | C4: Output KPIs | D4: Result No. | E4: Baseline (2023) | F4: 2024 Target | G4: Jan. - Dec Results | H4: Performance | I4: Adjusted Performance | J4: Remarks / Evidences
A5: January to June 2024 MDA/Sector Summary of Performance on Commitments
A7: Commitment 1: Continue provision of Critical Infrastructure including Regional and Township Roads, Bridges/Culverts for Inclsuive and Sustainable Economic Growth and improved Socieconomic Welbeing of the People. This includes new constructions, rehabilitation and routine maintenance.
A9: 1 | B9: Road Infrastructure Expanded | C9: Number of kilometer of New Regional Roads constructed | D9: 1 | E9: 3600 | F9: 3700 | G9: 3756 | H9: =(G9-E9)/(F9-E9) -> 1.56 | I9: 1.01 | J9: • S/Tankarkar -Garin Alko Rd - 30.5km • Kwanar Kuka – Tofa Road - 26km • Girinbo – Gantsa – Sara Rd - 46km • Yenleman-Kaugama-Madana - 30km • Shuwari-Chamo-Isari -5km • Maigari Babura - 19 km
C10: Number of kilometer of township roads constructed | D10: 2 | E10: 200 | F10: 230 | G10: =E10+2+2.3+5 -> 209.3 | H10: =(G10-E10)/(F10-E10) -> 0.31 | I10: =H10 -> 0.31 | J10: Wurno (2km), Kanya-Babba (3.5km), State Capital Roads (5 km),
C11: Number of kilometer of feeder roads constructed | D11: 3 | E11: 250 | F11: 300 | G11: 275 | H11: =(G11-E11)/(F11-E11) -> 0.5 | I11: =H11 -> 0.5 | J11: About 25 km of newly awarded 263 km of feeder roads completed as of Dec. 2024 including Chuwasu-Chakwaikwaiwa, Gagare - Karanka and
C12: Number of Major Box Culverts/Bridge constructed | D12: 4 | E12: 0 | F12: 10 | G12: 5 | H12: =(G12-E12)/(F12-E12) -> 0.5 | I12: =H12 -> 0.5 | J12: These include bridges/ culvers alomg Rabadi Gwaram-Basirka Road, Asayaya along B/Kudu-Kiyawa Road, Tsamiya - Yalwan Damai, Kiyako - Shungurin and Chaichai- Ringim
C13: Number of kilometer of regional roads Maintained | D13: 5 | E13: 400 | F13: 600 | G13: =765.4-140 -> 625.4 | H13: =(G13-E13)/(F13-E13) -> 1.127 | I13: 1.01 | J13: • Auyo – K/Hausa Road - 16km • B/Kudu – Kiyawa Road - 47km • Kiyawa – Jahun Road - 36.6km • Dutse – Gambari Road - 35.7km •Darai – Gilma Road - 9.5km •Kwalam – Gilma Road - 20km •Hantsu – Miga Road - 21.63km •Gumel-Gujungu-Jahun Road-39km
C14: Number of kilometer of township roads Maintained | D14: 6 | E14: 10 | F14: 15 | G14: 15.5 | H14: =(G14-E14)/(F14-E14) -> 1.1 | I14: 1.01 | J14: Rehabilitation of Gumel Toenship Roads (2.5) and B/Kudu (3.0 km)
C15: Number of kilometer of feeder roads Maintained | D15: 7 | E15: 100 | F15: 150 | G15: 157 | H15: =(G15-E15)/(F15-E15) -> 1.14 | I15: 1.01 | J15: *B/Kudu - Zazika -Nafara Road (50 Km) and Gumel Garin Gambo (7km)
C16: Overall Average Performance | I16: =AVERAGE(I9:I15) -> 0.76428571
C17: Number of kilometer of New Regional Roads constructed
C18: Number of kilometer of regional roads Maintained
C19: Number of kilometer of township roads Maintained
C20: Number of kilometer of feeder roads Maintained

Sheet 7. Power
A1: MINISTRY OF POWER AND ENERGY
A2: FULL YEAR [JANUARY TO DECEMBER 2024] PERFORMANCE ASSESSMENT
A3: OUTPUT LEVEL RESULT FRAMEWORK - POWER AND ENERGY
A4: Commitment 2: To improve access to realiable and affordable energy for the citizens through development of conventional energy sources
A5: No. of OPs | B5: Expected Outputs for Delivering the Outcome Targets | C5: Output KPIs | D5: Result No. | E5: 2024 Target | F5: Jan. - Dec Results | G5: Performance | H5: Adjusted Performance | I5: Evidences
A6: 1 | B6: Reliable access to Electricity from the National Grid Increase | C6: Number of Communities that are Connected to National Grid | D6: 1 | E6: 7 | F6: 8 | G6: =F6/E6 -> 1.1428571 | H6: 1.01 | I6: Sabo Garin A. Goje in Dutse LG, Duhuwa in Gumel LG, Dunbu in Yankwashi LG, Bayen Asibiti Quarters in Babura LG, Abuja quarters in Babura LG, Hydrabird in Gumel, NTA Qtrs. in Gumel, Nassarawa Qtr. in Gumel, Aigwa in Miga, Tudu Babba in B/Kudu, Unguwar Zango in K/hausa LGA. | J6: To select some site for physical verification | K6: Performance was doe to the interest of state Govt to provide more comm. With electricity
C7: Number of kilometer of 33/11kv - ITC Interconnected Lines | D7: 2 | E7: 90 | F7: 150 | G7: =F7/E7 -> 1.6666667 | H7: 1.01 | I7: ITC Auyo - Kafin Hausa, Kebberi to G/Gabas Tsohuwa in M/Madori, Zandam in Gwaram, Kawari in Kiyawa, Bulangu in K/Hausa and Fitare in Kazaure
C8: Number of Non Functional Transformers Replaced | D8: 3 | E8: 25 | F8: 8 | G8: =F8/E8 -> 0.32 | H8: =G8 -> 0.32 | I8: 1No. Jigawa State Radio Corporation, 1No. Grand Khadi & Chief Judge Res. 1No. Behind Jigawa State Radio Quart 1No. 744 Quarters in Dutse, 1No. Old Inec Qtrs. Dutse, 1No. Shagari Qtrs. Hadejia, 2No Gujungu Town in Taura L.G.A. | J8: To select some site for physical verification | K8: Low performance was due to lack of budgetary provision.
C9: Number of Non Functional Transformers Rehabilitated | D9: 4 | E9: 16 | F9: 2 | G9: =F9/E9 -> 0.125 | H9: =G9 -> 0.125 | I9: 300KVA, 33/0.415KV Transformer at Garun Gudunya Village in Babura L.G.A. , 200KVA , 33/0.415KV Transformer Sci. Sec. Sch. Lautai in Gumel L.G.A. | J9: To select some site for physical verification
A10: 2 | B10: Increased Unit of Power Generation and Distribution from the mini Grid | C10: Megawatt of Electricity Units Generated from mini - grid | D10: 5 | E10: 0 | H10: NA
C11: Megawatt of Electricity Units that was Generated from mini - grid Distributed | D11: 6 | E11: 0 | H11: NA
A12: 3 | B12: Development of renewable Energy | C12: Number of Town Provided with Solar Street Lights | D12: 7 | E12: 10 | F12: 5 | G12: =F12/E12 -> 0.5 | H12: =G12 -> 0.5 | I12: To provide evidence (list) | J12: This was assessed in the 2nd quarter 10% score
C13: Number of Stand-alone Solar Street Lights Provided or Rehabilitated in the State | D13: 8 | E13: 150 | F13: 60 | G13: =F13/E13 -> 0.4 | H13: =G13 -> 0.4 | I13: To provide evidence (list) | J13: This was assessed in the 2nd quarter 13% score
D14: Overall Average Performance | G14: =AVERAGE(G6:G13) -> 0.69242063 | H14: =AVERAGE(H6:H13) -> 0.56083333

Sheet 8. Min. of Comm
A1: MINISTRY OF COMMERCE
A2: FULL YEAR [JANUARY TO DECEMBER 2024] PERFORMANCE ASSESSMENT
A3: DELIVERY PERFORMANCE MANAGEMENT FRAMEWORK
A4: No. of OPs | B4: Expected Outputs for Delivering the Outcome Targets | C4: Output KPIs | D4: Result No. | E4: 2024 Target | F4: Jan. - Dec Results | G4: Performance | H4: Adjusted Performance | I4: Remarks / Evidence
A6: Commitment-1: Promoting Inclusive Participation in Economic Activities through Micro, Small and Medium Enterprises, Cooperatives, and Agriculture & Trade-based Associationsi. MSMEs, Cooperatives and Agriculture based Associations .
A8: 1 | B8: MSMEs, Cooperatives, Agriculture and Trade-based Associations captured in Database | C8: Number of MSMEs, (Cooperatives and Agricultural based associations) captured in Database | D8: 1 | E8: 3491 | F8: 1806 | G8: =F8/E8 -> 0.51733028 | H8: =G8 -> 0.51733028 | I8: Initial numbers of J-CARES beneficiaries was represented instead of number of Cooperatives registered | J8: To check the database for verification | K8: Data base will be readly availabe
A9: 2 | B9: Needs assessment of MSMEs and associations conductedii. Needs assessment of MSMEs and associations conducted | C9: Proportion of MSMEs including associations that are already in the database whose needs assessment conducted | D9: 2 | E9: 70 | F9: 502 | G9: =F9/E9 -> 7.1714286 | H9: 1.01 | I9: MSMEs were captured as a result of J-Cares Program
A10: 3 | B10: Capacity of MSMEs and associations enhanced based on identified needs | C10: Number of capacity building sessions on identified organizational needs conducted for the MSMEs | D10: 3 | E10: 9 | F10: 1 | G10: =F10/E10 -> 0.11111111 | H10: =G10 -> 0.11111111 | I10: J- CARES capcity building/ Sensitization across 3 Senetorial zones | J10: Dates, venues and attendance sheets | K10: 9/8/2024 at Gumel Emirate Foundation
C11: Number of MSMEs including associations trained on identified needs | D11: 4 | E11: 1040 | F11: 0 | G11: =F11/E11 -> 0 | H11: =G11 -> 0 | I11: to provide
A12: 4 | B12: Grants disbursed to selected MSMEs and associations | C12: Number of MSMEs including associations that received JCARES grants | D12: 5 | E12: =1548+12601 -> 14149 | F12: 12601 | G12: =F12/E12 -> 0.89059297 | H12: =G12 -> 0.89059297 | I12: Cluster of informal Co operative Societies for J-CARES | J12: 2024 is only needed | K12: The data is fro 9th Feb. - Dec. 2024
C13: Total amount of grants received by beneficiaries | D13: 6 | E13: 1500000000 | F13: 1264401000 | G13: =F13/E13 -> 0.842934 | H13: =G13 -> 0.842934 | I13: 1. Update report on the activities of J-Cares Result Area 3 SMEs from inception 2022 to December 2024. 2. BOI Disbursement Summary | J13: 2024 only should be presented | K13: The data is fro 9th Feb. - Dec. 2024
C14: Average Performance | I14: =AVERAGE(H8:H13) -> 0.56199473
A15: Commitment 2: Sustain and improve on the present effort of making Maigatari export processing zone a reality.
A16: 1 | B16: Operation license fee for Maigatari export processing zone paid | C16: Proportion of the operational license fee for Maigatari export processing zone paid | D16: 1 | E16: 0.7 | F16: 1 | G16: =F16/E16 -> 1.4285714 | H16: 1.01 | I16: 2024 Operational Liciense fully paid. | J16: How much and payment receipt is needed to verify | K16: 90,000,000.00 were paid on 18/07/2024
A17: 2 | B17: Promotional activities conducted to sensitise communities against vandalisation and attract investors to the zone | C17: Number of sensitization activities conducted with communities agaisnt vandalisation of properties in export processing zone | D17: 2 | E17: 4 | F17: 1 | G17: =F17/E17 -> 0.25 | H17: =G17 -> 0.25 | I17: Advocasy to Gumel Emirs Palace on Government's Plans to revitalised the EPZ with appeal for Community Support
C18: Number of active investors attracted to Maigatariexport processing zone | D18: 3 | E18: 5 | F18: 4 | G18: =F18/E18 -> 0.8 | H18: =G18 -> 0.8 | I18: 1.GOG MERCHANT AND TRADING. 2. STARLINK GLOBAL & IDEAL LTD. 3. S.I AMANA AGRI- COMMUDITIES LTD 4. Contraex
C19: Number of Transit warehouse certificatites issued for effective operation of Maigatari export processing zona | D19: 4 | E19: 100 | F19: 0 | G19: =F19/E19 -> 0 | H19: =G19 -> 0 | I19: It was not captured in 2024 Budget proposal
A20: 3 | B20: Leasing of Maigatari Boarder free zone to the private sectors operators to make the place viberant and enhance internaly generated revenue (IGR) | C20: Contribution to IGR from the Maigatari export processing zone | D20: 5 | E20: 170000000 | F20: 32081750 | G20: =F20/E20 -> 0.18871618 | H20: =G20 -> 0.18871618
C21: Number of Foreign Direct Investment (FDI) generated through Maigatari Export Free Trade (Processing) Zone | D21: 6 | E21: 2 | F21: 0 | G21: =F21/E21 -> 0 | H21: =G21 -> 0
C22: Value of foreign exchange earning generated through Maigatari export Processing zone | D22: 7 | E22: 340000000 | F22: 0 | G22: 0 | H22: =G22 -> 0
C23: Export Grownth rate of Maigatariexport proccessing zone | D23: 8 | E23: 10 | F23: 0 | G23: NA | H23: Not Assessed
C24: Percentage of Expoters that have Diversified their export product | D24: 9 | E24: 10 | F24: 0 | G24: NA | H24: Not Assessed
C25: Average Performance | I25: =AVERAGE(H16:H25) -> 0.32124517
A26: Commitment 3: Organze major and mini trade fairs on periodic basis to showcase the various business opportunities in the state
A27: 1 | B27: Trade Fair Conducted to showcase Agricultural Produce (raw and processed), Minerals Resources, Investment Opportunities and Technologiges, etc | C27: Number of Agricultural Products showcase in the trade fairs | D27: 1 | E27: 5 | F27: 0 | G27: NA | H27: Not Assessed | I27: Requires adequate budgetary provision and extensive colloboration
C28: Number of Mineral resources showcase in the trade fairs | D28: 2 | E28: 5 | F28: 0 | G28: NA | H28: Not Assessed | I28: - do -
C29: Average Performance | I29: NA
A30: Commitment 4: Intensify Domestic Tourism
A31: 1 | B31: State's Tourist Potentials developed in to actual Tourist attractions i.e Provision of necessary facilities & aminities | C31: Number of Tourists attracted into the State | D31: 1 | E31: 29436 | F31: 25000 | G31: =F31/E31 -> 0.84930018 | H31: =G31 -> 0.84930018 | I31: Tourists are coming during Sallah celebrations, Gani festival, Students of Institutions of learning for Excursion
C32: Number of Job Creation through Tourism | D32: 2 | E32: 1965 | F32: 1572 | G32: =F32/E32 -> 0.8 | H32: =G32 -> 0.8 | I32: Most of jobs created were Indirect jobs
C33: Average Performance | I33: =AVERAGE(H31:H32) -> 0.82465009
A34: Commitment 5: Improve Access to Financing
A35: 1 | B35: Sensitaization Workshops conducted in collaboration with Financial Institutions for enhaced access to business finance by small business owners | C35: Number of Sensitaization Workshops conducted in collaboration with Financial Institutions on enhanced access to business financing | D35: 1 | E35: 1 | F35: 2 | G35: =F35/E35 -> 2 | H35: 1.01 | I35: 1. Workshop 75 billion intervention funds in colaboration with BOI & Federal Government 2. Sensitization on SMEs business Clinic in colaboration with Jigawa Invest | J35: Attendance sheets is needed for verification
A36: 2 | B36: Public enlightment/Rodio programs broadcasted to expose all the available financial assistance/ Loan & how to accessed | C36: Number of Radio programs Conducted | D36: 2 | E36: 24 | F36: 36 | G36: =F36/E36 -> 1.5 | H36: 1.01
C37: Average Performance | I37: =AVERAGE(H35:H37) -> 1.01
A38: Commitment 6: Increase Market Access and International Trade Opportunities
A39: 1 | B39: More Trade Associations captured in Database | C39: Number of Trade Associations Captured in Database | D39: 1 | E39: 10 | F39: 9 | G39: =F39/E39 -> 0.9 | H39: =G39 -> 0.9 | I39: Records only in files need to be extracted and compiled into a database | J39: This Commitment is for Critical Infrastructure not Ministri of Commerce
A40: r | B40: Capacity building of Tradeassociations in the database conducted | C40: Number Capacity building sessions conduted with the Trade associations in the database | D40: 2 | E40: 5 | F40: 0 | G40: =F40/E40 -> 0 | H40: =G40 -> 0 | I40: None conducted
C41: Average Performance | I41: =AVERAGE(H39:H40) -> 0.45
A42: Commitment 7: Support the operation of Jigawa State Chamber of Commerce to drive the growth of Trade and Industries in the State.
A43: 1 | B43: Grants and Loans accessed by the members of trade trade associations that have been captured in the Ministry of Commerce Database | C43: Amount of grants accessed by the trade associations that were trained in collaboration with financial Institutions on business financing | D43: 1 | E43: 400000000 | F43: 0 | G43: =F43/E43 -> 0 | H43: =G43 -> 0 | I43: ?????
C44: Amount of Loan accessed by the trade associations that were trained in collaboration with financial Institutions on business financing | D44: 2 | E44: 400000000 | F44: 0 | G44: =F44/E44 -> 0 | H44: =G44 -> 0 | I44: ?????
C45: Average Performance | I45: =AVERAGE(H43:H44) -> 0
A46: Commitment 8: Capitalize Cooperatives, Agriculture-based Association and Social Enterprises Development
A47: 1 | B47: Enhanced enterprenureship skills of Cooperatives and Agriculture based association that are already in the Ministry database | C47: Number of Cooperatives and Trade Associations that were trained on enhancing enterprenuership skills | D47: 1 | E47: 1000 | F47: 300 | G47: =F47/E47 -> 0.3 | H47: =G47 -> 0.3 | I47: Trained under JCARES
C48: Number of informamal sector clustered Artisans that are registed for sub- contracting with the big contractors | D48: 2 | E48: 250 | F48: 0 | H48: Not Assessed | I48: Not Assessed
I49: =AVERAGE(H47:H48) -> 0.3
A50: Commitment 9: Support the Industrial Development of Jigawa State to promote Economic Development and Job Creation
A51: 1 | B51: Support the Establishment of Industries | C51: Progress toward the completion of Gagarawa Indistrial Park (% completion) | D51: 1 | E51: 75 | F51: 50 | G51: =F51/E51 -> 0.66666667 | H51: =G51 -> 0.66666667 | I51: Project ongoing ?? | J51: This Commitment is for Economic Empowerment & Youth Employment Agency not Ministri of Commerce
C52: Number of Industries / Manafacturing Companies established in the Park | D52: 2 | E52: 5 | F52: 1 | G52: =F52/E52 -> 0.2 | H52: =G52 -> 0.2 | I52: A wheat processing company established
C53: Average Performance | I53: =AVERAGE(H51:H52) -> 0.43333333
A55: Commitment 10: Development / Modernzation of Markets in the State to Support Trading Activities and Expand Revenue Generation
A56: 1 | B56: Establishment of Three Modern Markets (Hadejia, Dutse and Maigatari) | C56: Percentage Progress toward the Development of the Three Modern Markets in Hadejia, Dutse and Maigatari | D56: 1 | E56: 30 | F56: 10 | G56: =F56/E56 -> 0.33333333 | H56: =G56 -> 0.33333333 | I56: Project Feasibility Studies and Designs produced, projects sites identified, while preparation to commense procurement process for wall fencing was in progresss | J56: This Commitment is for Economic Empowerment & Youth Employment Agency not Ministri of Commerce
A57: 2 | B57: Development of Other Markets | C57: Number of Other New Markets Where Development is taking place | D57: 1 | E57: 3 | F57: 0 | G57: =F57/E57 -> 0 | H57: =G57 -> 0 | I57: None development in any new market
I58: =AVERAGE(H56:H57) -> 0.16666667
C59: Overall Performance | H59: =AVERAGE(H8:H58) -> 0.4496148

Sheet 9. Min. of Agric
A1: MINISTRY OF AGRICULTURE AND NATURAL RESOURCES
A2: FULL YEAR [JANUARY TO DECEMBER 2024] PERFORMANCE ASSESSMENT
A3: OUTPUT LEVEL RESULT FRAMEWORK - MINISTRY OF AGRICULTURE AND NATURAL RESOURCES
A4: No. of OPs | B4: Expected Outputs for Delivering the Outcome Targets | C4: Output KPIs | D4: Result No. | E4: 2024 Target | F4: Jan. - Dec. Results | G4: Performance | H4: Adjusted Performance | I4: Evidences
A5: Commitment-1: Development and Protection of Grazing Reserves
A7: 1 | B7: Grazing Reserves Developmet | C7: Hectares of Grazing Reserves Developed with Pastures | D7: 1 | E7: 22 | F7: Nil | G7: Nil | H7: NA | I7: Not Assessed
C8: No. of Water Points Provided in Grazing Reserves | D8: 2 | E8: 6 | F8: 4 | G8: =F8/E8 -> 0.66666667 | H8: =G8 -> 0.66666667 | I8: Six (6) wind powered watering facilities have been successfully converted to solar-powered systems in locations such as Zandauru, Tsakuwaram, Zuge Fulani and Arimari grazing reserve in Zinder Niger Republic. PICTURE ATTACHED
A9: 2 | B9: Grazing Protection | C9: No. of Grazing Reserves Demarcated. | D9: 3 | E9: 17 | F9: 12 | G9: =F9/E9 -> 0.70588235 | H9: =G9 -> 0.70588235 | I9: a) Out of 451 grazing reserves 12No. were demarcated.over 10,000 hecters of land demacated to prevent encrochiment and reduce conflicts. Areas demacated are Gwaram, Kiyawa, Dakaiyawa, Agin, Katanga, Barwa, Farin Dutse, Bagadaza, Kore Aoba, Zuzu Almazuzu, and Zuzo stock routes, (what are the 12No.) b) 439 undemarcated PICTURE ATTACHED
C10: Number of Grazing Reserves Gazetted | D10: 4 | E10: 5 | F10: 0 | G10: =F10/E10 -> 0 | H10: =G10 -> 0 | I10: Legal recognition and formalization of additional 20 grazing reserves to support sustainable livestock management and reduce disputes.No enough funds earmarked
C11: Hectares of Grazing Reserves Retrieved | D11: 5 | E11: 50000 | F11: 10000 | G11: =F11/E11 -> 0.2 | H11: =G11 -> 0.2 | I11: Gwaram, Kiyawa and Dakaiyawa/Agin stock route
A12: 3 | B12: Prevention and Resolution of Farmers-Herdmen Conflcts | C12: Number of Sensitization and Town Hall Meetings on conflict management and conflict resolution conducted for Farmers and Herdsmen | D12: 6 | E12: 10 | F12: 3 | G12: =F12/E12 -> 0.3 | H12: =G12 -> 0.3 | I12: These include Emirate & LGA level Sensitization by the State Committee and within Guri LGA
C13: Establishment of Security Committees on Farmer-Herdsmen Conflicts | D13: 7 | E13: 2 | F13: 2 | G13: =F13/E13 -> 1 | H13: =G13 -> 1 | I13: State Committee and Guri Local Government Area Committee
C14: Functionality of Security Committee on Farmer-Herdsmen Conflicts based on Number of Meetings | D14: 8 | E14: 12 | F14: 11 | G14: =F14/E14 -> 0.91666667 | H14: =G14 -> 0.91666667 | I14: Eleven Meetings Held
C15: Number of conflict management sensitization held with farmers and herdmen' | D15: 9 | E15: 6 | F15: 4 | G15: =F15/E15 -> 0.66666667 | H15: =G15 -> 0.66666667 | I15: a) 1No. at Niger Republic (Zinder) between Jigawa and Niger b) 3No. at 3 Senatorial districts covering 27 LGs PICTURE ATTACHED
F16: Overall Average Performance | I16: =AVERAGE(H7:H15) -> 0.55698529
A17: OUTPUT LEVEL RESULT FRAMEWORK - MINISTRY OF AGRICULTURE & NATURAL RESOURCES
A18: Commitment 2: Development and sustained support for cluster farmers
A19: 1 | B19: Establishment and Support for Cluster farms | C19: Number of Cluster farms Newly established | D19: 1 | E19: 1000 | F19: 852 | G19: =F19/E19 -> 0.852 | H19: =G19 -> 0.852
C20: Number of Farmers Supported under Newly Established Clusters | D20: 2 | E20: 50000 | F20: 45000 | G20: =F20/E20 -> 0.9 | H20: =G20 -> 0.9 | I20: Wheat (39,000No,), Rice (5,000No.), Others (1,000No.)
C21: Number of Previously Established Cluster farms Sustained | D21: 3 | E21: 900 | H21: NA | I21: Not Assessed
F22: Overall Average Performance | I22: =AVERAGE(H19:H21) -> 0.876
A23: Commitment 3: Support Capacity Enhancement for Value Addition in Agricultural Produce Processing and Marketing
A24: 1 | B24: Grain processing devices procured | C24: Number of processing device provided | D24: 1 | E24: 150 | F24: 470 | G24: =F24/E24 -> 3.1333333 | H24: 1.01 | I24: The processing device is Grinding machines PICTURE ATTACHED
A25: 2 | B25: Farmers capacity enahnced on processing of grains | C25: Number of training conducted on grain processing and marketing | D25: 2 | E25: 6 | F25: 2 | G25: =F25/E25 -> 0.33333333 | H25: =G25 -> 0.33333333 | I25: Processing device (Grinding Machines) were distributed in 2 phases and each phase benefited from the training on grain processing and marketing. The trainings were conducted between January to June 2024 (1st and 2nd phase)
C26: Number of beneficiaries of the training programme | D26: 3 | E26: 150 | F26: 48 | G26: =F26/E26 -> 0.32 | H26: =G26 -> 0.32 | I26: After providing processing device 2 trainings were conducted on grain processing marketing
A27: 3 | B27: Youth and women trained on Agricultural product value addition | C27: Number of training conducted with youths and women on Agricultural product value chain | D27: 4 | E27: 7 | F27: 4 | G27: =F27/E27 -> 0.57142857 | H27: =G27 -> 0.57142857 | I27: 4No. Trainings were conducted with a total beneficiary of 1,730 farmers disagregated by crops.
F28: Overall Average Performance | I28: =AVERAGE(H24:H27) -> 0.55869048
A29: Commitment 4: Timely Access to Quality and Affordable Agricultural Inputs (fertilizer, seedlings, herbicides, insecticide, etc)
A30: 1 | B30: Improved access to quality agric inputs at affordable /subsidize prize provided to farmers | C30: Quantity of improved quality inputs (seeds) supply at subsidized prize (mt) | D30: 1 | E30: 12540 | F30: 14093 | G30: =F30/E30 -> 1.1238437 | H30: 1.01
C31: Quantity of improved qualitty inputs (Fertilizer) supply at subsidize prize (mt) | D31: 2 | E31: 4371.6 | F31: 3643 | G31: =F31/E31 -> 0.83333333 | H31: =G31 -> 0.83333333 | I31: JASCO limited company provide fertilizer 3,643 mt for a farmers of Jigawa state out of a target of 4,372 for the year 2024 both dry and rain season
C32: Quantity of improved quality inputs (Chemicals) supply at subsidize prize (lt) | D32: 3 | E32: 15400 | F32: 14000 | G32: =F32/E32 -> 0.90909091 | H32: =G32 -> 0.90909091 | I32: JASCO limited company provide chemical 14,000Lt for the farmers of Jigawa state out of target of 15,400 Lt for the year 2024 both dry and rain season
C33: Quantity of improved quality inputs (seeds) supply free of charge (mt) | D33: 4 | E33: 8.4 | F33: 8.7 | G33: =F33/E33 -> 1.0357143 | H33: 1.01 | I33: the breakdown of package allocated are rice 1.270, maize 1.290, millet 3.410 and sorghum 2.760 provided by NG CARES free (Are these in mt or what???)
C34: Quantity of improved quality inputs (Fertilizer) supply free of charge (mt) | D34: 5 | E34: 433 | F34: 3092 | G34: =F34/E34 -> 7.1408776 | H34: 1.01 | I34: 20,611 number of benifisheries 2 bagof NPK/person and uria 1bag/per person
C35: Quantity of improved quality inputs (Chemicals) free of charge (lt) | D35: 6 | E35: 8649 | F35: =20611*3 -> 61833 | G35: =F35/E35 -> 7.1491502 | H35: 1.01 | I35: 1 post emergance harbicide, 1 bottle of insecticide and 1 sechet of fungicide (LT)
C36: Number of beneficiaries of improved qualitty inputs supply free of charge | D36: 7 | E36: 2883 | F36: 20611 | G36: =F36/E36 -> 7.1491502 | H36: 1.01 | I36: 20,611 Is the numer that benifite from farming input free from NG CARES
F37: Overall Average Performance | I37: =AVERAGE(H30:H36) -> 0.97034632
A38: Commitment 5: Sustained Collaboration with partners in the Pursuit of Agrictural Trasformation Agenda of the State Government
A39: 1 | B39: Improve collaboration to Deepened and Expanded Partnerships for Access to Finance, Technology and Technical Asistance | C39: No. of MoU Entered With Development Partners on Various Aspects of Agricultural Development | D39: 1 | E39: 10 | F39: 4 | G39: =F39/E39 -> 0.4 | H39: =G39 -> 0.4 | I39: MoUs signed with Sasakawa SG2000, PropCom, FMAN, Ethiopia,
C40: Percentage level of MoU Implementation | D40: 2 | E40: 0.4 | F40: 0.75 | G40: =F40/E40 -> 1.875 | H40: 1.01 | I40: Implementation is ongoing on Profcom, Floormills, Harvest Plus, SG2000 and few others
C41: Percentage of Resources Mobilised in Relation to Amount Captured in the State Budget | D41: 3 | E41: 0.8 | F41: =4.66/12.9 -> 0.36124031 | G41: =F41/E41 -> 0.45155039 | H41: =G41 -> 0.45155039 | I41: N12.9 bn is envisaged assessed as external funding from Loans and Grants in 2024 FY from Sasakawa, IsDb and JCARES. Out of the target, only about N4.66 billion was reported to be received (N413.8 bn from AfDB and N4.24 bn from JCARES which gives about 36.12 % as per AFS
F42: Overall Average Performance | I42: =AVERAGE(H39:H41) -> 0.6205168
A43: Commitment 6: Livestock Development to promote Meat and Dairy Production
A44: 1 | B44: Revitilization of LIBCs | C44: Number of LIBCs Rehablitated and Revitilised to provide Public Services | D44: 1 | E44: 2 | F44: 0 | G44: =F44/E44 -> 0 | H44: =G44 -> 0 | I44: The services at Gumel and Kazaure LIBCs still remained epileptic'
A45: 2 | B45: Veterinary. Clinics rehabilitated | C45: Number of Functional Vetrinary Clinics (Through rehablitation, staffing and working materials) | D45: 2 | E45: 4 | F45: 4 | G45: =F45/E45 -> 1 | H45: =G45 -> 1 | I45: Vetarinary hospitals at Dutse, Birnin Kudu, Gumel and Maigatari improved staffining and made functional. Construction of ne one one in Kachi still ongoing
A46: 3 | B46: More abattoir newly constructed | C46: Number of abattoirs newly constructed | D46: 3 | E46: 6 | F46: 1 | G46: =F46/E46 -> 0.16666667 | H46: =G46 -> 0.16666667 | I46: Constructed an abbatoir at Maigatari.
A47: 4 | B47: Goat breeding micro credit scheme conducted | C47: Number of Goats distributed through the Goat Breeding Program | D47: 4 | E47: 2100 | F47: 15480 | G47: =F47/E47 -> 7.3714286 | H47: 1.01 | I47: 5,160 women benefited 15,480 goats under the Regular Program of the Ministry in Maigatari, Kazaure, Buji and K/Hausa
C48: Number of Goats Retrieved / Revolved in the Goat Breeding Program | D48: 5 | E48: 500 | F48: 0 | G48: =F48/E48 -> 0 | H48: =G48 -> 0 | I48: There is no any retrieval under the revolving scheme
C49: Number of Women that Benefitted from the Goat Breeding Program | D49: 6 | E49: 700 | F49: =F47/3 -> 5160 | G49: =F49/E49 -> 7.3714286 | H49: 1.01 | I49: Each benificiary from Maigatari, Kazaure, Buji and K/Hausa received 3 goats.
C50: Number of Women Benefitting from JCARES Goat/Sheep Breeding Program | D50: 7 | E50: 7150 | F50: =E50 -> 7150 | G50: =F50/E50 -> 1 | H50: =G50 -> 1
C51: Number of Goats / Sheeps Distributed under JCARES Goat/Sheep Breeding Program | D51: 8 | E51: =(5750*4)+(1400*3) -> 27200 | F51: =E51 -> 27200 | G51: =F51/E51 -> 1 | H51: =G51 -> 1
A52: 5 | B52: Agric. Extension Service Delivery on Livestock Development Strengthened | C52: Number of Community Based Animal Health Workers (CBAHW) | D52: 9 | E52: 300 | F52: 300 | G52: =F52/E52 -> 1 | H52: =G52 -> 1 | I52: The number of Community Based Animal Health Workers (CBAHW) included newly recruited temporary Agents (J-AGRO) deployed to EAs
C53: Number of Community Based Animal Health Workers (CBAHW) Equipped including Mobility | D53: 10 | E53: 300 | F53: 300 | G53: =F53/E53 -> 1 | H53: =G53 -> 1 | I53: 300 Newly recruited temporaryCommunity Based Animal Health Workers provided with equipped motorcycles:
C54: Number of Livestock Reached in Vaccination Services | D54: 11 | E54: 800000 | F54: 845616 | G54: =F54/E54 -> 1.05702 | H54: 1.01 | I54: a) Vaccination of 565,000 covers: i) Cattle - 165,000 ii) Sheep / Goats - 400,000 This was conducted early January to March b) 280,616 vaccinated for antraxantrax september 2024.
F55: Overall Average Performance | I55: =AVERAGE(H44:H54) -> 0.74515152
A56: Commitment 7: Fisheries Development
A57: 1 | B57: Development of Water Bodies and Support to Fishermen Associations | C57: Number of water bodies restocked with fingerlings | D57: 1 | E57: 6 | F57: 3 | G57: =F57/E57 -> 0.5 | H57: =G57 -> 0.5 | I57: Three (3) Water Bodies Restocked out of the targetted Six (6). Out of 3,003 water bodies in the state, 3 number were restocked in Birnin kudu, Ringim and Hadejia
C58: Number of training conducted to fisher men association | D58: 2 | E58: 6 | F58: 0 | G58: =F58/E58 -> 0 | H58: =G58 -> 0 | I58: a) The trainings are scheduled to be conducted in Q3 after the fishermen are provided with fishing gears. b) The memo on the procurement of fishing gears will be submitted in the Q3. but no approval
C59: Number of Fishing Gears Provided | D59: 3 | E59: 1000 | F59: 0 | G59: =F59/E59 -> 0 | H59: =G59 -> 0 | I59: Memo has been writen in the Q3 quarter but no approval
C60: Number Participation in External Fishing Festivals including conduct of Local Ones | D60: 4 | E60: 3 | F60: 1 | G60: =F60/E60 -> 0.33333333 | H60: =G60 -> 0.33333333 | I60: Local Festival conducted at Auyo loca Government at Kalgwai village
F61: Overall Average Performance | I61: =AVERAGE(H57:H60) -> 0.20833333
A62: Commitment 8: Improve the Policy Environment for the Development of Agriculture in the State
A63: 1 | B63: State Agriculture Policy | C63: Agricultural Policy Developed / Revised and Published | D63: 1 | E63: 100 | F63: 100 | G63: =F63/E63 -> 1 | H63: =G63 -> 1 | I63: Revision of State Agriculture Policy was completed, approved and published
C64: Proportion (%) of Initiatives in the Policy commenced, ongoing or fully implemented | D64: 2 | E64: 75 | F64: 50 | G64: =F64/E64 -> 0.66666667 | H64: =G64 -> 0.66666667 | I64: The New Policy comes with 11 High Level Policy Objectives with 87 specific strategies spread across these objectives. About 50% of all the outlined strategies were commenced or ongoing.
A65: 2 | B65: Data Generation for Agricultural Planning | C65: Number of farmers registered in a Farm and Farmer Database | D65: 3 | E65: 250000 | F65: 134084 | G65: =F65/E65 -> 0.536336 | H65: =G65 -> 0.536336 | I65: Registered farmers include all the farmers who are involed in dry and rainy season
C66: Number of farms registered in the Database | D66: 4 | E66: 250000 | F66: 134084 | G66: =F66/E66 -> 0.536336 | H66: =G66 -> 0.536336 | I66: Registered farmers include all the farmers who are involed in dry and rainy season
C67: Number of Crops for which up-to-date data on Production and Productivity is available Annually (6 Major Crops and Others) | D67: 5 | E67: 10 | F67: 5 | G67: =F67/E67 -> 0.5 | H67: =G67 -> 0.5 | I67: Millet, sorghum, cowpea, ground nut and sesame. These are the major crops capturing the total production in the state
F68: Overall Average Performance | I68: =AVERAGE(H63:H67) -> 0.64786773
A69: Commitment 9: Farmer Support in Accesing Agricultral Financing
A70: 1 | B70: Establish linkage between farmers and financial institution | C70: Number of financial institutions that are linked with farmers | D70: 1 | E70: 2 | F70: 1 | G70: =F70/E70 -> 0.5 | H70: =G70 -> 0.5 | I70: The Farmers were linked with BoI and NIRSAL for micro-credit financing recovery collected by farmers
C71: Number of Farmers that have accessed Agricultural Financing | D71: 2 | E71: 50000 | F71: N/A | G71: 0 | H71: =G71 -> 0 | I71: Data not available due to human resource issus
F72: Overall Average Performance | I72: =AVERAGE(H70:H71) -> 0.25
A73: Commitment 10: Revitalize and strengthen the State Agricultural & Rural Development Agency
A74: 1 | B74: Strengthened the Institutional and Technical Capacity of JARDA to Deliver Quality Agricultural Support to Farmers. | C74: Number of staff that are profesionally qualified for their job position | D74: 1 | E74: 1300 | F74: 551 | G74: =F74/E74 -> 0.42384615 | H74: =G74 -> 0.42384615 | I74: 551 qualified as at 1st & 2nd Quarter due to their working experience
C75: Number of staff trained for skill enhancement | D75: 2 | E75: 1790 | F75: 1335 | G75: =F75/E75 -> 0.74581006 | H75: =G75 -> 0.74581006 | I75: Ministry trained 300 CBHW and JARDA trained 1,035 J-Agro at Fanisau NYSC camp on 6/6/2024 and J-Agro done their training on July 2024
C76: Provision of working materials (mobility) | D76: 3 | E76: 350 | F76: 350 | G76: =F76/E76 -> 1 | H76: =G76 -> 1 | I76: Working materials were purchased but yet to bedistributed
C77: Number of Zonal Offices Revitalised and Functional | D77: 4 | E77: 4 | F77: 4 | G77: =F77/E77 -> 1 | H77: =G77 -> 1 | I77: 4 zonal offices were revitalised by JARDA (B/Kudu, Hadejia, Kazaure and Gumel)
A78: 2 | B78: Agric. Extension Service Delivery on Crop Production Strengthened | C78: Number of Agricultural Extention Agents Provided or Recruited | D78: 5 | E78: 1000 | F78: 1335 | G78: =F78/E78 -> 1.335 | H78: 1.01 | I78: The number of Extension Agents included newly recruited temporary Agents (J-AGRO) deployed to EAs
C79: Farmer - Extension Worker Ratio | D79: 6 | E79: 10 | F79: 100 | G79: =E79/F79 -> 0.1 | H79: =G79 -> 0.1 | I79: 500 farmers to 1 extention worker achieved down from 1000:1
C80: Number of Agric. Extension Agents Provided with Necessary Working Materials including Mobility | D80: 7 | E80: 1000 | F80: 300 | G80: =F80/E80 -> 0.3 | H80: =G80 -> 0.3 | I80: Only CBHW provided with working mobility but other Jagro will be distributed later but the mobility is on ground
A81: 3 | B81: Agricultural Research and Technology Adaptation | C81: Number of New Agricultural Technologies / Research Outputs Introduced to Farmers for adaptation | D81: 8 | E81: 3 | F81: 5 | G81: =F81/E81 -> 1.6666667 | H81: 1.01 | I81: New technology introduced include improved seeds varieties for rice and wheat as well millets and sorghum
C82: Number of New Agricultural Technologies / Research Outputs Introduced to Farmers for adapted | D82: 9 | E82: 2 | F82: 2 | G82: =F82/E82 -> 1 | H82: =G82 -> 1 | I82: Cluster programe and other mechnisation machine
A83: 4 | B83: Women In Agriculture | C83: Number of Women reached in the Activities of WIA Operations | D83: 10 | E83: 250 | F83: 250 | G83: =F83/E83 -> 1 | H83: =G83 -> 1 | I83: There are 25 WIA Associasions in the state and each group has 100 members
F84: Overall Average Performance | I84: =AVERAGE(H74:H83) -> 0.75896562
A85: Commitment 11: Strengthen and expand the operations of the State Agricultural Supply to farmers.
A86: 1 | B86: Expansion of operational activities of JASCO | C86: JASCO Recapitalised as measured by Recapitalization Amount of fund released (in Billions) | D86: 1 | E86: 12 | F86: 5 | G86: =F86/E86 -> 0.41666667 | H86: =G86 -> 0.41666667 | I86: JASCO is a limited lability company recapitalized with a total sum of N5 billion to support its core mandate of supplying improved input to Jigawa state farmers at affordable prices N5 billion was collected in three (3) instalment (January, March and April, 2024) as recapitalization.
C87: Turnover in Sales | D87: 2 | H87: NA | I87: Not Assessed
C88: Profitability | D88: 3 | H88: NA | I88: Not Assessed
F89: Overall Average Performance | I89: =AVERAGE(H86:H88) -> 0.41666667
A90: Commitment 12: Exploit the State’s Agricultural Potentials through Agricultural Mechanization and Irrigation Development
A91: 1 | B91: All irrigation schemes in the State rehabilitated | C91: Number of irrigation scheme Rehabilitated | D91: 1 | E91: 10 | F91: 3 | G91: =F91/E91 -> 0.3 | H91: =G91 -> 0.3 | I91: Irrigation schemes rehabilitated are: a) Auyo, b) Miga and c) Gwaram Achievement was due to timely commencement of the process, approval and release of the funds In addition, 10No. Dams were redesigned for rehabilation expected to be conducted by ACRISAL
C92: Number of New Upland Irrigation Schemes Established | D92: 2 | E92: 2 | F92: 1 | G92: =F92/E92 -> 0.5 | H92: =G92 -> 0.5 | I92: Lallashi Irrigation Schemes completed and commissioned
A93: 2 | B93: Mechanization | C93: Number of the purchased tractors that were distributed to farmers | D93: 3 | E93: 66 | F93: 66 | G93: =F93/E93 -> 1 | H93: =G93 -> 1 | I93: 60 number tractors were distributed to farmers across the state by JASCO and 6No. Are kept in the Ministry for hiring services to farmers
C94: Number of the purchased Combined Harvesters that were distributed to farmers | D94: 4 | E94: 20 | F94: 10 | G94: =F94/E94 -> 0.5 | H94: =G94 -> 0.5 | I94: Distributed to farmers by JASCO
C95: Number Other Assorted Labour-Saving Devices | D95: 5 | E95: 50 | F95: 30 | G95: =F95/E95 -> 0.6 | H95: =G95 -> 0.6 | I95: Number not acertained ut included small milling machines, grinding machines, etc
C96: Number of Agricultural Mechanization Centers Established | D96: 6 | E96: 31 | F96: 0 | G96: =F96/E96 -> 0 | H96: =G96 -> 0 | I96: Established but not yet functional
I97: =AVERAGE(H91:H96) -> 0.48333333
F98: Overall Average Performance | H98: =AVERAGE(H7:H97) -> 0.64717905 | I98: =AVERAGE(H92:H97) -> 0.52

Sheet 10. Min. of Water SS
A1: MINISTRY OF WATER RESOURCES
A2: FULL YEAR [JANUARY TO DECEMBER 2024] PERFORMANCE ASSESSMENT
A3: No. of OPs | B3: Expected Outputs for Delivering the Outcome Targets | C3: Output KPIs | D3: Result No. | E3: 2024 Target | F3: Jan. - Dec. Results | G3: Performance | H3: Adjusted Performance | I3: Remarks / Evidences
A4: OUTPUT LEVEL RESULT FRAMEWORK - MINISTRY OF WATER RESOURCES
A6: Commitmnent 1 - Achieve universal access to safe drinking water and sanitation services
A8: 1 | B8: Expansion of Water Supply Schemes across the State to achieve univeral coverrage | C8: Expansion / Upgrading and conversion of motorised schemes to solar powered of Urban Water Supply Schemes (54No. New Water Schemes Constructed) | D8: 1 | E8: 27 | F8: 13 | G8: =F8/E8 -> 0.48148148 | H8: =G8 -> 0.48148148 | I8: Remarks needed including some locations
C9: Construction of new solar powered water supply schemes in small town | D9: 2 | E9: 80 | F9: 98 | G9: =F9/E9 -> 1.225 | H9: 1.01 | I9: Remarks needed including some locations
C10: Conversion of motorised schemes to solar in small towm of the state | D10: 3 | E10: 100 | F10: 220 | G10: =F10/E10 -> 2.2 | H10: 1.01 | I10: Remarks needed including some locations
C11: To extend 1150km pipelines network across the state in small towns | D11: 4 | E11: 150 | F11: 196 | G11: =F11/E11 -> 1.3066667 | H11: 1.01
C12: Expansion / Upgrading of Small Towns Water Supply Schemes (100No. Solar-powered Water Schemes Constructed) | D12: 5 | E12: 100 | F12: 50 | G12: =F12/E12 -> 0.5 | H12: =G12 -> 0.5 | I12: Remarks needed including some locations by LG
C13: Provision of Additional Rural Water Facilities hand pump water points provided) | D13: 6 | E13: 469 | F13: 632 | G13: =F13/E13 -> 1.347548 | H13: 0.1 | I13: Remarks needed including some locations
C14: Actualization of Dutse Metropolitan Water Supply Project in line with Greater Dutse Water plan through the Completion of the Four Phases of the Project | D14: 7 | E14: 4 | F14: 1 | G14: =F14/E14 -> 0.25 | H14: =G14 -> 0.25 | I14: Phase 1 of the project includes review of design, Feasibilty studies, preperation of procurement documents. In addition to improvemet works currently on going
A15: 2 | B15: Rehabilitation of Exisiting Water Supply Schemes | C15: Rehabilitation and upgrading of Urban Water Supply Schemes | D15: 8 | E15: 60 | F15: 50 | G15: =F15/E15 -> 0.83333333 | H15: =G15 -> 0.83333333 | I15: Some locations needed by LG
C16: Rehabilitation Small Towns Solar-Powered Supply Schemes (1,200) | D16: 9 | E16: 300 | F16: 218 | G16: =F16/E16 -> 0.72666667 | H16: =G16 -> 0.72666667 | I16: Remarks needed including some locations by LG
C17: Rehabilitation of Exisiting Hand Pumps in Rural Communities | D17: 10 | E17: 500 | F17: 607 | G17: =F17/E17 -> 1.214 | H17: 1.01 | I17: Remarks needed including some locations by LG
C18: Water Supply Schemes in the State Capital Maintenained and Expanded (Number of Schemes Provided, Rehabilitated or Improved) | D18: 11 | E18: 12 | F18: 12 | G18: =F18/E18 -> 1 | H18: =G18 -> 1 | I18: 8No new setlight solar powered schemes, 8km pipekines reticulations, including replacement of booster and 29No additional boreholes
A19: 3 | B19: Increased access to water supply | C19: Litres of water produced in urban | D19: 12 | E19: 9320000 | F19: 8532000 | G19: =F19/E19 -> 0.91545064 | H19: =G19 -> 0.91545064
C20: Litres of water produced in small town | D20: 13 | E20: 6848500 | F20: 6177600 | G20: =F20/E20 -> 0.90203694 | H20: =G20 -> 0.90203694
C21: Litres of water produced in rural communities | D21: 14 | E21: 2852232 | F21: 7188480 | G21: =F21/E21 -> 2.5202999 | H21: 1.01
A22: 4 | B22: Increased level of water supply in communities | C22: Litres of water supplied per capita per day in urban | D22: 15 | E22: 84 | F22: 75 | G22: =F22/E22 -> 0.89285714 | H22: =G22 -> 0.89285714
C23: Litres of water supplied per capitaper day in small towns | D23: 16 | E23: 42 | F23: 35 | G23: =F23/E23 -> 0.83333333 | H23: =G23 -> 0.83333333
C24: Litres of water supplied per capita per day in rural | D24: 17 | E24: 20 | F24: 18 | G24: =F24/E24 -> 0.9 | H24: =G24 -> 0.9
A25: 5 | B25: Increased access to sanitation and hygiene | C25: Develop and implement an Open Defecation Free (ODF) sustainability plan (Initiatives / Activities in the ODF Plan Implemented) | D25: 18 | E25: 17 | F25: 4 | G25: =F25/E25 -> 0.23529412 | H25: =G25 -> 0.23529412 | I25: What are the activities implemented in the ODF plan
C26: Functonality of ODF Multi-Sectoral Steering and Implementation Committees (Number of Meetings) | D26: 19 | E26: 17 | F26: 4 | G26: =F26/E26 -> 0.23529412 | H26: =G26 -> 0.23529412 | J26: Attendance sheet needed as evidence for each meeting
C27: Percentage of household with access to basic sanitation | D27: 20 | E27: 89 | F27: 88 | G27: =F27/E27 -> 0.98876404 | H27: =G27 -> 0.98876404
C28: Percentage of households that observe basic hygiene practrices | D28: 21 | E28: 60 | F28: 20 | G28: =F28/E28 -> 0.33333333 | H28: =G28 -> 0.33333333
A29: 6 | B29: 2023 WASH policy document finalised , implementation guide developed and implemented | C29: Progress in development of WASH policy documents | D29: 22 | E29: 100 | F29: 100 | G29: =F29/E29 -> 1 | H29: =G29 -> 1 | I29: WASH Policy reviewed to be published | J29: To view the reviewed policy (unpublished) as evidence
C30: Progress in development of WASH policy implementation guide documents | D30: 23 | E30: 100 | F30: 100 | G30: =F30/E30 -> 1 | H30: =G30 -> 1 | I30: WASH policy Implementation guide developed | J30: To view the level of the implemtation guide document
C31: Percentage of WASH policy implementation | D31: 24 | E31: 50 | F31: 50 | G31: =F31/E31 -> 1 | H31: =G31 -> 1 | J31: Evidence needed
A32: 7 | B32: Community based organisation established and trained | C32: Percentage of established Water Consumer Association(WCAs) trained in small towns | D32: 25 | E32: 400 | F32: 0 | G32: =F32/E32 -> 0 | H32: =G32 -> 0
C33: Percentage of Water Sanitation and Hygiene committes strengthened | D33: 26 | E33: 300 | F33: 0 | G33: =F33/E33 -> 0 | H33: =G33 -> 0
C34: Average Performance Rating | I34: =AVERAGE(H8:H33) -> 0.69914789
A35: Commitment 2 – Increased Investments in the Rehabilitation and Expansion of Irrigation Facilities and Infrastructure (Dams and Water Reservoirs)
A36: 8 | B36: Existing 4 Nos dams and 2 Nos reservoir rehabilitated | C36: Existing 4No. Dams Rehabilitated or Desilted | D36: 1 | E36: 4 | F36: 1 | G36: =F36/E36 -> 0.25 | H36: =G36 -> 0.25 | I36: Location needed
C37: Existing 2No. Reservoirs rehabilitated | D37: 2 | E37: 2 | F37: 0 | G37: =F37/E37 -> 0 | H37: =G37 -> 0
C38: No. of Water User Associations Established | D38: 3 | E38: 1 | F38: 2 | G38: =F38/E38 -> 2 | H38: 1.01 | I38: Where?
A39: 9 | B39: River channels cleared and dredged | C39: Number of kilometers of Jekarade river and ruwan garau cleared manually | D39: 4 | E39: 3.5 | F39: 3.5 | G39: =F39/E39 -> 1 | H39: =G39 -> 1
C40: Average Performance Rating | I40: =AVERAGE(H36:H39) -> 0.565
A41: Commitment 3 – Achieve the provisions of SDG Goal 6 to ensure availability and sustainable management of water and sanitation for all
A42: 10 | B42: Accelerate the attainment of the SDGS as per access to safe drinking water is concerned | C42: Proportion of schools with access to basic drinking water | D42: 1 | E42: 80 | F42: 70 | G42: =F42/E42 -> 0.875 | H42: =G42 -> 0.875 | I42: Evidence needed. How many schools in total and how many with access
C43: Proportion of schools with access to single-sex toilet facilities | D43: 2 | E43: 40 | F43: 24 | G43: =F43/E43 -> 0.6 | H43: =G43 -> 0.6 | I43: Evidence needed. How many schools in total and how many with access
C44: Proportion of schools with access to basic handwashing facilities | D44: 3 | E44: 70 | F44: 35 | G44: =F44/E44 -> 0.5 | H44: =G44 -> 0.5 | I44: Evidence needed. How many schools in total and how many with access
C45: Proportion of population using safely managed drinking water services | D45: 4 | E45: 40 | F45: 8 | G45: =F45/E45 -> 0.2 | H45: =G45 -> 0.2
C46: Proportion of population using safely managed sanitation services, including a hand-washing facility with soap and water | D46: 5 | E46: 40 | F46: 14 | G46: =F46/E46 -> 0.35 | H46: =G46 -> 0.35 | I46: What is the evidence? How do you arrived to this pproportion?
C47: Percentage Outturn of water- and sanitation-related Official Development Assistance that is part of the Annual Approved Estimate | D47: 6 | E47: 90 | F47: 0 | G47: =F47/E47 -> 0 | H47: =G47 -> 0
C48: Average Performance Rating | I48: =AVERAGE(H42:H47) -> 0.42083333
C49: Overall Performance | H49: =AVERAGE(H8:H48) -> 0.63785681

Sheet 11. Min. of Health
A1: MINISTRY OF HEALTH
A2: FULL YEAR [JANUARY TO DECEMBER 2024] PERFORMANCE ASSESSMENT
A3: HEALTH SECTOR DELIVERY PERFORMANCE MANAGEMENT FRAMEWORK
A4: OP No. | B4: Output Deliverable | C4: Output KPIs | D4: Result No. | E4: 2024 Target | F4: Jan - Dec Actual | G4: Performance Score (%) | H4: Adjusted Performance | I4: Remarks and Evidences
A5: Commitment 1: Improve access to healthcare services through the attainment of Government’s vision of at least one functional Basic Health Clinic per Political Ward, one Secondary Health Facility for each State Constituency and a Specialist Hospital for each Senatorial Zone. This involve the completion and commissioning all the outstanding projects on Secondary and Specialist Hospitals before the end of the year 2024.
A6: 1 | B6: Completion and Commissioning of Ongoing Expansion and Improvement of Construction of new hospitals | C6: Number of the 4 General Hospitals at Garki, Gantsa, Gwiwa, and Guri fully equipped | D6: 1 | E6: 2 | F6: 4 | G6: =F6/E6 -> 2 | H6: 1.01 | I6: Facilities fully equipped awaiting operationalization
C7: Number of PHCs out of the 13 PHCs upgraded to secondary care facilities across the state | D7: 2 | E7: 13 | F7: 13 | G7: =F7/E7 -> 1 | H7: =G7 -> 1 | I7: Kiyawa, Maigatari, Gwaram, Gwiwa, Karkarna, Auyo, Guri, Kirikasamma,Kanya Babba, Gwaram, Roni, Garki, and Miga | J7: Kiyawa and Maigatari schedule for visit
C8: Number of the upgraded PHCs out of the 13 that are fully equipped | D8: 3 | E8: 10 | F8: 6 | G8: =F8/E8 -> 0.6 | H8: =G8 -> 0.6 | I8: Guri, Kanya Babba, Maigatari, Miga, Auyo, Malam madori
C9: Number of the upgraded and fully equipped PHCs out of the 13 that are fully functional | D9: 4 | E9: 4 | F9: 3 | G9: =F9/E9 -> 0.75 | H9: =G9 -> 0.75 | I9: Auyo, Malam madori and Maigatari
C10: Progress status towards the Completion of General Hospitals at Gagarawa, Kiri Kasamma, | D10: 5 | E10: 0.8 | F10: 0.65 | G10: =F10/E10 -> 0.8125 | H10: =G10 -> 0.8125 | I10: Outstanding works includes laudry, kitchen, mutuary, landscaping, block of external toilet etc
C11: Progress status towards equipping Kirikasamma and Gagarawa General Hospitals | D11: 6 | E11: 0.8 | F11: 0.8 | G11: =F11/E11 -> 1 | H11: =G11 -> 1 | I11: Equipment supplied yet to be installed
C12: Level of Progress towards the Construction of New General Hospitals in Ringim and Kafin Hausa | D12: 7 | E12: 30 | F12: 25 | G12: =F12/E12 -> 0.83333333 | H12: =G12 -> 0.83333333 | I12: 30% Mobilization Advanced paid project ongoing satisfactorily | J12: Schedule for Viist
C13: Level of Progress towards Equipping newly constructed General Hospitals at Ringim and Kafin Hausa | D13: 8 | E13: 0 | F13: 0 | G13: NA | H13: NA
C14: Full functionality of New General Hospitals at Ringim and Kafin Hausa) | D14: 9 | E14: 0 | F14: 0 | G14: NA | H14: =G14 -> NA
C15: Progress status in completion of new Orthopedic Hospital in Gumel | D15: 10 | E15: 0.6 | F15: 0.4 | G15: =F15/E15 -> 0.66666667 | H15: =G15 -> 0.66666667 | I15: The contract is ongoing in 2024 Q2
C16: Number of hospitals where special care baby, emergency pediatrics, Gynae emergency, and ICUs have been established, (Dutse, Gumel & K/Hausa) | D16: 11 | E16: 1 | F16: 0 | G16: =F16/E16 -> 0 | H16: =G16 -> 0 | I16: The construction for the new emergency block at Gumel General Hospital has been completed waiting to be equipped and staffed.
C17: Number of ward level PHCs newly constructed (2 at Gumel 4no at Hadejia) | D17: 12 | E17: 2 | F17: 0 | G17: NA | H17: NA | I17: Not Yet
C18: Number of midwife quarters that were upgraded | D18: 13 | E18: 40 | F18: 37 | G18: =F18/E18 -> 0.925 | H18: =G18 -> 0.925 | I18: The upgrade of 37 midwives quarters by SMOH has been completed
C19: Number of upgraded midwife quarters that were furnished | D19: 14 | E19: 40 | F19: 7 | G19: =F19/E19 -> 0.175 | H19: =G19 -> 0.175 | I19: Madaci, Chakwaikwaiwa, Koya, Amanga, Yarsara. Abaya,and Kanzan. Furnished
C20: Percentage of the 281 ward level PHCs that were provided with functional solar lighting system | D20: 15 | E20: 0.26 | F20: 0.17 | G20: =F20/E20 -> 0.65384615 | H20: =G20 -> 0.65384615 | I20: Ongoing
C21: Percentage of 281 ward level PHCs where neonatal resuscitating corners are established | D21: 16 | E21: 0.2 | F21: 0 | G21: NA | H21: NA | I21: Not Assessed
C22: Percentage of Secondary Health Facilities Covered in the Solarization of Critical Sections in Health Facilities for 24 Hour Services. Number of secondary health facilities with 24 hours solar power service | D22: 17 | E22: 14 | F22: 4 | G22: =F22/E22 -> 0.28571429 | H22: =G22 -> 0.28571429 | I22: Gumel Gen. Hospital KafinHausa Gen. Hospital Dutse Gen. Hospital Gwaram Gen. Hospital | J22: Schedule for Visit
C23: Average Performance | I23: =AVERAGE(H6:H22) -> 0.6701585
A25: Commitment 2: Improved Performance and Expanded Coverage of State Health Insurance Scheme
A26: 2 | B26: Improved Performance and Expand Coverage of State Health Insurance Scheme | C26: Number of organized private sector that subscribe to health insurance scheme | D26: 18 | E26: 6 | F26: 0 | G26: NA | H26: NA | I26: Not Assessed
C27: Proportion of persons benefiting from informal sector health insurance scheme | D27: 19 | E27: 0.15 | F27: 0.12 | G27: =F27/E27 -> 0.8 | H27: =G27 -> 0.8
C28: Proportion of total population of the state ( formal and informal) that are enrolled into health insurance scheme | D28: 20 | E28: 0.1 | F28: 0.09 | G28: =F28/E28 -> 0.9 | H28: =G28 -> 0.9 | I28: Aabout 217,521, TSHIP fr Student (12,087), Jbasic (145312), BHCPF (97867), Bill abd Melinder (2,507, UNICEF 29,335, Group,Individuals and Social Contributory (361) all totalling 504,990.
C29: Number of Services Covered under the State's Basic Health Insurance Scheme | D29: 21 | E29: 15 | F29: 10 | G29: =F29/E29 -> 0.66666667 | H29: =G29 -> 0.66666667
C30: Annual Growth Rate in the Capital Base of the Insurance Scheme | D30: 22 | E30: 0.1 | F30: 0.06 | G30: =F30/E30 -> 0.6 | H30: =G30 -> 0.6
I31: =AVERAGE(H26:H30) -> 0.74166667
A33: Commitment 3: Pursuit of Interventions and Initiatives that Accelerate Progress towards the attainment of SDG Goal 3 concerned with ensuring healthy lives and promotion of well-being of the citizens. Specifically, this includes achieving Universal Health Coverage, Access to Quality Essential Basic Healthcare Services, Access to safe, effective, quality and affordable essential medicines.
A34: 3 | B34: Strengthening Primary Healthcare Program for improved Coverage of Essential Health Services including Interventions around Maternal, Newborn & Child Health, Infectious Diseases, Non-Communicable Diseases among the General Population. This includes the Strengthening of Routine Immunization, Vaccination, Antenatal Care Services and Nutrition Programs | C34: Percentage of ANC coverage at 1st visit | D34: 23 | E34: 0.78 | F34: 1.1 | G34: =F34/E34 -> 1.4102564 | H34: 1.01 | I34: DHIS2
C35: Skill Birth Delivery attendance | D35: 24 | E35: 0.28 | F35: 0.959 | G35: =F35/E35 -> 3.425 | H35: 1.01 | I35: DHIS2
C36: Percentage of Pregnant Women and Lactating Mothers Covered under the State's Maternal, Neonatal and Child Healthcare Program (including those covered under Health Insurance Scheme) | D36: 25 | E36: 0.5 | F36: 0.68 | G36: =F36/E36 -> 1.36 | H36: 1.01 | I36: DHIS2
C37: Percentage of Pregnant Women and Lactating Mothers Covered under the State Government's Maternal Cash Transfer Program. | D37: 26 | E37: 0.05 | G37: NA | H37: NA | I37: Program under Min. of Women Affairs
C38: Percentage of fully immunized children (1 year) | D38: 27 | E38: 0.45 | F38: 0.85 | G38: =F38/E38 -> 1.8888889 | H38: 1.01 | I38: DHIS2
C39: Number of communities (12,000 villages) covered with community based nutritional (Masaki) Nutrition Program | D39: 28 | E39: 404 | F39: 300 | G39: =F39/E39 -> 0.74257426 | H39: =G39 -> 0.74257426 | I39: Jigawa Masaki report
C40: Percentage of Access/coverage of RuTF in Designated Centers for Community Management of Acute Malnutrition | D40: 29 | E40: 1 | F40: 0.62 | G40: =F40/E40 -> 0.62 | H40: =G40 -> 0.62
C41: Percentage of children that received Vit A supplement | D41: 30 | E41: 0.79 | F41: 0.95 | G41: =F41/E41 -> 1.2025316 | H41: 1.01 | I41: DHIS2
C42: Percentage of children U5 sleeping under LLIN | D42: 31 | E42: 0.7 | G42: NA | H42: NA | I42: Survey data
C43: Percentage of reduction of Malaria prevalence among children U5 | D43: 32 | E43: 0.38 | F43: 0.25 | G43: =F43/E43 -> 0.65789474 | H43: =G43 -> 0.65789474 | I43: Survey data, MICS 2021
C44: Percentage of women that are engaging in exclusive breastfeeding | D44: 33 | E44: 0.37 | F44: 0.3 | G44: =F44/E44 -> 0.81081081 | H44: =G44 -> 0.81081081 | I44: MICS 2021
C45: Access to Essential Medicines under Drugs Revolving System | D45: 34 | E45: 1 | F45: 0.5 | G45: =F45/E45 -> 0.5 | H45: =G45 -> 0.5
A46: 4 | B46: Reviewed and strengthened drug revolving system by ensuring that all essential drugs are made available to patients and make the system accountable | C46: Progress status in decreasing decapitalization of health facilities ( secondary and ward level PHCs) | D46: 35 | E46: 50 | F46: 20 | G46: =F46/E46 -> 0.4 | H46: =G46 -> 0.4
C47: Proportion of health facilities recording DRF | D47: 36 | E47: 20 | F47: 20 | G47: =F47/E47 -> 1 | H47: =G47 -> 1
C48: Percentage of health facilities (Secondary and ward level PHCs) with tracer drugs | D48: 37 | E48: 50 | F48: 35 | G48: =F48/E48 -> 0.7 | H48: =G48 -> 0.7
A49: 5 | B49: Achieve universal access to sexual and reproductive health-care services including for family planning, information and education, and the integration of reproductive health into the State’s Strategic Health Plans and Program | C49: Proportion of women of reproductive age (aged 15-49 years) who have their need for family planning satisfied with modern methods | D49: 38 | E49: 0.08 | F49: 0.04 | G49: =F49/E49 -> 0.5 | H49: =G49 -> 0.5
C50: Proportion of women of reproductive age (aged 15-49 years) who have their need for family planning satisfied with modern methods | D50: 39 | E50: 30 | F50: 22 | G50: =F50/E50 -> 0.73333333 | H50: =G50 -> 0.73333333 | I50: To review the indicatir for clarity
A51: Average Performance | I51: =AVERAGE(H34:H50) -> 0.78097421
A53: Commitment 4: Improve Emergency Response Capacity and Effective in the Mitigation and Containment of Epidemics including AIDS, Tuberculosis, Malaria and Other Water-borne and Communicable Diseases Enhanced including the Strengthening the Referral Systems
A54: 6 | B54: Effectiveness of Health Emergency Response and Referral system | C54: Number of functional isolation centers in the State | D54: 40 | E54: 2 | F54: 1 | G54: =F54/E54 -> 0.5 | H54: =G54 -> 0.5
C55: Number of optimum Accident and Emergency Centers | D55: 41 | E55: 14 | F55: 1.5 | G55: =F55/E55 -> 0.10714286 | H55: =G55 -> 0.10714286
C56: Progress status in domestication of NEMSAS policy | D56: 42 | E56: 100 | F56: 40 | G56: =F56/E56 -> 0.4 | H56: =G56 -> 0.4
C57: Percentage of Effectiveness in Response and Containment of Incidences of Tuberculosis incidence per 1,000 population | D57: 43 | E57: 0.9 | F57: 0.7 | G57: =F57/E57 -> 0.77777778 | H57: =G57 -> 0.77777778
C58: Percentage of Effectiveness in Response and Containment of Incidences Malaria incidence per 1,000 population •Effective Response and Containment of Incidences of Meningitis incidence per 1,000 population | D58: 44 | E58: 0.9 | F58: 0.7 | G58: =F58/E58 -> 0.77777778 | H58: =G58 -> 0.77777778
C59: Effective response and containment of incidences of Maningitis incidence per 1,000 population | D59: 45 | E59: 0.9 | F59: 0.7 | G59: =F59/E59 -> 0.77777778 | H59: =G59 -> 0.77777778
C60: Percentage of Effectiveness in Response and Containment of Incidences of Cholera incidence per 1,000 population | D60: 46 | E60: 0.9 | F60: 0.6 | G60: =F60/E60 -> 0.66666667 | H60: =G60 -> 0.66666667
C61: Percentage Progress in the prevention and treatment of drug and substance abuse | D61: 47 | G61: NA | H61: NA | I61: Not assessed
C62: Average Performance | I62: =AVERAGE(H54:H61) -> 0.57244898
A64: Commitment 5:Sustained Improvement in the Recruitment, Training and Deployment of Human resources for Health
A65: 7 | B65: Ensured fair distribution of medical personnel between urban and rural areas through the introduction of the whole rural incentive scheme | C65: Number of ward level PHCs with minimum HRH package | D65: 48 | E65: 150 | F65: 120 | G65: =F65/E65 -> 0.8 | H65: =G65 -> 0.8
C66: Number of critical healthcare workers employed | D66: 49 | E66: 1520 | F66: 1100 | G66: =F66/E66 -> 0.72368421 | H66: =G66 -> 0.72368421
C67: Number of Foreign Medical Students under Bonding | D67: 50 | E67: ?? | G67: NA | H67: NA
C68: Number of Nurses and Midwives Graduating Annually from the State Health Training Institutions through the expansion of the enrolment capacity | D68: 51 | E68: 300 | F68: 210 | G68: =F68/E68 -> 0.7 | H68: =G68 -> 0.7
C69: Percentage Progress in the Implementation Task-shifting Policy. | D69: 52 | E69: 100 | F69: 40 | G69: =F69/E69 -> 0.4 | H69: =G69 -> 0.4
C70: Percentage of Hard to Reach Facilities Fully Provided with Critical Medical Personnel through a Rational and Fair Staff Deployment Policy | D70: 53 | E70: 100 | F70: 45 | G70: =F70/E70 -> 0.45 | H70: =G70 -> 0.45
A71: Average Performance | I71: =AVERAGE(H65:H70) -> 0.61473684
A73: Commitment: 6 Improved Planning of the State's Health System
A74: 8 | B74: Health Financing, Planning and Management Information System | C74: Progress status in development of functional health information system and dashboard with real time data on healthcare management | D74: 54 | E74: 100 | F74: 40 | G74: =F74/E74 -> 0.4 | H74: =G74 -> 0.4 | K74: 69
C75: Progress Level in the Coordination of Heath System Development Partnerships (25-Percentage Points each for Functional Health Partners Coordination Committee, Consolidated Health Partners Work Plan, Inclusion of Donor Support in Health Sector Plan / Budget, and Quarterly Reports | D75: 55 | E75: 100 | F75: 65 | G75: =F75/E75 -> 0.65 | H75: =G75 -> 0.65 | K75: 74
C76: Progress Status in the Computerization of the State Health Systems (Hospital Operations and Management, Drug Revolving Fund Operations, and other Critical Aspects of the Health System | D76: 56 | E76: 40 | F76: 5 | G76: =F76/E76 -> 0.125 | H76: =G76 -> 0.125 | K76: 106
C77: Number of Partnerships and or Number of Ongoing Initiatives in the Area of Health Operational Research | D77: 57 | E77: 2 | F77: 0 | G77: =F77/E77 -> 0 | H77: =G77 -> 0 | K77: 57
C78: Progress in the Review of JICHMA Law to capture Health Equity Fund Operation / Guidelines, Employer Contribution and other Means of Enhancing the Scheme's Capital Base | D78: 58 | E78: 0.5 | F78: 0.2 | G78: =F78/E78 -> 0.4 | H78: =G78 -> 0.4 | K78: 61
A79: Average Performance | I79: =AVERAGE(H74:H78) -> 0.315 | K79: 32
A80: Overall Performance | H80: =AVERAGE(H6:H79) -> 0.65406464

Sheet 12. Min. of Infor
A1: MINISTRY OF INFORMATION
A2: FULL YEAR [JANUARY TO DECEMBER 2024] PERFORMANCE ASSESSMENT
A3: No. of Outputs | B3: Expected Outputs for Delivering the Outcome Targets | C3: Output KPIs | D3: No. of Results | E3: 2024 Target | F3: Jan - Dec Actuals | G3: Performance | H3: Adjusted Performance | I3: Evidence / Remarks
A4: Commitment 1: Strategic Information Management to generate Public Awareness, Mass Mobilization and Re-orientation for Participatory Governance and Patriotism.
A5: 1 | B5: Projecting a positive image of Government and the State across Nigeria and the World as the ‘New World”, generating awareness on Government Policies & Programmes and the Rich History & Culture of the State. | C5: No. Coverage of Government Policies and Programs in National and International Media (No of Features in Print and Electronic Media) | D5: 1 | E5: 1200 | F5: 1000 | G5: =F5/E5 -> 0.83333333 | H5: =G5 -> 0.83333333 | I5: Remarks needed | J5: Monthly Jigawa state Newsletters, Jigawa state website uploads, …………...
C6: Percentage of Features that is of International Coverage | D6: 2 | E6: 0.1 | F6: 0.06 | G6: =F6/E6 -> 0.6 | H6: =G6 -> 0.6
C7: Number of functional FM Stations across the State (A minimum of 18 Hours of Daily Broadcast) | D7: 3 | E7: 2 | F7: 2 | G7: =F7/E7 -> 1 | H7: =G7 -> 1
C8: Number of Languages of Broadcast in State FM and AM Stations (A minimum of 2 Hours of Daily Broadcast in Langauges other than Hausa) | D8: 4 | E8: 3 | F8: 3 | G8: =F8/E8 -> 1 | H8: =G8 -> 1 | J8: Kanuri, Fulfulde and English
C9: Number of Unique Jingles developed and aired Annually by State AM and FM Stations on Public Sensitization, Government Policies and Programs | D9: 5 | E9: 48 | F9: 39 | G9: =F9/E9 -> 0.8125 | H9: =G9 -> 0.8125 | I9: List of some jingles
C10: Number of Documentaries, Publications, Press Releases Special-focused Stories Produced on Government Policies and Programs | D10: 6 | E10: 120 | F10: 5 | G10: =F10/E10 -> 0.041666667 | H10: =G10 -> 0.041666667
C11: Performance | I11: =AVERAGE(H5:H10) -> 0.71458333
A13: Commitment 2: Mass Mobilization for Societal Re-orientation and Participatory Governance
A14: 2 | B14: Social Re-Orientation & Mobilization (Public Education, Information and Communication on Mobilization on Participatory Governance, Social Cohesion and Peaceful Co-existence) | C14: Number of Participations in the Multisectoral State Taskforce on the fight against Drug / Substance Abuse in the State | D14: 1 | E14: 6 | F14: 2 | G14: =F14/E14 -> 0.33333333 | H14: =G14 -> 0.33333333
C15: No. of School- and Community-based clubs established on Campaigns Against Drug Abuse | D15: 2 | E15: 100 | F15: 55 | G15: =F15/E15 -> 0.55 | H15: =G15 -> 0.55 | J15: List is needed foor verification
C16: No. of Engagements with the Established Clubs on the Campaigns Against Drug Abuse | D16: 3 | E16: 40 | F16: 30 | G16: =F16/E16 -> 0.75 | H16: =G16 -> 0.75 | J16: List of established clubs and date of engagement with each of them
C17: No. of Events Led by the Ministry in Activities Conducted by the MultiSectoral Task Force | D17: 4 | E17: 6 | F17: 4 | G17: =F17/E17 -> 0.66666667 | H17: =G17 -> 0.66666667 | J17: List of events needed
C18: No. of Government Organized Town Hall Meetings | D18: 5 | E18: 6 | F18: 3 | G18: =F18/E18 -> 0.5 | H18: =G18 -> 0.5 | I18: Senatorial zones | J18: Provide date and venue of each town hall meeting
C19: No / Frequency of publications on Societal Orientation / Mobilization (Pliers / other Periodicals) | D19: 6 | E19: 24 | F19: 8 | G19: =F19/E19 -> 0.33333333 | H19: =G19 -> 0.33333333
C20: No. of Phone-in Programs and Press Conferences Organised for Government Officials on Public Sensitization (State Radio and Television) | D20: 7 | E20: 60 | F20: 50 | G20: =F20/E20 -> 0.83333333 | H20: =G20 -> 0.83333333
C21: Performance | I21: =AVERAGE(H14:H21) -> 0.56666667
A23: Commitment 3: Support the General Development of Sports and Improvement the State's Performance in National Sporting Events and other Youth Development Initiatives
A24: 3 | B24: Provision / Improvement of Sporting Infrastructures & Facilities, Development of Local Talents and Greater Performance in National Sporting Events | C24: Functionality of Dutse Stadium (No of Days of Sporting Activities Annually) | D24: 1 | E24: 60 | F24: 0 | G24: =F24/E24 -> 0 | H24: =G24 -> 0
C25: Functionality of Other Mini Stadia in the Emirate Headquarters (No. of Sporting Activities undertaken Quarterly) | D25: 2 | E25: 40 | F25: 38 | G25: =F25/E25 -> 0.95 | H25: =G25 -> 0.95 | I25: No. by each stadium -
C26: Number of Sporting Activities in which the State is participating in National Leagues | D26: 3 | E26: 24 | F26: 20 | G26: =F26/E26 -> 0.83333333 | H26: =G26 -> 0.83333333
C27: No. of Sporting Events Promoted Through Inter-Local Government Competitions | D27: 4 | E27: 6 | F27: 5 | G27: =F27/E27 -> 0.83333333 | H27: =G27 -> 0.83333333
C28: Number of Youth Registered for Participation in State Sporting Events Annually | D28: 5 | E28: =27*(18+12+20) -> 1350 | F28: 1000 | G28: =F28/E28 -> 0.74074074 | H28: =G28 -> 0.74074074
C29: Propotion of Registered youths that partipated in Local, State or National Champiionships | D29: 6 | E29: 0.5 | F29: 0.4 | G29: =F29/E29 -> 0.8 | H29: =G29 -> 0.8
C30: No. of Youths in Sports (Sports Men and Women) Promoted through Local Sports Talents Hunt | D30: 7 | E30: 12 | F30: 9 | G30: =F30/E30 -> 0.75 | H30: =G30 -> 0.75
A31: 4 | B31: Youths Leadership Development | C31: Number of Youths Aged 18 - 24 years Engaged in National Citizens and Leadership Training Centers Annually | D31: 8 | E31: 54 | F31: 0 | G31: =F31/E31 -> 0 | H31: =G31 -> 0
C32: Performance | I32: =AVERAGE(H24:H31) -> 0.61342593
A34: Commitment 4: Promote the Development of History and Culture
A35: 5 | B35: Promote History and Culture | C35: No. of Local and National Cultural Events Organized or Participated by the State | D35: 1 | E35: 6 | F35: 3 | G35: =F35/E35 -> 0.5 | H35: =G35 -> 0.5 | I35: =H35 -> 0.5
C36: Progress towards the Establishment of Archive and Reference Library in the State | D36: 2 | E36: 0.3 | F36: 0.25 | G36: =F36/E36 -> 0.83333333 | H36: =G36 -> 0.83333333 | I36: =H36 -> 0.83333333 | J36: To conduct site visit
C37: Performance | G37: =AVERAGE(G35:G36) -> 0.66666667 | H37: =G37 -> 0.66666667 | I37: =H37 -> 0.66666667
A39: Commitment 5: Revitalization of Jigawa State Printing Press
A40: 6 | B40: Jigawa State Printing Press Revitilised as a Viable Profitable Government Owned Enterprices | C40: Functionality and Profitability State Printing Press (IGR Performance as per Approved Budget) | D40: 1 | E40: 0.9 | F40: 0.8 | G40: =F40/E40 -> 0.88888889 | H40: =G40 -> 0.88888889 | J40: To confirm from end of year 2024 budget implementation report or Audit report 2024.
C41: Functionality of State Printing Press (Quarterly Turnover) | D41: 2 | G41: NA | H41: =G41 -> NA | I41: Not Assessed
C42: Profitability of State Printing Press (Atainment of Revenue Targets in %) | D42: 3 | E42: 0.8 | F42: =6175000/5000000 -> 1.235 | G42: =F42/E42 -> 1.54375 | H42: 1.01 | I42: The sum of N6.175 was reported as actual against a target of N5 millio n
C43: Percentage of Employees of the Printing Press not under State Payroll (40% in 4 Years) | D43: 4 | E43: 0.04 | F43: 0.02 | G43: =F43/E43 -> 0.5 | H43: =G43 -> 0.5 | J43: Total employees on payroll and Total not on payroll needed
C44: Performance | I44: =AVERAGE(H40:H43) -> 0.79962963
C45: Overall Performance | H45: =AVERAGE(H5:H44) -> 0.65038752

Sheet 13. Min. of Basic Edu
A1: MINISTRY OF BASIC EDUCATION
A2: FULL YEAR [JANUARY TO DECEMBER 2024] PERFORMANCE ASSESSMENT
A3: PERFORMANCE BOND FOR DELIVERING TARGETED RESULTS IN BASIC EDUCATION FOR ACHIEVING THE PRIORITY DEVELOPMENT COMMITMENTS OF JIGAWA STATE GOVERNOR
A4: No. of Opts | B4: Deliverable Outputs | C4: Output KPIs | D4: No. of RAs | E4: 2024 Target | F4: Jan - Dec Actual | G4: Performance | H4: Adjusted Performance | I4: Remarks / Evidences
A5: Expected Output Deliverables and Performance Measurement
A6: Commitment 1 - Automation and digitization of school administrations, governance and admission process
A8: 1 | B8: School administration, governance and admission process automated and digitized | C8: No. of platforms developed/adopted | D8: 2 | E8: 2 | F8: 2 | G8: =F8/E8 -> 1 | H8: =G8 -> 1 | I8: Digitial Platforms establshed to improve internal processess of educational planning such as e-registration, admissions, recruitments examinations, etc (subebjigawa.org.ng), additional ones by PLANE and UNICEF supporting with some aspects of educational management.
F9: Average Performance | I9: =AVERAGE(H8) -> 1
A10: Commitment 2 - Enhance the Education database for proper mapping of all schools in the State by undertaking bio-metric-based capturing of all pupils and teachers
A11: 2 | B11: Database for mapping of all schools in the state developed with biometric-based features to capture all pupils and teachers (to leverage on BAMIS, TMIS, LURITS) | C11: Percentage coverage of pupils in the database. | D11: 2 | E11: 0.3 | F11: 0.3 | G11: =F11/E11 -> 1 | H11: =G11 -> 1 | I11: x% of students covered under LURITS application in 150 schools across 10 LGEAs. BAMIS application used for capturing biometric attandance of pupils in 1,351 schools in 15 LGEA (SUBEB) (1)Birnin kudu (2)Dutse (3)Gwaram (4)Buji (5)Buji (6)Ringim (7)Kazaure (8)Hadejia (9)Birniwa(10)Kafin Huasa (11)Auyo (12)Gwaiwa (13)Jahun (14)Maigatari (15)Kiri Kasamma
I12: =AVERAGE(H11) -> 1
A13: Commitment 3 - Sustain and improve the present drive of reducing the number of out-of-school children through a fragmented approach that involves all the stakeholders
A14: 3 | B14: Reduced out of school children through a fragmented approach that involves all the stakeholders | C14: Percentage of OOSC in Primary | D14: 3 | E14: 33.9 | F14: 20 | G14: =F14/E14 -> 0.5899705 | H14: =G14 -> 0.5899705 | I14: Out of the projected OOSC of 820,000 in 2024, about 164,000 were enrolld backed to school as ascertained through improved enrolment.
C15: Percentage of OOSC in JSS | D15: 4 | E15: 40 | F15: 10 | G15: =F15/E15 -> 0.25 | H15: =G15 -> 0.25 | I15: Procurement and Distribution of Transition package and sanitary and Sanitation items to Nomad Girls Child Transiting to Boarding J.S.S to Nomadic Schools aacross the state, (ANE) - Learners made literate:(1)Basic and post basic literacy 9,199 (3)Continuous education 1,201 (4)Remedial education 2,025 (5)Women vocational and skills2,025 (5)Literacy by radio 6,499. (AME) - Procurement and Distribution of Instructional materials for 400no. Adult and 150no. Youth Islamiyya literacy centres and Facilitators Allowances. Monitoring of 400no. Adult and 150no.Youth Islamiyya centres and Sansitization to unwilling communities across the State (AME)
I16: =AVERAGE(H14:H15) -> 0.41998525
A17: Commitment 4 - Enhance the efficiency, resourcefulness, competence of teachers and other educational personnel through training, capacity building, and motivation (Continuous training and retraining of at least 5,000 Teachers/Instructors annually, focusing on Modern Teaching Research Techniques, Digital Literacy, and Skills for Basic Education)
A18: 4 | B18: Teachers rewarded for their outstanding performance/achievements | C18: No. of teachers rewarded for extra ordinary performance | D18: 10 | E18: 50 | F18: 0 | G18: 0 | H18: =G18 -> 0 | I18: none
A19: 5 | B19: Teachers/intstructors trained on modern teaching, research techniques/pedagogical skills, digital literacy and basic skills to promote investment in skills-based training and certification programs | C19: No. of teachers trained on modern teaching, research techniques (pedagogy) | D19: 11 | E19: 5000 | F19: 3588 | G19: =F19/E19 -> 0.7176 | H19: =G19 -> 0.7176 | I19: Teachers train on Strengthing Mathmatics and Science Education(SMASE), Strengthing Teachers on English on Proficiancy (STEP) and School Based Training (SBT)(SUBEB). -Training of facilitators for remedial program across the 27LGA
C20: No. of teachers trained on digital literacy | D20: 12 | E20: 3000 | F20: 5800 | G20: =F20/E20 -> 1.9333333 | H20: 1.01 | I20: J-Teach Teachers given Induction Training and 2nd Chance J-Teach Teachers.
C21: Number of teachers trained on basic skills to bridge hand skill gap | D21: 13 | E21: 800 | F21: 20 | G21: =F21/E21 -> 0.025 | H21: =G21 -> 0.025 | I21: 20NO. teachers, trained on Teacher Internship Scheme (TIS)
C22: Performance | I22: =AVERAGE(H18:H21) -> 0.43815
A23: Commitment 5 - Consolidate on gains achieved in girl-child education by introducing Girl-Child Community Committee (GCCC) to monitor retention rates for girls in schools
A24: 6 | B24: Girl-Child Community Committee (GCCC) to monitor retention rates for girls in schools introduced | C24: No. GCCC formed to monitor retenton rates for girls in schools | D24: 14 | E24: 500 | F24: 3288 | G24: =F24/E24 -> 6.576 | H24: 1.01 | I24: Mothers association were created 3288 in Basic Education Schools in the State, Five (5) Women in each School with a leader (1) in each local government,
I25: =AVERAGE(H24) -> 1.01
A26: Commitment 6 - Leapfrog Jigawa into the Digital Economy by introducing digital skills such as coding, web development, and artificial intelligence to all public primary and secondary schools in the state | J26: 1MOTHER ASS to eac LGEA
A27: 7 | B27: Teachers trained on digital skills in basic schools | C27: No. of teachers trained in basic coding, web design & artificial inteligence | D27: 15 | E27: 1000 | F27: 55 | G27: =F27/E27 -> 0.055 | H27: =G27 -> 0.055 | I27: on Artificial Intellegence
A28: 8 | B28: Learners acquired digital skills in basic schools | C28: No. of learners trained in basic coding, web design & artificial inteligence | D28: 16 | E28: 2000 | F28: 0 | G28: =F28/E28 -> 0 | H28: =G28 -> 0 | I28: none
C29: Performance | H29: =G29 | I29: =AVERAGE(H27:H29) -> 0.0275
A30: Commitment 7 - Address the challenge of unfavorable pupil-teacher ratio in Basic schools
A31: 9 | B31: Net increase of teachers in primary schools | C31: Number of teachers recruited annually | D31: 17 | E31: 1000 | F31: 6236 | G31: =F31/E31 -> 6.236 | H31: 1.01 | I31: 36Teachers were recuited to MEGA Schools, 3,000 Teachers were recruited in both Primary and Junior Secondary Schools and also 3,200 J-teachers were engaged to Basic Education Schools
A32: 10 | B32: Net increase of teachers in junior secondary schools | C32: Number of teachers recruited annually | D32: 18 | E32: 500 | F32: 200 | G32: =F32/E32 -> 0.4 | H32: =G32 -> 0.4 | I32: To confirm
A33: 11 | B33: Reduced Pupil Teacher Ratio in Primary Schools from 65 to 45. Pupil Class Ratio reduced from 101 to 50 in PS and from 59 to 30 in JSS | C33: Pupil Teacher Ratio in Primary | D33: 19 | E33: 55 | F33: 52 | G33: =E33/F33 -> 1.0576923 | H33: 1.01
C34: Pupil Teacher Ratio in JSS | D34: 20 | E34: 32 | F34: 32 | G34: =E34/F34 -> 1 | H34: =G34 -> 1
C35: Pupil Class Ratio in PS | D35: 21 | E35: 80 | F35: 80 | G35: =E35/F35 -> 1 | H35: =G35 -> 1 | I35: 1) ANE Construction of 1 Block of 2 Class Rooms in the following LGAs 1. Migawa - Birnin Kudu L.G.A 2. DADIN KOWA - DUTSE L.G.A 3. MALAM BAKO BORNAWA - S/TANKARKAR 4. JAMAARE - GURI L.G.A 2) Construction of 4no. Block of 2 classrooms CHAMBAWA IN K/HAUSA LGA 2. DANZABARMA IN B/KUDU LGA 3. SAFAMI IN GURI LGA 4. WAIDU RAUDA IN YAN KWASHI
C36: Pupil Class Ratio in JSS | D36: 22 | E36: 40 | F36: 40 | G36: =E36/F36 -> 1 | H36: =G36 -> 1
C37: Performance | I37: =AVERAGE(H31:H36) -> 0.90333333
A38: Commitment 8 - Reviewing the concept of established Effective Schools at Basic Education
A39: 12 | B39: Increased number of the existing Effective schools that meet the standard requirement of being a Effective from 1 to 40 based on the redefined concept | C39: No of the existing Effective Primary schools that meet the standard requirement of being effective | D39: 23 | E39: 10 | F39: 10 | G39: =F39/E39 -> 1 | H39: =G39 -> 1 | I39: LIST OF SCHOOLS THAT MEET THE CRITERIA OF BEING EFFECTIVE 1) JAHUN SPRIMARY SCHOOL 2)ABDULKADIR PILOT PRIMARY SCHOOL 3)JSS FAGOJI 4)ZANDAM NAGOGO SPRIMARY SCHOOL 5)MARKE CENTRAL PRIMARY SCHOOL 5)HARBO SABUWA 6)SANKARA PRIMARY SCHOOL 7)DABI PRIMARY SCHOOL 8)JSS DANGYATIN 9)BANDAWA PRIMARY SCHOOL
I40: =AVERAGE(H39) -> 1
A41: Commitment 9 - Leveraging on the power of e-learning to achieve better learning outcomes in schools (This would be part of an integrated State ICT Strategy and e-governance)
A42: 13 | B42: E-learning centers for better learning outcomes in schools as part of ICT and e-governance agenda from 3 to 20 built and equiped | C42: No. of e-learning centers built and equiped | D42: 24 | E42: 2 | F42: 6 | G42: =F42/E42 -> 3 | H42: 1.01 | I42: 1. Construction of 1no. Block of ICT Lab with office at Dangan Tsaure Nomadic Girls Junior Secondary School, Dutse LGA (ANE) - Construction of Laboratories at: 1) JSSS Aujara 2) JSS Jahun 3)JSS Kanya Babba 4)JSS Guri 5)JSS Ahmad Habu (MoBE)
I43: =AVERAGE(H42) -> 1.01
F44: Overall Performance | H44: =AVERAGE(H8:H42) -> 0.6888195

Sheet 14. Min. of Higher Edu
A1: MINISTRY OF EDUCATION SCIENCE AND TECHNOLOGY DUTSE
A2: FULL YEAR [JANUARY TO DECEMBER 2024] PERFORMANCE ASSESSMENT
A3: OPT No. | B3: Outputs | C3: Outputs KPIs | D3: No. of RAs | E3: 2024 Target | F3: Jan - Dec Actual | G3: Performance | H3: Adjusted Performance | I3: Remarks / Evidences | L3: 2024 | M3: 125620 | N3: 2750 | O3: =M3/N3 -> 45.68
A4: Commitment 1: Address the chalenges of unfavourable pupil - teacher ratio in post basic school (senior secondary school) | M4: Students | N4: Teacer
A6: 1 | B6: Reduced pupil teacher ratio in post Basic Schools | C6: Pupils Teacher ratio in SSS | D6: 1 | E6: 50 | F6: 46 | G6: =E6/F6 -> 1.0869565 | H6: 1.01 | I6: Teacer-Student Ratio improved from about 67 per teacher in 2023 to about 46 in Dec. 2024 achieved through massive teacher recruitment including 2,77 teachers redeployed from basic Education to Higher and 1,100 J-Teachers engaged, recruitment of 72 teachers for MEGA Schools, the ratio of 50 student per teacher is achieved - . Number of Teachers increased from 2,563 in 2023 to 5,986 by Dec. With an enrolment of 142,195 this gives a new ratio of 2024 based on the | J6: Let have the enrolments and teachers on the ground to establish the basis
I7: =AVERAGE(H6) -> 1.01
A8: Commitment- 2: Reviewing the concept of Establishing centres of excellence and effecctive schools at post basic Education
B9: increasing No of existing centre of excellence secondary school that meet the standard requirement of being a centre of excellence from 1 to 4 based on the redefined concept | C9: No of existing centre of excellence secondary school that meet the standard requirement of being a centre of excellence | D9: 1 | E9: 2 | F9: 2 | G9: =F9/E9 -> 1 | H9: =G9 -> 1 | I9: Reviewed Standard for Centers of Excellence in terms of structures, facilities, services and human resources. Four were established including Bamaina Academy and Centre of Excellence for Techincal and Vocaltional Studies Garki Currently ongoing are Dutse Model and SSS K/Hausa | J9: Santami Project
I10: =AVERAGE(H9) -> 1
A11: Commitment -3: Provision of Critical Infracturactures (Decongestion of student classes ans Hostel)
B12: Improved Student - Classroom Ratio from a Baseline of over 100 students per classroom | C12: Student classroom ratio in sss | D12: 1 | E12: 55 | F12: 50.3 | G12: =F12/E12 -> 0.91454545 | H12: =G12 -> 0.91454545 | I12: Based on the 2024 ASC with 125,620 student enrolment and 2,498 classrooms, pupil classroom has improved from 50.3 in 2024. | J12: To be verified | K12: Classess | L12: 2024 | M12: 125620 | N12: =2033+360+105 -> 2498 | O12: =M12/N12 -> 50.288231
B13: Student Hostel ratio reduced | C13: Student Hostel ratio boarding sss | D13: 2 | E13: 150 | F13: 73 | G13: =E13/F13 -> 2.0547945 | H13: 1.01 | I13: With additiional renovation of 86 student hotels and 11 newly constructed giving the total number of hostels of 458 in 2024 and 33,185 student borders, gives a new student hostel ratio of about 73. | K13: Hostels | L13: 2024 | M13: 33185 | N13: =361+86+11 -> 458 | O13: =M13/N13 -> 72.456332
I14: =AVERAGE(H12:H13) -> 0.96227273
A15: Commitment -4: Enhance quality of science, technology and vocational Education Training (STEM and TVET)
B16: STEM & TVET Teachers capacity developed | C16: No of STEM Teachers trained on subject releted matters | D16: 1 | E16: 100 | F16: 300 | G16: =F16/E16 -> 3 | H16: 1.01 | I16: Training of 300 Science subject Teachers on Biology, Chemistry and Physics practicals, G4H program | J16: Attendance sheet
C17: No of TVET Teachers trained on subject releted matters | D17: 2 | E17: 20 | F17: 67 | G17: =F17/E17 -> 3.35 | H17: 1.01 | I17: Capacity building, methodology of teaching, computer literacy & practical subjects (electrical, mechanical etc), Training of teachers on Guidance & Councelling, FTDS | J17: Attendance sheet
I18: =AVERAGE(H16:H17) -> 1.01
A19: Commitment - 5:Leveraging on the power of e-learning to achieve better learning outcomes in schools (This would be part of an integrated state ICT strategy and e-governence
B20: improve student learning outcomes through e-learning platforms | C20: No, of students participating on e-learning platforms | D20: 1 | E20: 3000 | F20: 4000 | G20: =F20/E20 -> 1.3333333 | H20: 1.01 | I20: xx No. Jigawa State Studetns participating in the Nigerian Learning Passport (NLP) as per the NLP Dashboard Data | J20: To be verified through NLP Dashboard
C21: No. of rubust e-governance service system developed for the educational sector | D21: 2 | E21: 6 | F21: 6 | G21: =F21/E21 -> 1 | H21: =G21 -> 1 | I21: JEMIS, TIS, e-admission, e-learning (NLP), e-data collection, e-registration of candidates | J21: Whether they are functional or not. To be verified
C22: Number of staff trained on the use of e- governance system | D22: 3 | E22: 5000 | F22: 5000 | G22: =F22/E22 -> 1 | H22: =G22 -> 1 | I22: JCOMPETE-3,733 School Directors/Principlas- 286 MoHEST Directors, Deputies& Asst., Zonal Offices - 981 | J22: Attendance sheet
I23: =AVERAGE(H20:H22) -> 1.0033333
A24: Commitment -: 6: Ensure effective operation of ICT in Schools
B25: ICT in schools improve | C25: No of senior secondary schools with ICT facilities | D25: 1 | E25: 200 | F25: 300 | G25: =F25/E25 -> 1.5 | H25: 1.01 | I25: Provision of 300 routers and data services to all senior secondary schools Distribution of 300 Tablets to all school EMIS officers and Zonal EMIS officers | J25: How many Computer Labs?
C26: No of ICT teachers in senior secondary schools | D26: 2 | E26: 109 | F26: 99 | G26: =F26/E26 -> 0.90825688 | H26: =G26 -> 0.90825688 | I26: ICT staff Record
C27: No of ICT training conducted for teachers | D27: 3 | E27: 5 | F27: 5 | G27: =F27/E27 -> 1 | H27: =G27 -> 1 | I27: 1)Training of Bamaina Academy staff on teaching strategies and the use of ICT gadgets in teaching 2)Training of school managers on proper record keeping in offline and online facilities 3)Training of Directors, Zonal directors and principals on the use of ICT 4) -Training on J-COMPETE and online data collection 5) Training of teachers on NLP | J27: Training reports
C28: No. of teachers trained on ICT | D28: 4 | E28: 1300 | F28: 1500 | G28: =F28/E28 -> 1.1538462 | H28: 1.01 | I28: Drawn from above activities | J28: Attendance sheets
I29: =AVERAGE(H25:H28) -> 0.98206422
A30: Commitment -: 7: Accelerate effort to commence medical training in the state university
B31: Medical collage established in the state university | C31: % of medical structures constructed | D31: 1 | E31: 25 | F31: 25 | G31: =F31/E31 -> 1 | H31: =G31 -> 1 | I31: Construction of Faculty of Medicine ongoing at SLU have reached 25%% | J31: To be verified
B32: Medical courses accredited in the sule lamido university (SLU) | C32: Number of Medical courses accredited in SLU | D32: 2 | E32: 3 | F32: 0 | G32: Not Assessed | H32: =G32 -> Not Assessed | I32: Not assessed
C33: Average Performance | I33: =AVERAGE(H31:H32) -> 1
A34: Commitment -: 8: Improve operation of Jigawa quality Assurance Agency (JISEQAA)
B35: Quality Assurance Agency Established | C35: % of JISEQAA corperate plan developed | D35: 1 | E35: 100 | F35: 65 | G35: =F35/E35 -> 0.65 | H35: =G35 -> 0.65 | I35: The policy & the corperate plan developed but certain adjustments are to be carried out
C36: Number of QA Evaluators deployed to the Agency | D36: 2 | E36: 40 | F36: 42 | G36: =F36/E36 -> 1.05 | H36: 1.01 | I36: 42 QA evaluators @JISEQAA
C37: Number of QA Evaluators trained | D37: 3 | E37: 40 | F37: 42 | G37: =F37/E37 -> 1.05 | H37: 1.01 | I37: PERL/ARC, PLANE and AGILE
C38: Proportion of senior secondary Quality assured during whole school evaluation QA Exercise | D38: 4 | E38: 25 | F38: 18 | G38: =F38/E38 -> 0.72 | H38: =G38 -> 0.72 | I38: 51 Senior Secondary Schools (27,10,14)
C39: percentage of QA reports dissiminated | D39: 5 | E39: 100 | F39: 100 | G39: =F39/E39 -> 1 | H39: =G39 -> 1
C40: Average Performance | I40: =AVERAGE(H35:H39) -> 0.878
A41: Commitment -: 9:Ensure that all programm in the state tertiary institution are fully accredited by the relevant authorities
B42: All programme in the 7 state tertiary institutions are accredited | C42: % of programme in the 7 state tertiary owned institutions accredited | D42: 1 | E42: 90 | F42: 90 | G42: =F42/E42 -> 1 | H42: =G42 -> 1 | I42: All courses matured for accreditation have obtained full accreditation. No course was denied accreditation by the relevant accreditating body | J42: To confirm accredition status of all courses in tertiary institutions
I43: =AVERAGE(H42) -> 1
A44: Commitment -: 10: Establish research centres in tertiary institutions to attract intervention/colaboration from (public/private sectors) and improve the exixting ones
B45: Additional research centres established | C45: No of additional research centres established in the state owned tertiary institutions | D45: 1 | E45: 4 | F45: 3 | G45: =F45/E45 -> 0.75 | H45: =G45 -> 0.75 | I45: 1) Wetland Research & Development Center (SLU) 2) Directorate of Research, Innovation & Partnership Center (DRIP) SLU. 3. Career Development Center, CoE Gumel 4. ) Center for Semi Arid & Research Development (BUPOLY)
I46: =AVERAGE(H45) -> 0.75
A47: Commitment -: 11: Funding research in science, technology and Agriculture through collaboration with private sector and Donor agencies
B48: Additional research centres established | C48: No of additional research centres established in the state own tertiary institutions | D48: 1 | E48: 4 | F48: 2 | G48: =F48/E48 -> 0.5 | H48: =G48 -> 0.5 | I48: Funding received frm TET Fund for Career Development Centre COE. Center for Semi Arid & Research. Development (BUPOLY) also received from xxx
F49: Performance | I49: =AVERAGE(H48) -> 0.5
F50: Overall Performance | H50: =AVERAGE(H6:H49) -> 0.9333092

Sheet 15. Empowerment
A1: YOUTHS EMPLOYMENT AND EMPOWERMENT AGENCY
A2: FULL YEAR [JANUARY TO DECEMBER 2024] PERFORMANCE ASSESSMENT
A3: No. of OPs | B3: Outputs Deliverables | C3: Output KPIs | D3: Result No. | E3: 2024 Target | F3: Jan. - Dec Results | G3: Performance | H3: Adjusted Performance | I3: Remarks / Evidences
A4: OUTPUT LEVEL RESULT FRAMEWORK - YOUTH EMPOWERMENT AND EMPLOYMENT AGENCY
A5: Employment Generation and Youths Empowerment for productivity and sustainable means of livelihoods for the people
A7: 1 | B7: Skills of 150,000 youths enhanced on ICT and other industry demand skills and them with industry remote work and freelancing opportunities to earn income across borders | C7: Number of youths that were trained on ICT | D7: 1 | E7: 3000 | F7: 2900 | G7: =F7/E7 -> 0.96666667 | H7: =G7 -> 0.96666667 | I7: Additional 1,200 youth trained on various ICT skill in the month of December 2024 in partnership with Gluwa.
C8: Number of youths that were trained on ICT that have started earning income with the acquired skills | D8: 2 | E8: 1000 | F8: 500 | G8: =F8/E8 -> 0.5 | H8: =G8 -> 0.5 | I8: This was assumed as no evidence was provided
C9: Number of trained youths on other skills that have started earning income with the acquired skills | D9: 3 | E9: 30000 | F9: 19673 | G9: =F9/E9 -> 0.65576667 | H9: =G9 -> 0.65576667 | I9: Additional 200 youth trained on various skills such as social marketing etc by Arewa Development Initiative in December 2024
C10: Number of trained youths on other skills that have started earning income with the acquired skills | D10: 4 | E10: 10000 | F10: 5000 | G10: =F10/E10 -> 0.5 | H10: =G10 -> 0.5 | I10: This was assumed as no evidence was provided
A11: Performance | I11: =AVERAGE(H7:H10) -> 0.65560833
A12: 2 | B12: Youths livelihood and vocational skills enhanced through hands-on internship programme with private sector organizations | C12: Number of private sector organizations that have signed MoU with Jigawa State to provide internship programme for youths in the state | D12: 5 | E12: 6 | F12: 4 | G12: =F12/E12 -> 0.66666667 | H12: =G12 -> 0.66666667 | I12: MoUs signed with ITF, IDEAS, BoI, NITDA and Baze University | J12: Question on Baze Uniersity and BoI out
C13: Number of youths that acquired skills through vocational internship programme with the private sector organizations and other public institutions (by gender) | D13: 6 | E13: 1500 | F13: 1220 | G13: =F13/E13 -> 0.81333333 | H13: =G13 -> 0.81333333 | I13: ?????
D14: 7 | E14: 500 | F14: 400 | G14: =F14/E14 -> 0.8 | H14: =G14 -> 0.8 | I14: Hadejia Skills Centre in collaboration with Jilo Akida Foundation have trained 250 youth (150 female & 100 male) on different trades such as Catering, Tailoring, Electrical, Plumbing and Leather Work. HW Foundation Gumel has also trained 150 women on Basiline, Air Freshner and Morning Fresh making.
A15: Performance | I15: =AVERAGE(H12:H14) -> 0.76
A16: 3 | B16: Home-grown artisan’s public works programs designed and implemented | C16: Number of home-grown artisans engaged by state contractors for work execution | D16: 8 | E16: 250 | F16: 680 | G16: =F16/E16 -> 2.72 | H16: 1.01 | I16: 250 youth trained on Hand Pump Repairs and Installation, 300 youth trained on Solar Installation & Repairs, 130 trained on Motor Mechanic repairs, Plumbing and Welding across the state by NATA
A17: Performance | I17: =AVERAGE(H16) -> 1.01
A18: 4 | B18: Alternative funding partners sourced for youth Empowerment Programs | C18: Number of MoU signed with partners for youth empowerment training and seed fund grants | D18: 9 | E18: 7 | F18: 7 | G18: =F18/E18 -> 1 | H18: =G18 -> 1 | I18: Gluwa, Arewa Development Support Initiative, Jilo Akida Foundation Hadejia and HW Foundation Gumel
C19: Number of youth that benefitted from the partners empowerment support | D19: 10 | E19: 20000 | F19: 1800 | G19: =F19/E19 -> 0.09 | H19: =G19 -> 0.09
A20: 5 | B20: Access created for small business opportunity grants and soft loans for MSMEs and retail businesses with seed capital to support small businesses | C20: Number of new businesses that benefitted from soft loans as seed capital | D20: 11 | E20: 1000 | F20: 5818 | G20: =F20/E20 -> 5.818 | H20: 1.01 | I20: Workers Agric Loan 5000, J-Agro 550, 10 number combine Harvesters to Large scale farmers, 27 beneficiaries of N10m plus N2m to one beneficiary
C21: Number of new businesses that benefitted from grants as seed capital | D21: 12 | E21: 60000 | F21: 169470 | G21: =F21/E21 -> 2.8245 | H21: 1.01 | I21: Partnered with J-CARES 13,200, FGN Nano Grants 110,800, Governors Grant 27,940, Progressive Governors Forum Grant, JGSG Empowerment Grant 4,810
C22: Number of existing businesses that benefitted from soft loans | D22: 13 | E22: 1000 | F22: 1010 | G22: =F22/E22 -> 1.01 | H22: =G22 -> 1.01 | I22: It is assumed that out of the 6000 govt. workers that were given Agric loan, 948 are already involved in farming. 10 Combine Harvesters were giving out to 10 individuals as loan.
C23: Number of existing businesses that benefitted from grants | D23: 14 | E23: 20000 | F23: 15720 | G23: =F23/E23 -> 0.786 | H23: =G23 -> 0.786 | I23: Empowerment grant to 5,000 SMEs 3 Senatorial Zones, 6,720 Nano Business Grant, 4000 Presidential Nano Grant
A24: Performance | I24: =AVERAGE(H18:H23) -> 0.81766667
A25: 6 | B25: Skill Acquisition Centres to train youth on demand driven skills renovated and equipped with modern facilities | C25: Number of skills acquisition Centres renovated | D25: 15 | E25: 6 | F25: 3 | G25: =F25/E25 -> 0.5 | H25: =G25 -> 0.5 | I25: Dutse, Hadejia and Gumel Centres (Embroidery Factories) currently ongoing
C26: Number of skills Acquisition Centres equipped with modern facilities | D26: 16 | E26: 7 | F26: 3 | G26: =F26/E26 -> 0.42857143 | H26: =G26 -> 0.42857143 | I26: Dutse, Hadejia and Gumel Centres (Embroidery Factories) currently ongoing
A27: Performance | I27: =AVERAGE(H25:H26) -> 0.46428571
A28: 7 | B28: Comprehensive database developed for unemployed and under-employed graduates to cover graduates of Diploma upwards to facilitate job search and placement outside the state civil services | C28: Percentage progress of developing a comprehensive database of unemployed and under-employed youths | D28: 17 | E28: 100 | F28: 50 | G28: =F28/E28 -> 0.5 | H28: =G28 -> 0.5 | I28: Website created www.yeea.jg.gov.ng, over 100,000 unemployed youth registered.
C29: Proportion of unemployed youth job-placement done through selection from state youth skills demand database and market demand | D29: 18 | E29: 20 | F29: 13170 | G29: =F29/E29 -> 658.5 | H29: 1.01 | I29: 10,000 Hisbah Recruitment, 36 Nigeria Navy, 7 employed under Federal Government, 319 employed by Dangote Rice Mill, 1,600 Mota Engine Company, 3 at ECGCC
C30: Proportion of under-employed youths job placement done through selection from state youth skills demand database and market demand | D30: 19 | H30: NA | I30: Not Assessed
A31: Performance | I31: =AVERAGE(H28:H30) -> 0.755
A32: 8 | B32: Contribution to State IGR from youth empowerment intervention programmes | C32: Amount of state IGR contribution from all youth empowerment interventions through their tax payment | D32: 20 | E32: 100000000 | F32: 60000000 | G32: =F32/E32 -> 0.6 | H32: =G32 -> 0.6 | I32: Interest from BoI Managed Funds (confirm figure)
A33: Performance | I33: =AVERAGE(H32) -> 0.6
A34: Overall Performance | H34: =AVERAGE(H7:H33) -> 0.72931604
C35: Number of youth trained on any Vocational Skills
C36: Number of youths supported with employment

Sheet 16. JigawaInvest
A1: JIGAWA STATE INVESTMENT PROMOTION AGENCY (INVESTJIGAWA)
A2: FULL YEAR [JANUARY TO DECEMBER 2024] PERFORMANCE ASSESSMENT
A3: JIGAWA STATE INVESTMENT PROMOTION AGENCY (INVESTJIGAWA)
A4: OP No. | B4: Output Deliverable | C4: Output KPIs | D4: No. of RAs | E4: 2024 Target | F4: Jan - Dec Result | G4: Performance | H4: Adjusted Performance | I4: Evidences / Remarks
A5: Commitment 1: Improvement of the State’s Business Environment and Investment Climate aimed at mobilizing Domestic and Foreign Direct Investments into the State to support quest for economic growth and development. This will involve the provision of pragmatic and relevant policy, legal, regulatory, and institutional frameworks for investment mobilization and private sector development.
A7: 1 | B7: Provision of Robust Policies to facilitate improved Business environment, Investment Climate and Private Sector Development. These included, but not limited to, Policies on PPP, LARF, Export Promotion, Industrialization, and Regime of Investment Incentives | C7: Number of Consultations with critical stakeholders held | D7: 1 | E7: 4 | F7: 6 | G7: =F7/E7 -> 1.5 | H7: 1.01 | I7: 1. FCDO Propcom+ provided a technical support for the development of Jigawa State Agricultural Investment policy (2025-2030). Stakeholder consutations were completed and initial draft of the policy is being developed 2. Stakeholder consultations conducted on the review Jigawa State’s Land Acquisition and Resettlement Framework (LARF) to comply with Framework for Responsible and Inclusive Land Intensive Investment in Agriculture (FRILIA) principle. The document had been developed, approved and published. https://www.facebook.com/share/p/1BMmU8QowZ/ ttps://jigawastate.gov.ng/uploads/saber/Jigawa%20State%20FRILIA%20Document.pdf 3.https://jigawastate.gov.ng/uploads/Jigawa%20state%20FRILIA%20GRM%20toolkit.pdf https://www.jigawastate.gov.ng/uploads/Jigawa%20State%20FRILIA%20Stakeholder%20Management%20Toolkit.pdf https://www.jigawastate.gov.ng/uploads/Jigawa%20State%20FCCL%20Framework%20for%20PPP%20Projects.pdf https://www.jigawastate.gov.ng/uploads/Jigawa%20State%20Public%20Private%20Partnership%20Manual.pdf https://www.jigawastate.gov.ng/uploads/Jigawa%20State%20PPP%20Disclosure%20Framework.pdf 3.http://www.investjigawa.gov.ng/wp-content/uploads/2023/10/JIGAWA-STATE-PUBLIC-PRIVATE-PARTNERSHIP-POLICY-2023-2.pdf https://ppp.investjigawa.gov.ng/ 4. Stakeholders from the private sector reviewed the Jigawa State Business-Enabling Reform Action Plan (BERAP) 2025. (https://www.facebook.com/share/p/1H6doDRqoT/) 5. Information sessions organised with aim at improving access to credit for micro, small, and medium enterprises (MSMEs). (https://www.facebook.com/share/p/1ET7pnxPcS/) (https://www.facebook.com/share/p/1HJZNGm2Zq/) | J7: To verify item 1 - present the attendance and draft of the policy To verify by presnting the published document and through the mentioned website To verify website To verify website To verify website To verify website To verify website
C8: Number of State Investment Policies Initiated (New and Review of Exisiting ones) | D8: 2 | E8: 2 | F8: 1 | G8: =F8/E8 -> 0.5 | H8: =G8 -> 0.5 | I8: Industrial Policy development in progress. The first stakeholder consultation meeting has been convened (https://www.facebook.com/share/p/1BMmU8QowZ/) | J8: Industrial policy is only one (1) investment policy not 4
C9: Number of State Investment Policies approved by the State | D9: 3 | E9: 1 | F9: 0 | G9: =F9/E9 -> 0 | H9: =G9 -> 0 | I9: Industrial Policy development in progress. The first stakeholder consultation meeting has been convened
C10: Number of Initiatives in the State's Annual Business Enabling Environment Reform Plan (BERAP) that are implemented beyond 50% | D10: 4 | E10: 11 | F10: 9 | G10: =F10/E10 -> 0.81818182 | H10: =G10 -> 0.81818182 | I10: This is based on the 2024 BERAP Progress Report. | J10: What are the initiatives implemented?
A11: 2 | B11: New investments originated | C11: New investments attracted in the State through various engagement channels (pipeline) | D11: 5 | E11: 55 | F11: 72 | G11: =F11/E11 -> 1.3090909 | H11: 1.01 | I11: Investment Pipeline tracker mosty have gone beyong 70% actialziation. | J11: ???? To provide the list of new investmen attracted
A12: 3 | B12: Fully operational investments sustained | C12: Number of existing investments in the InvestJigawa database that are fully operational | D12: 6 | E12: 23 | F12: 28 | G12: =F12/E12 -> 1.2173913 | H12: 1.01 | I12: An aftercare manual was developed to assist in undertaking targetted aftercare services for investors for effective facilitation InvestJigawa Pipeline Tracker | J12: ???? To provide the list of new investmen attracted
A13: 4 | B13: Investment database of the state expanded | C13: Number of fully operational existing investments newly captured into the State investment database | D13: 7 | E13: 3 | F13: 13 | G13: =F13/E13 -> 4.3333333 | H13: 1.01 | I13: These include 5 investments mobilized by the Agency and 8 independent exisiting investment onboarding into its database, strengthening investor relations, and ensuring database accuracy. | J13: List of fully operational existing investmens newly captured
C14: Number of non-fully operational existing investments newly captured into the State investment database | D14: 8 | E14: 6 | F14: 2 | G14: =F14/E14 -> 0.33333333 | H14: =G14 -> 0.33333333 | I14: Data capturing was carried out around Kazaure axis, and could not proceed with other parts of the state as a result of untimely release of funds for the activities of the agency
A15: 5 | B15: Development and Implementation of the Agency's Strategic Plan | C15: Strategic Investment Plan Developed and Annually Reviewed | D15: 9 | E15: 1 | F15: 1 | G15: =F15/E15 -> 1 | H15: =G15 -> 1 | I15: InvestJigawa with support of FCDO LINKS developed a 5 year strategic plan (2021-2026) and recently developed a corporate plan to ensure effective implementation https://jigawastate.gov.ng/uploads/INVESTJIGAWA%20STRATEGIC%20PLAN.pdf
C16: Number of Initiatives in the Strategic Plan that are implemented' | D16: 10 | E16: 13 | F16: 10 | G16: =F16/E16 -> 0.76923077 | H16: =G16 -> 0.76923077 | I16: https://www.jigawastate.gov.ng/uploads/Jigawa%20state%20investment%20promotion%20agency%20corporate%20plan.pdf | J16: To check the website
A17: 6 | B17: Gagarawa Industrial Park (GIP) operational | C17: Number of phases of GIP completed | D17: 11 | E17: 1 | F17: 1 | G17: =F17/E17 -> 1 | H17: =G17 -> 1 | I17: Technical Committee for GIP was reconstituted, and the works for water, and electricity are not fully completed | J17: Provide the list of phase completed
C18: Number of plots at GIP allocated to investors | D18: 12 | E18: 38 | F18: 2 | G18: =F18/E18 -> 0.052631579 | H18: =G18 -> 0.052631579 | I18: Six (6) additional applications from interested investors were received and submitted for approval of Jigawa State government, but no action was taken | J18: What are the two beneficiaries
C19: Functional management team at GIP in place | D19: 13 | E19: 1 | F19: 0 | G19: =F19/E19 -> 0 | H19: =G19 -> 0 | I19: A memo was submitted by the Agency to His Excellency the Deputy governor on proposed management structure of the park
C20: Number of operational investments at GIP | D20: 14 | E20: 3 | F20: 0 | G20: =F20/E20 -> 0 | H20: =G20 -> 0 | I20: Nine (9) companies commenced constructions of fence of the plots and production of blocks
A21: 7 | B21: Private industrial park (PIP) established | C21: Number of private investors identified | D21: 15 | E21: 2 | F21: 0 | G21: Not Assessed | H21: NA | I21: The investors (Cydam Group) which initiially indicated an interest to establish a Private Industrial Park has withdrawn its interest to do so as a result of other projects that the company is presently engaged in other states | J21: Mention the investor
C22: Number of PIP approved | D22: 16 | E22: 1 | F22: 0 | G22: Not Assessed | H22: NA
C23: Number of PIP established | D23: 17 | E23: 1 | F23: 0 | G23: Not Assessed | H23: NA
A24: 8 | B24: Sustain and improve on the present effort of making Maigatari Export Processing Zone (MEPZ) a reality. * In collaboration with Ministry of Commerce, Industry, Cooperatives and TourismMEPZ fully occupied by investors | C24: Number of warehouses occupied by investors through the contribution of the Agency | D24: 18 | E24: 10 | F24: 4 | G24: =F24/E24 -> 0.4 | H24: =G24 -> 0.4 | I24: Cmttraex Limited occupied 2 prototype ware houses Starlink Ideal Limited occupied 2 warehouses at MEPZ
G25: Performance | I25: =AVERAGE(H7:H24) -> 0.59422517
A26: Commitment 2: To Fast track the realization of mobilized / pipeline investment proposals and support to the private sector for increased investments and job creation
A27: 9 | B27: Speeding Realzation of Pipiline Investment and Investment Proposals | C27: Number of targetted investor targetting events conducted | D27: 19 | E27: 2 | F27: 3 | G27: =F27/E27 -> 1.5 | H27: 1.01 | I27: The Nigeria Agribusiness Group (NABG) in collaboration with InvestJigawa hosted the Women and Young Farmers Agripreneurs Regional Conference (WAYFARC) in Jigawa State. The conference focused on sustainable and inclusive agricultural practices. (https://www.facebook.com/share/v/1DstrGU88t/) InvestJigawa in Discussion with 2 Investors attracted at the Nigeria Agribusiness Group (NABG) The JIWEN Trade Fair, organised by the Jigawa Women Entrepreneur Network (JIWEN) in collaboration with InvestJigawa, took place from 27th to 29th November, 2024, at the Aminu Kano Triangle in Dutse. This landmark event provided a platform for women entrepreneurs to showcase their products and services, nurture business collaborations, and connect with key stakeholders. (https://www.facebook.com/share/p/144rNquvqH/) | J27: To check the websites
C28: Number of Investments attracted as a result of targetted investor targetting event. | D28: 20 | E28: 1 | F28: 2 | G28: =F28/E28 -> 2 | H28: 1.01
C29: Number of hand-holding support provided to Investors | D29: 21 | E29: 2 | F29: 2 | G29: =F29/E29 -> 1 | H29: =G29 -> 1 | I29: Jigawa State Government intervening in the water channelisation project by GNA Limited with Federal Ministry of Water Resources. Also Defirst Flour Mill was supported in Gagarawa IP
G30: Performance | I30: =AVERAGE(H27:H29) -> 1.0066667
A31: Commitment 3: Continue to provide the necessary business environment and investment climate attractive to both Domestic and Foreign Investors; be among the topmost performers in the Nation’s Business Competitiveness Index
A32: 10 | B32: Improvement in PEBEC Sub-national Ease of Doing Business Survey indicators sustained (TO BE SCORED NEXT YEAR) | C32: Percentage Improvement in PEBEC's EoDB sub-national survey aggregate score | D32: 22 | E32: 10 | G32: Not Assessed | H32: NA | I32: The survey is conducted after two years and it is not applicable in 2024. However the Steering Committee was constituted to ensure implementation of reforms to enable the state improve in its performance in 2025.
G33: Performance | I33: NA
G34: Overall Performance | H34: =AVERAGE(H7:H33) -> 0.66296542

Sheet MoF-JIRS
A1: STATE INTERNAL REVENUE SERVICE
A2: FULL YEAR [JANUARY TO DECEMBER 2024] PERFORMANCE ASSESSMENT
A3: DELIVERY PERFORMANCE MANAGEMENT FRAMEWORK
A4: No. of OPs | B4: Expected Outputs for Delivering the Outcome Targets | C4: Output KPIs | D4: No. of RAs | E4: 2024 Target | F4: Jan. - Dec Results | G4: Performance | H4: Adjusted Performance | I4: Remarks / Evidences
A5: Commitment: Sustained Improvement in the Effeciency and Effectiveness in Internal Revenue Administration, Management and Performance
A6: 1 | B6: Improved Efficiency of Revenue Collection System | C6: Functionality of Tax Payers Database of the State Internal Revenue Service measured by Percentage Annual Increase in the Number of Tax Payers Captured in the Database (50% in Year 1, 50% in Year 2, 50% in Year 3 and 10% thereafter) | D6: 1 | E6: 0.5 | F6: =K6 -> 3.1454545 | G6: =F6/E6 -> 6.2909091 | H6: 1.01 | I6: The Data base is fully functional as at December 2024 (baeline 5.500) increased to 22,800 as of Dec. 2024 | J6: =22800-5500 -> 17300 | K6: =J6/5500 -> 3.1454545
C7: Number of New Taxpayers captured within the Database system | D7: 2 | E7: 14500 | F7: 17300 | G7: =F7/E7 -> 1.1931034 | H7: 1.01 | I7: Tax Payer Database said to increase from 5,500 in December 2023 to 22,800 as at December 2024 | J7: =F7-5500 -> 11800
C8: Number of revenue leakage points eliminated | D8: 3 | E8: 10 | F8: 8 | G8: =F8/E8 -> 0.8 | H8: =G8 -> 0.8 | I8: Five key leakage points that have been addressed include: a) Implementation of electronic formal registration using JIGITAS b) Streamlining the filing of returns. c) Adoption of an electronic assessment process. d) Expanding payment options for convenience. e) Strengthening taxpayer identification mechanisms. f) Strentening GRM system g) monitoring MDA targets (h) Tax Audit and investigation unit to check underpayment (i) electronic receipt was introduced to block the issue of fake receipt (j) introduction of consolidated invoice/demand notice to eliminate double
C9: % progress in automation of all revenue collection and accounting processes and systems | D9: 4 | E9: 0.3 | F9: 0.3 | G9: =F9/E9 -> 1 | H9: =G9 -> 1 | I9: Automation is done in stages - 5 stages as follows: 1. registration process 2. invoicing process 3. Payment process 4. Receipt 5. filing process
A10: 2 | B10: Improved Effeciency of Tax Policy and Revenue Administration | C10: Number of informal sector Artisan formed into skills clusters | D10: 5 | E10: 20 | F10: 34 | G10: =F10/E10 -> 1.7 | H10: 1.01 | I10: Informal sector artisans 850No. broken down into 34 clusters attached to apppropriate contractors
C11: % of informal sector clustered Artisans that are registered for sub-contracting with big contractors | D11: 6 | E11: 0.75 | F11: 1 | G11: =F11/E11 -> 1.3333333 | H11: 1.01 | I11: All the 34 clusters artisans were registered for subcontracting with big contractors
C12: Percentage of the registered informal sector artisans paired for sub-contracting with big contractors | D12: 7 | E12: 0.35 | F12: 0.35 | G12: =F12/E12 -> 1 | H12: =G12 -> 1 | I12: The state listed and clustered informal artisans and are being paired with big contractors, the 24 clusters are almost exusted
C13: Percentage of the registered informal sector artisans integrated into the Tax system | D13: 8 | E13: 1 | F13: 1 | G13: =F13/E13 -> 1 | H13: =G13 -> 1 | I13: The Jigawa Engagement and Enlightenment are presently on field caturing the informal artisan in to the JIGITAS
C14: Progress (%) achieved towards the review and approval State Tax Policy | D14: 9 | E14: 100 | F14: 80 | G14: =F14/E14 -> 0.8 | H14: =G14 -> 0.8 | I14: The Tax policy was reviewed yet to be vlalidated and approved
C15: Existence of Presumptive tax Framework | D15: 9 | E15: 1 | F15: 1 | G15: =F15/E15 -> 1 | H15: =G15 -> 1 | I15: Presumptive Tax Framework Developed
C16: Number of the markets that signs Tax-for-Service agreement for piloting | D16: 10 | E16: 2 | F16: 3 | G16: =F16/E16 -> 1.5 | H16: 1.01 | I16: Hadejia, DUtse and Shuwarin Markets
C17: Number of Tax for Service Initiatives Implemented | D17: 11 | E17: 6 | F17: 3 | G17: =F17/E17 -> 0.5 | H17: =G17 -> 0.5 | I17: Sanitation Facilities (Shuwarin), Toilet (Shuwarin, Hadjia and Dutse), Solar Project in Dutse
C18: Percentage of Grievance Received and Timely Addressed on Matters concerning Revenue Administration | D18: 12 | E18: 0.8 | F18: 0.6 | G18: =F18/E18 -> 0.75 | H18: =G18 -> 0.75 | I18: key concerns include Road Taxes administration, Filling returns, accessing the JIGITAS,
A19: 3 | B19: Improvement in IGR Collection | C19: Percentage of Annual Increase in Actual Outturn in State Taxes | D19: 13 | E19: 0.25 | F19: 2.09 | G19: =F19/E19 -> 8.36 | H19: 1.01 | I19: The 2023 actual was N16,483,046,204 while that of 2024 was N51,146,385,494.10 | J19: =51-16.5 -> 34.5
C20: Percentage of Annual Increase in Non-Public Sector PAYEE OnlyActual Outturn based on Published Budget Implementtion Reports | D20: 14 | E20: 0.2 | F20: 0.31 | G20: =F20/E20 -> 1.55 | H20: 1.01 | I20: the 2023 actual payee (non ublic sector) was 600,949,239.55 while that of 2024 as at december 2024 was 784,734,060.55 | J20: =J19/16.5 -> 2.0909091
C21: Percentage Increase in Actual IGR Collection by JSIR as measured by Outturns in Published Quarterly Budget Implementation Report or Annual Finaicial Statements | D21: 15 | E21: 0.1 | F21: -0.3 | G21: =F21/E21 -> -3 | H21: 0 | I21: The 2023 JIRS collection was 6,683,897,441.49, while that of 2024 was 4,676,195,800.80 - a reduction of over 300% indicating nonperformance | J21: =784.7-600.9 -> 183.8 | K21: =6684-4676 -> 2008
C22: Percentage Increase in Actual IGR Collection by all MDAs as measured by Outturns in Published Quarterly Budget Implementation Report or AFS in the case of full year report. | D22: 16 | E22: 0.2 | F22: 0.6 | G22: =F22/E22 -> 3 | H22: 1.01 | I22: The 2023 MDAs collections was 9,799,148,762.91 while that of 2024 was 46,470,189,693.80 | J22: =J21/600.9 -> 0.30587452 | K22: =K21/6684 -> 0.30041891
C23: Effeciency and Effectiveness of Revenue Monitorining Across MDAS as measured by Quarterly Published Reports by MoF & JSIRS | D23: 17 | E23: 2 | F23: 1 | G23: =F23/E23 -> 0.5 | H23: =G23 -> 0.5 | I23: considering the 60% increased MDA collections the monitoring was effective and efficient
C24: Progress in the Implementation of Presumptive Tax Regime | D24: 18 | E24: 0.5 | F24: 0.5 | G24: =F24/E24 -> 1 | H24: =G24 -> 1 | I24: The presuptive tax frramework was develoed with the governor
C25: Average Performance | H25: =AVERAGE(H6:H24) -> 0.86473684

Sheet 18. Min. of Women Affrs
A1: MINISTRY OF WOMEN AND SOCIAL DEVELOPMENT
A2: FULL YEAR [JANUARY TO DECEMBER 2024] PERFORMANCE ASSESSMENT
A3: Commitment: 1. Pursuit of targeted women empowerment programmes for job and employment creation to provide sustainable means of livelihoods and vulnarability among women
A4: Output No. | B4: Expected Outputs for Delivering the Outcome Targets | C4: Results | D4: Result No. | E4: 2024 Target | F4: Jan. - Dec Results | G4: Performance | H4: Adjusted Performance | I4: Remarks / Evidence
A5: 1 | B5: Existing Goat micro credit scheme for women expanded to cover the entire state and create an export market for the sale of goats | C5: Number of women that benefited in State sponsored goat breeding Programme | D5: 1 | E5: 1435 | F5: 1722 | G5: NA | H5: NA | I5: Confirm role of MoWA and obtain list of Beneficiaries | J5: List of beneficiaries by LG needed
A6: 2 | B6: Create a sustainable financing window to support business initiatives of both our young men and women that will make them self-reliant including the formation of Women Cooperatives and Entrepreneurship Affinity Groups | C6: Number of Advocacies, Training on Skills Development, Sensitization Programs & other Activities Conducted to promote women entrepreneurship | D6: 2 | E6: 10 | F6: 9 | G6: =F6/E6 -> 0.9 | H6: =G6 -> 0.9 | I6: These include Computer, Beads works, fashion & Design, leather Works, Liquid Soap Making, Cosmetics, Advocacies by NWDC, Persiable goods preservations and VVF Patiants | J6: List of activities, with attendance sheet including the date of each one needed
C7: Number of Women Cooperatives groups benefited the skills / entrepreneurship development training | D7: 3 | E7: 60 | F7: 25 | G7: =F7/E7 -> 0.41666667 | H7: =G7 -> 0.41666667 | I7: 25No. Women Cooperative Groups formed with ten members each | J7: List of women cooperative groups that benefited from the training is needed
C8: Number of Members of Women Cooperatives Groups and Entrepreneurship Affinity Groups that have accessed to Financing (loans, grants and start-up packages) | D8: 4 | E8: 300 | F8: 250 | G8: =F8/E8 -> 0.83333333 | H8: =G8 -> 0.83333333 | I8: Inclusive of Beneficiaries of JCARES Program | J8: To veriify
C9: Numer of Women Benefiting from Women Targeted Skill Acquisition Programs, Enterprenurship Grants/Loans or Start-up Kits | D9: 5 | E9: 7000 | F9: 11309 | G9: =F9/E9 -> 1.6155714 | H9: 1.01 | I9: Include JCARES Program Benefciairies and other regular women empowerment programs
G10: Performance | I10: =AVERAGE(H5:H9) -> 0.79
A12: Commitment 2: Evolve new social protection programs to achieve coverage of the life cycle including Pregnant Women, Children under the Age of 5, Orphans, People with Disability and the Aged-Population (maternal cash transfer and social security for people with the disability)
A13: 3 | B13: Establishment of Database of People with Disability, Orphans and other Vulnerable Groups for the purpose of Social Protection Intervention | C13: Number of Databsed Established | D13: 1 | E13: 5 | F13: 4 | G13: =F13/E13 -> 0.8 | H13: =G13 -> 0.8 | I13: Database of Orphans (65,607), PwDs (34,994) and Aged Persons (93,212) and Pregnant Women)Established with | J13: To verify the database established | K13: =65607+34994+93212+8610 -> 202423 | L13: =L14/K13 -> 0.050508094
C14: Percentage of People in the Database Enrolled in Social Protection Programs | D14: 2 | E14: 0.1 | F14: =(8610+1614)/202423 -> 0.050508094 | G14: =F14/E14 -> 0.50508094 | H14: =G14 -> 0.50508094 | I14: Beneficiea 8,610 maternal cash transfer and 1,614 pwDs) | J14: To verify from the database and the enrolment in SSP | K14: =30*287 -> 8610 | L14: =K14+1614 -> 10224
A15: 4 | B15: Review of Social Security Law for Disabled to Expand Scope and Increase Benefit Package | C15: Percentage of Progress achieved from Review of the Existing Law to its Accent by the Governor | D15: 3 | E15: 1 | F15: 0.5 | G15: 0.6 | H15: =G15 -> 0.6 | I15: Amended Law was not accented until May 2025 though it was sub,mitted to HoA much earlier. | K15: =K14/345000 -> 0.024956522
A16: 5 | B16: Introduce new Social Protection Interventions and welfare programs covering more vulnerable groups | C16: Number of New Social Protection and Welfare Programmes Introduced or Revised | D16: 4 | E16: 5 | F16: 2 | G16: =F16/E16 -> 0.4 | H16: =G16 -> 0.4 | I16: No new Social Protection Commenced. Old Aged Transfer and Support for Orphans still pending.However, two exisiring ones were reviewed (Maternal Cash Transfer and Social Security for Disabled) | K16: 20
C17: Percentage Increase Enrolment of Beneficiaries in Existing / New Social Protection Interventions | D17: 5 | E17: 0.1 | F17: 0.39 | G17: =F17/E17 -> 3.9 | H17: 1.01 | I17: Benefir Package and Coverage for Social Security Allowance for PwD and MCT was approved but only effected for the later which was increased from 20 to 30 women per ward. PwD still pending | J17: Encounter Register | M17: =296.5+135.6 -> 432.1 | N17: =538+135.6 -> 673.6 | O17: =N17-M17 -> 241.5 | P17: =O17/M17 -> 0.5588984
C18: Percentage Increase in Social Protection Spending | D18: 6 | E18: 0.1 | F18: 0.56 | G18: =F18/E18 -> 5.6 | H18: 1.01 | I18: Exp on MCT rose from N296,5 million in 2023 to N538 million in 2024 while Social Security remained static at N135.6 million | J18: Actual amount spent needed both for 2023 and 2024 to ascertained the % increase | K18: =20*287 -> 5740 | L18: 1614 | M18: =L18*12*7000 -> 135576000
A19: 6 | B19: Strengthen and expand the operations of the State Disability Trust Fund | C19: Percentage Increases in the Amount in the DTF | D19: 7 | E19: 0.1 | F19: 0.579 | G19: =F19/E19 -> 5.79 | H19: 1.01 | I19: Amount in DTF at the end of 2023 was about N44.5 million which rose to about N70.3 million in 2024 | J19: Actual amount raised in 2023 and 2024 are needed to ascertained the % increase | K19: 8610 | L19: 1614
C20: Percentage Increase in Expenditure Commitments and or Actual Funding of Activities covered by the DTF | D20: 8 | E20: 0.1 | F20: 0 | G20: =F20/E20 -> 0 | H20: =G20 -> 0 | I20: No Expenditure Yet from the Disability Trust Fund | J20: Is there no any expenditure commiitment from the DTF? | K20: =K19-K18 -> 2870 | L20: =L19-L18 -> 0
G21: Performance | I21: =AVERAGE(H18:H20) -> 0.67333333 | K21: =K18+L18 -> 7354
K22: =K19+L19 -> 10224
A23: Commitment 3: Evolve policies that specifically address concerns for the protection, survival and development of women and children as raised in the published “Situation Analysis” of Children in Jigawa State | K23: =K22-K21 -> 2870
A24: 7 | B24: Support the strengthening of Immunization, Vaccination, Safe Deliveries and Antenatal Care Services and Protection of Women Against Proven Harmful Traditional Practices | C24: Number of Programmes undertaken towards protection, survival and development of women and children (sensitization of hamrful traditional practices, birth registration, rape & violence against women, child trafficking, gender-based violence, etc) | D24: 1 | E24: 10 | F24: 3 | G24: =F24/E24 -> 0.3 | H24: =G24 -> 0.3 | I24: Sensitization during International Women's Day; Post-trauma sensitization for VVF and Victims of Rape, | J24: List of programmes needed
C25: Number of communities and Political wards covered with Safe Motherhood sensitization Programme | D25: 2 | E25: 287 | F25: 54 | G25: =F25/E25 -> 0.18815331 | H25: =G25 -> 0.18815331 | I25: 2 Communitis selected in each political wards Rankace and Unguwar Juda in Dutse LGA verified | J25: List of communities by LG is needed to verify
C26: Development and Implementation of State Gender Policy (% Progress) | D26: 3 | E26: 0.4 | F26: 0 | G26: =F26/E26 -> 0 | H26: =G26 -> 0 | J26: How?
G27: Performance | I27: =AVERAGE(H24:H26) -> 0.16271777
A29: Commitment 4 - Sustained Improvements in Social Welfare Institutions including quality care for inmates and improvement of structures and facilities
A30: 8 | B30: Improvement in Structure and facilities in Social Welfare Institutions | C30: Annual Budget Performance in the maintenance of structures, facilities and operational expenses of social welfare institutions | D30: 1 | E30: 1 | F30: 0.87 | G30: =F30/E30 -> 0.87 | H30: =G30 -> 0.87 | I30: Renovation of structures undertaken in K/Hausa and Birniwa and Kazaure totalling about N48.7 million against N55.8 million | J30: To be verified - From end of year 2024 budget performance report and the institutions where the maintenance of structures and facilities were made.
